Workbook

Sheet Master
A1: No | B1: Email | C1: Full name | D1: Người nhà | E1: Bus | F1: Room | G1: Gender | H1: Room Type
A2: 1 | B2: phamkhanh.tran@amaris.com | C2: =_xlfn.XLOOKUP(OfficeForms.Table[[#This Row],[Email]],Table2[Email],Table2[FullName],"") -> TRAN Pham Khanh Linh | E2: 1 | F2: 45 | G2: =IFERROR(_xlfn.XLOOKUP(OfficeForms.Table[[#This Row],[Email]],EE!C:C,EE!H:H,"Missing"),"Missing") -> Female | H2: DBL
A3: 2 | B3: thuytien.phamdo@amaris.com | C3: =_xlfn.XLOOKUP(OfficeForms.Table[[#This Row],[Email]],Table2[Email],Table2[FullName],"") -> PHAM Do Thuy Tien | E3: 1 | F3: 1 | G3: =IFERROR(_xlfn.XLOOKUP(OfficeForms.Table[[#This Row],[Email]],EE!C:C,EE!H:H,"Missing"),"Missing") -> Female | H3: DBL
A4: 3 | B4: hoangha.nguyen@amaris.com | C4: =_xlfn.XLOOKUP(OfficeForms.Table[[#This Row],[Email]],Table2[Email],Table2[FullName],"") -> NGUYEN Hoang Ha Quyen | E4: 1 | F4: 2 | G4: =IFERROR(_xlfn.XLOOKUP(OfficeForms.Table[[#This Row],[Email]],EE!C:C,EE!H:H,"Missing"),"Missing") -> Female | H4: DBL
A5: 4 | B5: thientrang.doan@amaris.com | C5: =_xlfn.XLOOKUP(OfficeForms.Table[[#This Row],[Email]],Table2[Email],Table2[FullName],"") -> DOAN Thien Trang | E5: 1 | F5: 2 | G5: =IFERROR(_xlfn.XLOOKUP(OfficeForms.Table[[#This Row],[Email]],EE!C:C,EE!H:H,"Missing"),"Missing") -> Female | H5: DBL
A6: 5 | B6: uhonguyenhong@amaris.com | C6: =_xlfn.XLOOKUP(OfficeForms.Table[[#This Row],[Email]],Table2[Email],Table2[FullName],"") -> HO Nguyen Hong Uyen | E6: 1 | F6: 85 | G6: =IFERROR(_xlfn.XLOOKUP(OfficeForms.Table[[#This Row],[Email]],EE!C:C,EE!H:H,"Missing"),"Missing") -> Female | H6: DBL
A7: 6 | B7: pha1@amaris.com | C7: =_xlfn.XLOOKUP(OfficeForms.Table[[#This Row],[Email]],Table2[Email],Table2[FullName],"") -> HA Phuong Thao | E7: 1 | F7: 88 | G7: =IFERROR(_xlfn.XLOOKUP(OfficeForms.Table[[#This Row],[Email]],EE!C:C,EE!H:H,"Missing"),"Missing") -> Female | H7: DBL
A8: 7 | B8: hvu3@amaris.com | C8: =_xlfn.XLOOKUP(OfficeForms.Table[[#This Row],[Email]],Table2[Email],Table2[FullName],"") -> VU Thanh Hang | E8: 1 | F8: 85 | G8: =IFERROR(_xlfn.XLOOKUP(OfficeForms.Table[[#This Row],[Email]],EE!C:C,EE!H:H,"Missing"),"Missing") -> Female | H8: DBL
A9: 8 | B9: cao.minh@amaris.com | C9: =_xlfn.XLOOKUP(OfficeForms.Table[[#This Row],[Email]],Table2[Email],Table2[FullName],"") -> CAO Duc Minh | E9: 1 | F9: 4 | G9: =IFERROR(_xlfn.XLOOKUP(OfficeForms.Table[[#This Row],[Email]],EE!C:C,EE!H:H,"Missing"),"Missing") -> Male | H9: TWN
A10: 9 | B10: hoangtu.la@amaris.com | C10: =_xlfn.XLOOKUP(OfficeForms.Table[[#This Row],[Email]],Table2[Email],Table2[FullName],"") -> LA Hoang Tu | E10: 1 | F10: 4 | G10: =IFERROR(_xlfn.XLOOKUP(OfficeForms.Table[[#This Row],[Email]],EE!C:C,EE!H:H,"Missing"),"Missing") -> Male | H10: TWN
A11: 10 | B11: trungnghia.cao@amaris.com | C11: =_xlfn.XLOOKUP(OfficeForms.Table[[#This Row],[Email]],Table2[Email],Table2[FullName],"") -> CAO Trung Nghia | E11: 1 | F11: 5 | G11: =IFERROR(_xlfn.XLOOKUP(OfficeForms.Table[[#This Row],[Email]],EE!C:C,EE!H:H,"Missing"),"Missing") -> Male | H11: TWN
A12: 11 | B12: minhthuan.le@amaris.com | C12: =_xlfn.XLOOKUP(OfficeForms.Table[[#This Row],[Email]],Table2[Email],Table2[FullName],"") -> LE Minh Thuan | E12: 1 | F12: 3 | G12: =IFERROR(_xlfn.XLOOKUP(OfficeForms.Table[[#This Row],[Email]],EE!C:C,EE!H:H,"Missing"),"Missing") -> Male | H12: TWN
A13: 12 | B13: thanhthuan.nguyenvan@amaris.com | C13: =_xlfn.XLOOKUP(OfficeForms.Table[[#This Row],[Email]],Table2[Email],Table2[FullName],"") -> NGUYEN Van Thanh Thuan | E13: 1 | F13: 3 | G13: =IFERROR(_xlfn.XLOOKUP(OfficeForms.Table[[#This Row],[Email]],EE!C:C,EE!H:H,"Missing"),"Missing") -> Male | H13: TWN
... A30: 29 | B30: thanhson.nguyen@amaris.com | C30: =_xlfn.XLOOKUP(OfficeForms.Table[[#This Row],[Email]],Table2[Email],Table2[FullName],"") -> NGUYEN Thanh Son | E30: 1 | F30: 10 | G30: =IFERROR(_xlfn.XLOOKUP(OfficeForms.Table[[#This Row],[Email]],EE!C:C,EE!H:H,"Missing"),"Missing") -> Male | H30: TWN
A31: 30 | B31: nguyen.tai3@amaris.com | C31: =_xlfn.XLOOKUP(OfficeForms.Table[[#This Row],[Email]],Table2[Email],Table2[FullName],"") -> NGUYEN Thanh Tai | D31: 1. Nguyen Thu Huyen - Female - 1991 - TBD 2. Nguyen Kha Han - Female - 2017 - TBD | E31: 1 | F31: 73 | G31: =IFERROR(_xlfn.XLOOKUP(OfficeForms.Table[[#This Row],[Email]],EE!C:C,EE!H:H,"Missing"),"Missing") -> Male | H31: DBL
A32: 31 | B32: vanthanh.khuat@amaris.com | C32: =_xlfn.XLOOKUP(OfficeForms.Table[[#This Row],[Email]],Table2[Email],Table2[FullName],"") -> KHUAT Van Thanh Danh | E32: 1 | F32: 12 | G32: =IFERROR(_xlfn.XLOOKUP(OfficeForms.Table[[#This Row],[Email]],EE!C:C,EE!H:H,"Missing"),"Missing") -> Male | H32: TWN
A33: 32 | B33: quangnien.nguyen@amaris.com | C33: =_xlfn.XLOOKUP(OfficeForms.Table[[#This Row],[Email]],Table2[Email],Table2[FullName],"") -> NGUYEN Quang Nien | E33: 1 | F33: 15 | G33: =IFERROR(_xlfn.XLOOKUP(OfficeForms.Table[[#This Row],[Email]],EE!C:C,EE!H:H,"Missing"),"Missing") -> Male | H33: TWN
A34: 33 | B34: thanhphuoc.le@amaris.com | C34: =_xlfn.XLOOKUP(OfficeForms.Table[[#This Row],[Email]],Table2[Email],Table2[FullName],"") -> LE Thanh Phuoc | E34: 1 | F34: 11 | G34: =IFERROR(_xlfn.XLOOKUP(OfficeForms.Table[[#This Row],[Email]],EE!C:C,EE!H:H,"Missing"),"Missing") -> Male | H34: TWN
A35: 34 | B35: nnguyen9@amaris.com | C35: =_xlfn.XLOOKUP(OfficeForms.Table[[#This Row],[Email]],Table2[Email],Table2[FullName],"") -> NGUYEN Tien Nam | E35: 8 | F35: 110 | G35: =IFERROR(_xlfn.XLOOKUP(OfficeForms.Table[[#This Row],[Email]],EE!C:C,EE!H:H,"Missing"),"Missing") -> Male | H35: TWN
A36: 35 | B36: congdanh.bui@amaris.com | C36: =_xlfn.XLOOKUP(OfficeForms.Table[[#This Row],[Email]],Table2[Email],Table2[FullName],"") -> BUI Cong Danh | E36: 1 | F36: 15 | G36: =IFERROR(_xlfn.XLOOKUP(OfficeForms.Table[[#This Row],[Email]],EE!C:C,EE!H:H,"Missing"),"Missing") -> Male | H36: TWN
A37: 36 | B37: huynhchi.vo@amaris.com | C37: =_xlfn.XLOOKUP(OfficeForms.Table[[#This Row],[Email]],Table2[Email],Table2[FullName],"") -> VO Huynh Chi Tin | E37: 1 | F37: 16 | G37: =IFERROR(_xlfn.XLOOKUP(OfficeForms.Table[[#This Row],[Email]],EE!C:C,EE!H:H,"Missing"),"Missing") -> Male | H37: TWN
A38: 37 | B38: quangtrung.do@amaris.com | C38: =_xlfn.XLOOKUP(OfficeForms.Table[[#This Row],[Email]],Table2[Email],Table2[FullName],"") -> DO Quang Trung | E38: 1 | F38: 16 | G38: =IFERROR(_xlfn.XLOOKUP(OfficeForms.Table[[#This Row],[Email]],EE!C:C,EE!H:H,"Missing"),"Missing") -> Male | H38: TWN
A39: 38 | B39: vantrien.dang@amaris.com | C39: =_xlfn.XLOOKUP(OfficeForms.Table[[#This Row],[Email]],Table2[Email],Table2[FullName],"") -> DANG Van Trien | E39: 2 | F39: 65 | G39: =IFERROR(_xlfn.XLOOKUP(OfficeForms.Table[[#This Row],[Email]],EE!C:C,EE!H:H,"Missing"),"Missing") -> Male | H39: TWN
A40: 39 | B40: thanhdat.nguyen@amaris.com | C40: =_xlfn.XLOOKUP(OfficeForms.Table[[#This Row],[Email]],Table2[Email],Table2[FullName],"") -> NGUYEN Thanh Dat | E40: 2 | F40: 66 | G40: =IFERROR(_xlfn.XLOOKUP(OfficeForms.Table[[#This Row],[Email]],EE!C:C,EE!H:H,"Missing"),"Missing") -> Male | H40: TWN
A41: 40 | B41: songtoan.vu@amaris.com | C41: =_xlfn.XLOOKUP(OfficeForms.Table[[#This Row],[Email]],Table2[Email],Table2[FullName],"") -> VU Song Toan | E41: 2 | F41: 66 | G41: =IFERROR(_xlfn.XLOOKUP(OfficeForms.Table[[#This Row],[Email]],EE!C:C,EE!H:H,"Missing"),"Missing") -> Male | H41: TWN
A42: 41 | B42: quangtin.tran@amaris.com | C42: =_xlfn.XLOOKUP(OfficeForms.Table[[#This Row],[Email]],Table2[Email],Table2[FullName],"") -> TRAN Quang Tin | E42: 2 | F42: 67 | G42: =IFERROR(_xlfn.XLOOKUP(OfficeForms.Table[[#This Row],[Email]],EE!C:C,EE!H:H,"Missing"),"Missing") -> Male | H42: TWN
A43: 42 | B43: tuongduy.vo@amaris.com | C43: =_xlfn.XLOOKUP(OfficeForms.Table[[#This Row],[Email]],Table2[Email],Table2[FullName],"") -> VO Tuong Duy | E43: 2 | F43: 67 | G43: =IFERROR(_xlfn.XLOOKUP(OfficeForms.Table[[#This Row],[Email]],EE!C:C,EE!H:H,"Missing"),"Missing") -> Male | H43: TWN
... A91: 90 | B91: minhtan.tran1@amaris.com | C91: =_xlfn.XLOOKUP(OfficeForms.Table[[#This Row],[Email]],Table2[Email],Table2[FullName],"") -> TRAN Minh Tan | E91: 3 | F91: 40 | G91: =IFERROR(_xlfn.XLOOKUP(OfficeForms.Table[[#This Row],[Email]],EE!C:C,EE!H:H,"Missing"),"Missing") -> Male | H91: TWN
A92: 91 | B92: nguyen.tuananh@amaris.com | C92: =_xlfn.XLOOKUP(OfficeForms.Table[[#This Row],[Email]],Table2[Email],Table2[FullName],"") -> NGUYEN Anh Tuan - Tl | D92: 1. TRẦN THỊ KIM THUỶ - 07/10/1998 - 079198004873 2. NGUYỄN NGỌC KIM ANH - 04/09/2022 - 079322018996 3. NGUYỄN NGỌC TUỆ NHI - 01/03/2024 - 079324006070 | E92: 3 | F92: 74 | G92: =IFERROR(_xlfn.XLOOKUP(OfficeForms.Table[[#This Row],[Email]],EE!C:C,EE!H:H,"Missing"),"Missing") -> Male | H92: TWN
A93: 92 | B93: nhamquy.tran@amaris.com | C93: =_xlfn.XLOOKUP(OfficeForms.Table[[#This Row],[Email]],Table2[Email],Table2[FullName],"") -> TRAN Nham Quy | D93: Lam Vi Phuong - Female - 25/05/1994 - 084194007540 | E93: 3 | F93: 72 | G93: =IFERROR(_xlfn.XLOOKUP(OfficeForms.Table[[#This Row],[Email]],EE!C:C,EE!H:H,"Missing"),"Missing") -> Male | H93: DBL
A94: 93 | B94: thuong.trinhxuan@amaris.com | C94: =_xlfn.XLOOKUP(OfficeForms.Table[[#This Row],[Email]],Table2[Email],Table2[FullName],"") -> TRINH Xuan Thuong | E94: 4 | F94: 57 | G94: =IFERROR(_xlfn.XLOOKUP(OfficeForms.Table[[#This Row],[Email]],EE!C:C,EE!H:H,"Missing"),"Missing") -> Male | H94: TWN
A95: 94 | B95: nguyen.huyhoang@amaris.com | C95: =_xlfn.XLOOKUP(OfficeForms.Table[[#This Row],[Email]],Table2[Email],Table2[FullName],"") -> NGUYEN Huy Hoang | D95: 1. Lương Thị Lưu - Female - 06/03/1993 - 040193036578 2. Nguyễn Lương Hoàng Yến - Female - 19/10/2021 - 086321006062 3. Nguyễn Lương Thanh Thảo - Female - 06/03/2024 - 086324001119 | E95: 3 | F95: 75 | G95: =IFERROR(_xlfn.XLOOKUP(OfficeForms.Table[[#This Row],[Email]],EE!C:C,EE!H:H,"Missing"),"Missing") -> Male | H95: TWN
A96: 95 | B96: vanhieu.nguyen@amaris.com | C96: =_xlfn.XLOOKUP(OfficeForms.Table[[#This Row],[Email]],Table2[Email],Table2[FullName],"") -> NGUYEN Van Hieu | E96: 3 | F96: 41 | G96: =IFERROR(_xlfn.XLOOKUP(OfficeForms.Table[[#This Row],[Email]],EE!C:C,EE!H:H,"Missing"),"Missing") -> Male | H96: TWN
A97: 96 | B97: kimgia.nguyen@amaris.com | C97: =_xlfn.XLOOKUP(OfficeForms.Table[[#This Row],[Email]],Table2[Email],Table2[FullName],"") -> NGUYEN Kim Gia Huy | E97: 3 | F97: 41 | G97: =IFERROR(_xlfn.XLOOKUP(OfficeForms.Table[[#This Row],[Email]],EE!C:C,EE!H:H,"Missing"),"Missing") -> Male | H97: TWN
A98: 97 | B98: congquan.pham@amaris.com | C98: =_xlfn.XLOOKUP(OfficeForms.Table[[#This Row],[Email]],Table2[Email],Table2[FullName],"") -> PHAM Cong Quan | D98: 1. Ung Thụy Song Quỳnh - Female - 11/11/1995 - 049195000151 2. Phạm Công Quang - Male - 26/05/2024 - 049224004390 | E98: 3 | F98: 76 | G98: =IFERROR(_xlfn.XLOOKUP(OfficeForms.Table[[#This Row],[Email]],EE!C:C,EE!H:H,"Missing"),"Missing") -> Male | H98: DBL
A99: 98 | B99: thanhxuan.bui@amaris.com | C99: =_xlfn.XLOOKUP(OfficeForms.Table[[#This Row],[Email]],Table2[Email],Table2[FullName],"") -> BUI Thanh Xuan | E99: 3 | F99: 42 | G99: =IFERROR(_xlfn.XLOOKUP(OfficeForms.Table[[#This Row],[Email]],EE!C:C,EE!H:H,"Missing"),"Missing") -> Male | H99: TWN
A100: 99 | B100: thiphuong.vu@amaris.com | C100: =_xlfn.XLOOKUP(OfficeForms.Table[[#This Row],[Email]],Table2[Email],Table2[FullName],"") -> VU Thi Phuong Thao | D100: Cao Thi Truc Duyen - Female - 15/06/1997 - 083197002767 | E100: 3 | F100: 43 | G100: =IFERROR(_xlfn.XLOOKUP(OfficeForms.Table[[#This Row],[Email]],EE!C:C,EE!H:H,"Missing"),"Missing") -> Female | H100: DBL
A101: 100 | B101: vantinh.pham@amaris.com | C101: =_xlfn.XLOOKUP(OfficeForms.Table[[#This Row],[Email]],Table2[Email],Table2[FullName],"") -> PHAM Van Tinh | E101: 3 | F101: 42 | G101: =IFERROR(_xlfn.XLOOKUP(OfficeForms.Table[[#This Row],[Email]],EE!C:C,EE!H:H,"Missing"),"Missing") -> Male | H101: TWN
A102: 101 | B102: tuan.vancong@amaris.com | C102: =_xlfn.XLOOKUP(OfficeForms.Table[[#This Row],[Email]],Table2[Email],Table2[FullName],"") -> VAN Cong Tuan | D102: Nguyen Thi Viet Le - Female - 20/11/1997 - 049197010026 | E102: 3 | F102: 71 | G102: =IFERROR(_xlfn.XLOOKUP(OfficeForms.Table[[#This Row],[Email]],EE!C:C,EE!H:H,"Missing"),"Missing") -> Male | H102: DBL
A103: 102 | B103: thanhtrung.nguyen@amaris.com | C103: =_xlfn.XLOOKUP(OfficeForms.Table[[#This Row],[Email]],Table2[Email],Table2[FullName],"") -> NGUYEN Thanh Trung | E103: 4 | F103: 46 | G103: =IFERROR(_xlfn.XLOOKUP(OfficeForms.Table[[#This Row],[Email]],EE!C:C,EE!H:H,"Missing"),"Missing") -> Male | H103: TWN
A104: 103 | B104: nguyenngoc.nguyensy@amaris.com | C104: =_xlfn.XLOOKUP(OfficeForms.Table[[#This Row],[Email]],Table2[Email],Table2[FullName],"") -> NGUYEN SY Nguyen Ngoc | E104: 4 | F104: 46 | G104: =IFERROR(_xlfn.XLOOKUP(OfficeForms.Table[[#This Row],[Email]],EE!C:C,EE!H:H,"Missing"),"Missing") -> Male | H104: TWN
A105: 104 | B105: anhquoc.pham@amaris.com | C105: =_xlfn.XLOOKUP(OfficeForms.Table[[#This Row],[Email]],Table2[Email],Table2[FullName],"") -> PHAM Anh Quoc | E105: 4 | F105: 47 | G105: =IFERROR(_xlfn.XLOOKUP(OfficeForms.Table[[#This Row],[Email]],EE!C:C,EE!H:H,"Missing"),"Missing") -> Male | H105: TWN
A106: 105 | B106: haibinh.dang@amaris.com | C106: =_xlfn.XLOOKUP(OfficeForms.Table[[#This Row],[Email]],Table2[Email],Table2[FullName],"") -> DANG Hai Binh | E106: 4 | F106: 47 | G106: =IFERROR(_xlfn.XLOOKUP(OfficeForms.Table[[#This Row],[Email]],EE!C:C,EE!H:H,"Missing"),"Missing") -> Male | H106: TWN
A107: 106 | B107: trungtin.thai@amaris.com | C107: =_xlfn.XLOOKUP(OfficeForms.Table[[#This Row],[Email]],Table2[Email],Table2[FullName],"") -> THAI Trung Tin | E107: 4 | F107: 48 | G107: =IFERROR(_xlfn.XLOOKUP(OfficeForms.Table[[#This Row],[Email]],EE!C:C,EE!H:H,"Missing"),"Missing") -> Male | H107: TWN
A108: 107 | B108: minhnhat.dang@amaris.com | C108: =_xlfn.XLOOKUP(OfficeForms.Table[[#This Row],[Email]],Table2[Email],Table2[FullName],"") -> DANG MINH Nhat | E108: 4 | F108: 48 | G108: =IFERROR(_xlfn.XLOOKUP(OfficeForms.Table[[#This Row],[Email]],EE!C:C,EE!H:H,"Missing"),"Missing") -> Male | H108: TWN
A109: 108 | B109: kimnha.dao@amaris.com | C109: =_xlfn.XLOOKUP(OfficeForms.Table[[#This Row],[Email]],Table2[Email],Table2[FullName],"") -> DAO Kim Nha | E109: 4 | F109: 89 | G109: =IFERROR(_xlfn.XLOOKUP(OfficeForms.Table[[#This Row],[Email]],EE!C:C,EE!H:H,"Missing"),"Missing") -> Female | H109: DBL
A110: 109 | B110: pnguyen4@amaris.com | C110: =_xlfn.XLOOKUP(OfficeForms.Table[[#This Row],[Email]],Table2[Email],Table2[FullName],"") -> NGUYEN Thi Minh Phuong | E110: 4 | F110: 86 | G110: =IFERROR(_xlfn.XLOOKUP(OfficeForms.Table[[#This Row],[Email]],EE!C:C,EE!H:H,"Missing"),"Missing") -> Female | H110: DBL
A111: 110 | B111: chienhao.cao@amaris.com | C111: =_xlfn.XLOOKUP(OfficeForms.Table[[#This Row],[Email]],Table2[Email],Table2[FullName],"") -> CAO Chien Hao | E111: 4 | F111: 50 | G111: =IFERROR(_xlfn.XLOOKUP(OfficeForms.Table[[#This Row],[Email]],EE!C:C,EE!H:H,"Missing"),"Missing") -> Male | H111: TWN
A112: 111 | B112: donhat.pham@amaris.com | C112: =_xlfn.XLOOKUP(OfficeForms.Table[[#This Row],[Email]],Table2[Email],Table2[FullName],"") -> PHAM Do Nhat Minh | E112: 4 | F112: 50 | G112: =IFERROR(_xlfn.XLOOKUP(OfficeForms.Table[[#This Row],[Email]],EE!C:C,EE!H:H,"Missing"),"Missing") -> Male | H112: TWN
A113: 112 | B113: duyhanh.le@amaris.com | C113: =_xlfn.XLOOKUP(OfficeForms.Table[[#This Row],[Email]],Table2[Email],Table2[FullName],"") -> LE Duy Hanh | E113: 4 | F113: 51 | G113: =IFERROR(_xlfn.XLOOKUP(OfficeForms.Table[[#This Row],[Email]],EE!C:C,EE!H:H,"Missing"),"Missing") -> Male | H113: TWN
A114: 113 | B114: huuthinh.nguyen@amaris.com | C114: =_xlfn.XLOOKUP(OfficeForms.Table[[#This Row],[Email]],Table2[Email],Table2[FullName],"") -> NGUYEN Huu Thinh | E114: 4 | F114: 51 | G114: =IFERROR(_xlfn.XLOOKUP(OfficeForms.Table[[#This Row],[Email]],EE!C:C,EE!H:H,"Missing"),"Missing") -> Male | H114: TWN
... A121: 120 | B121: nguyen.phamhuukhoi@amaris.com | C121: =_xlfn.XLOOKUP(OfficeForms.Table[[#This Row],[Email]],Table2[Email],Table2[FullName],"") -> PHAM Huu Khoi Nguyen | E121: 4 | F121: 55 | G121: =IFERROR(_xlfn.XLOOKUP(OfficeForms.Table[[#This Row],[Email]],EE!C:C,EE!H:H,"Missing"),"Missing") -> Male | H121: TWN
A122: 121 | B122: nhattan.tranhuynh@amaris.com | C122: =_xlfn.XLOOKUP(OfficeForms.Table[[#This Row],[Email]],Table2[Email],Table2[FullName],"") -> TRAN Huynh Nhat Tan | D122: Nguyễn Thị Bích Duyên - Female - 05/08/1995 | E122: 4 | F122: 70 | G122: =IFERROR(_xlfn.XLOOKUP(OfficeForms.Table[[#This Row],[Email]],EE!C:C,EE!H:H,"Missing"),"Missing") -> Male | H122: DBL
A123: 122 | B123: khanhlinh.dangngoc@amaris.com | C123: =_xlfn.XLOOKUP(OfficeForms.Table[[#This Row],[Email]],Table2[Email],Table2[FullName],"") -> DANG Ngoc Khanh Linh | E123: 4 | F123: 62 | G123: =IFERROR(_xlfn.XLOOKUP(OfficeForms.Table[[#This Row],[Email]],EE!C:C,EE!H:H,"Missing"),"Missing") -> Female | H123: DBL
A124: 123 | B124: phuocson.le@amaris.com | C124: =_xlfn.XLOOKUP(OfficeForms.Table[[#This Row],[Email]],Table2[Email],Table2[FullName],"") -> LE Phuoc Son | E124: 3 | F124: 40 | G124: =IFERROR(_xlfn.XLOOKUP(OfficeForms.Table[[#This Row],[Email]],EE!C:C,EE!H:H,"Missing"),"Missing") -> Male | H124: TWN
A125: 124 | B125: thanhtung.le@amaris.com | C125: =_xlfn.XLOOKUP(OfficeForms.Table[[#This Row],[Email]],Table2[Email],Table2[FullName],"") -> LE Thanh Tung | E125: 4 | F125: 57 | G125: =IFERROR(_xlfn.XLOOKUP(OfficeForms.Table[[#This Row],[Email]],EE!C:C,EE!H:H,"Missing"),"Missing") -> Male | H125: TWN
A126: 125 | B126: vuduy.dinh@amaris.com | C126: =_xlfn.XLOOKUP(OfficeForms.Table[[#This Row],[Email]],Table2[Email],Table2[FullName],"") -> DINH Vu Duy | E126: 4 | F126: 58 | G126: =IFERROR(_xlfn.XLOOKUP(OfficeForms.Table[[#This Row],[Email]],EE!C:C,EE!H:H,"Missing"),"Missing") -> Male | H126: TWN
A127: 126 | B127: tunglam.ngo@amaris.com | C127: =_xlfn.XLOOKUP(OfficeForms.Table[[#This Row],[Email]],Table2[Email],Table2[FullName],"") -> NGO Tung Lam | E127: 4 | F127: 59 | G127: =IFERROR(_xlfn.XLOOKUP(OfficeForms.Table[[#This Row],[Email]],EE!C:C,EE!H:H,"Missing"),"Missing") -> Male | H127: TWN
A128: 127 | B128: chitam.nguyenle@amaris.com | C128: =_xlfn.XLOOKUP(OfficeForms.Table[[#This Row],[Email]],Table2[Email],Table2[FullName],"") -> NGUYEN LE Chi Tam | E128: 3 | F128: 37 | G128: =IFERROR(_xlfn.XLOOKUP(OfficeForms.Table[[#This Row],[Email]],EE!C:C,EE!H:H,"Missing"),"Missing") -> Male | H128: TWN
A129: 128 | B129: qtran5@amaris.com | C129: =_xlfn.XLOOKUP(OfficeForms.Table[[#This Row],[Email]],Table2[Email],Table2[FullName],"") -> Trần Quỳnh Anh | E129: 3 | F129: 61 | G129: =IFERROR(_xlfn.XLOOKUP(OfficeForms.Table[[#This Row],[Email]],EE!C:C,EE!H:H,"Missing"),"Missing") -> Female | H129: DBL
A130: 129 | B130: sang.truongvan@amaris.com | C130: =_xlfn.XLOOKUP(OfficeForms.Table[[#This Row],[Email]],Table2[Email],Table2[FullName],"") -> TRUONG Van Sang | E130: 4 | F130: 59 | G130: =IFERROR(_xlfn.XLOOKUP(OfficeForms.Table[[#This Row],[Email]],EE!C:C,EE!H:H,"Missing"),"Missing") -> Male | H130: TWN
A131: 130 | B131: baongoc.nguyen@amaris.com | C131: =_xlfn.XLOOKUP(OfficeForms.Table[[#This Row],[Email]],Table2[Email],Table2[FullName],"") -> NGUYEN Bao Ngoc | E131: 4 | F131: 69 | G131: =IFERROR(_xlfn.XLOOKUP(OfficeForms.Table[[#This Row],[Email]],EE!C:C,EE!H:H,"Missing"),"Missing") -> Female | H131: DBL
A132: 131 | B132: pham.trungkien@amaris.com | C132: =_xlfn.XLOOKUP(OfficeForms.Table[[#This Row],[Email]],Table2[Email],Table2[FullName],"") -> PHAM Trung Kien | D132: TRẦN DIỆP HUY - 046098011753 - 0766669006 - Male - 07/01/1998 | E132: 4 | F132: 49 | G132: =IFERROR(_xlfn.XLOOKUP(OfficeForms.Table[[#This Row],[Email]],EE!C:C,EE!H:H,"Missing"),"Missing") -> Male | H132: DBL
A133: 132 | B133: ket.vovan@amaris.com | C133: =_xlfn.XLOOKUP(OfficeForms.Table[[#This Row],[Email]],Table2[Email],Table2[FullName],"") -> VO Van Ket | E133: 4 | F133: 54 | G133: =IFERROR(_xlfn.XLOOKUP(OfficeForms.Table[[#This Row],[Email]],EE!C:C,EE!H:H,"Missing"),"Missing") -> Male | H133: TWN
A134: 133 | B134: vuphuong.nguyen@amaris.com | C134: =_xlfn.XLOOKUP(OfficeForms.Table[[#This Row],[Email]],Table2[Email],Table2[FullName],"") -> NGUYEN Vu Phuong | E134: 4 | F134: 56 | G134: =IFERROR(_xlfn.XLOOKUP(OfficeForms.Table[[#This Row],[Email]],EE!C:C,EE!H:H,"Missing"),"Missing") -> Male | H134: TWN
A135: 134 | B135: nducquy@amaris.com | C135: =_xlfn.XLOOKUP(OfficeForms.Table[[#This Row],[Email]],Table2[Email],Table2[FullName],"") -> NGUYEN Duc Quy | E135: 4 | F135: 68 | G135: =IFERROR(_xlfn.XLOOKUP(OfficeForms.Table[[#This Row],[Email]],EE!C:C,EE!H:H,"Missing"),"Missing") -> Male | H135: DBL
A136: 135 | B136: lle@mantu.com | C136: =_xlfn.XLOOKUP(OfficeForms.Table[[#This Row],[Email]],Table2[Email],Table2[FullName],"") -> LE Lan Vy | E136: 5 | F136: 101 | G136: =IFERROR(_xlfn.XLOOKUP(OfficeForms.Table[[#This Row],[Email]],EE!C:C,EE!H:H,"Missing"),"Missing") -> Female | H136: DBL
A137: 136 | B137: hpham1@amaris.com | C137: =_xlfn.XLOOKUP(OfficeForms.Table[[#This Row],[Email]],Table2[Email],Table2[FullName],"") -> PHAM Hoang Mai Quyen | E137: 5 | F137: 98 | G137: =IFERROR(_xlfn.XLOOKUP(OfficeForms.Table[[#This Row],[Email]],EE!C:C,EE!H:H,"Missing"),"Missing") -> Female | H137: DBL
A138: 137 | B138: xle@amaris.com | C138: =_xlfn.XLOOKUP(OfficeForms.Table[[#This Row],[Email]],Table2[Email],Table2[FullName],"") -> LE Xuan Tung | E138: 5 | F138: 109 | G138: =IFERROR(_xlfn.XLOOKUP(OfficeForms.Table[[#This Row],[Email]],EE!C:C,EE!H:H,"Missing"),"Missing") -> Male | H138: TWN
A139: 138 | B139: hnguyen13@amaris.com | C139: =_xlfn.XLOOKUP(OfficeForms.Table[[#This Row],[Email]],Table2[Email],Table2[FullName],"") -> NGUYEN Ho Ngoc Tran | E139: 5 | F139: 98 | G139: =IFERROR(_xlfn.XLOOKUP(OfficeForms.Table[[#This Row],[Email]],EE!C:C,EE!H:H,"Missing"),"Missing") -> Female | H139: DBL
A140: 139 | B140: tvo4@amaris.com | C140: =_xlfn.XLOOKUP(OfficeForms.Table[[#This Row],[Email]],Table2[Email],Table2[FullName],"") -> VO Tran Phuong Nga | E140: 5 | F140: 97 | G140: =IFERROR(_xlfn.XLOOKUP(OfficeForms.Table[[#This Row],[Email]],EE!C:C,EE!H:H,"Missing"),"Missing") -> Female | H140: DBL
A141: 140 | B141: tnguyen38@amaris.com | C141: =_xlfn.XLOOKUP(OfficeForms.Table[[#This Row],[Email]],Table2[Email],Table2[FullName],"") -> NGUYEN Thi Thanh Thao | E141: 5 | F141: 97 | G141: =IFERROR(_xlfn.XLOOKUP(OfficeForms.Table[[#This Row],[Email]],EE!C:C,EE!H:H,"Missing"),"Missing") -> Female | H141: DBL
A142: 141 | B142: tle8@amaris.com | C142: =_xlfn.XLOOKUP(OfficeForms.Table[[#This Row],[Email]],Table2[Email],Table2[FullName],"") -> LE Thi Tu Quyen | E142: 5 | F142: 96 | G142: =IFERROR(_xlfn.XLOOKUP(OfficeForms.Table[[#This Row],[Email]],EE!C:C,EE!H:H,"Missing"),"Missing") -> Female | H142: DBL
A143: 142 | B143: dle3@amaris.com | C143: =_xlfn.XLOOKUP(OfficeForms.Table[[#This Row],[Email]],Table2[Email],Table2[FullName],"") -> LE Dang Quang | E143: 5 | F143: 106 | G143: =IFERROR(_xlfn.XLOOKUP(OfficeForms.Table[[#This Row],[Email]],EE!C:C,EE!H:H,"Missing"),"Missing") -> Male | H143: TWN
A144: 143 | B144: qnguyen13@amaris.com | C144: =_xlfn.XLOOKUP(OfficeForms.Table[[#This Row],[Email]],Table2[Email],Table2[FullName],"") -> NGUYEN Quynh Mai | E144: 5 | F144: 99 | G144: =IFERROR(_xlfn.XLOOKUP(OfficeForms.Table[[#This Row],[Email]],EE!C:C,EE!H:H,"Missing"),"Missing") -> Female | H144: DBL
... A151: 150 | B151: hnguyen6@mantu.com | C151: =_xlfn.XLOOKUP(OfficeForms.Table[[#This Row],[Email]],Table2[Email],Table2[FullName],"") -> NGUYEN Ha Nhi | E151: 5 | F151: 96 | G151: =IFERROR(_xlfn.XLOOKUP(OfficeForms.Table[[#This Row],[Email]],EE!C:C,EE!H:H,"Missing"),"Missing") -> Female | H151: DBL
A152: 151 | B152: qdiep@mantu.com | C152: =_xlfn.XLOOKUP(OfficeForms.Table[[#This Row],[Email]],Table2[Email],Table2[FullName],"") -> DIEP Tue Quan | D152: Nguyen The Anh - Male - 21/07/2000 - 040200000125 | E152: 5 | F152: 105 | G152: =IFERROR(_xlfn.XLOOKUP(OfficeForms.Table[[#This Row],[Email]],EE!C:C,EE!H:H,"Missing"),"Missing") -> Female | H152: DBL
A153: 152 | B153: nle1@mantu.com | C153: =_xlfn.XLOOKUP(OfficeForms.Table[[#This Row],[Email]],Table2[Email],Table2[FullName],"") -> LE Ngoc Khanh | E153: 5 | F153: 103 | G153: =IFERROR(_xlfn.XLOOKUP(OfficeForms.Table[[#This Row],[Email]],EE!C:C,EE!H:H,"Missing"),"Missing") -> Female | H153: DBL
A154: 153 | B154: yhong@mantu.com | C154: =_xlfn.XLOOKUP(OfficeForms.Table[[#This Row],[Email]],Table2[Email],Table2[FullName],"") -> HONG Yen Xuan | E154: 5 | F154: 125 | G154: =IFERROR(_xlfn.XLOOKUP(OfficeForms.Table[[#This Row],[Email]],EE!C:C,EE!H:H,"Missing"),"Missing") -> Female | H154: DBL
A155: 154 | B155: htran4@amaris.com | C155: =_xlfn.XLOOKUP(OfficeForms.Table[[#This Row],[Email]],Table2[Email],Table2[FullName],"") -> TRAN Huu Phuc - Tony | E155: 5 | F155: 107 | G155: =IFERROR(_xlfn.XLOOKUP(OfficeForms.Table[[#This Row],[Email]],EE!C:C,EE!H:H,"Missing"),"Missing") -> Male | H155: TWN
A156: 155 | B156: tluong1@mantu.com | C156: =_xlfn.XLOOKUP(OfficeForms.Table[[#This Row],[Email]],Table2[Email],Table2[FullName],"") -> LUONG Thi Tram Anh | E156: 5 | F156: 95 | G156: =IFERROR(_xlfn.XLOOKUP(OfficeForms.Table[[#This Row],[Email]],EE!C:C,EE!H:H,"Missing"),"Missing") -> Female | H156: DBL
A157: 156 | B157: nphuonguyen@mantu.com | C157: =_xlfn.XLOOKUP(OfficeForms.Table[[#This Row],[Email]],Table2[Email],Table2[FullName],"") -> NGUYEN Vu Phuong Uyen | E157: 5 | F157: 100 | G157: =IFERROR(_xlfn.XLOOKUP(OfficeForms.Table[[#This Row],[Email]],EE!C:C,EE!H:H,"Missing"),"Missing") -> Female | H157: DBL
A158: 157 | B158: utran@mantu.com | C158: =_xlfn.XLOOKUP(OfficeForms.Table[[#This Row],[Email]],Table2[Email],Table2[FullName],"") -> TRAN Ngoc Phuong Uyen | E158: 5 | F158: 103 | G158: =IFERROR(_xlfn.XLOOKUP(OfficeForms.Table[[#This Row],[Email]],EE!C:C,EE!H:H,"Missing"),"Missing") -> Female | H158: DBL
A159: 158 | B159: cnguyen@mantu.com | C159: =_xlfn.XLOOKUP(OfficeForms.Table[[#This Row],[Email]],Table2[Email],Table2[FullName],"") -> NGUYEN Chau Giang | E159: 5 | F159: 94 | G159: =IFERROR(_xlfn.XLOOKUP(OfficeForms.Table[[#This Row],[Email]],EE!C:C,EE!H:H,"Missing"),"Missing") -> Female | H159: DBL
A160: 159 | B160: cvodinhque@amaris.com | C160: =_xlfn.XLOOKUP(OfficeForms.Table[[#This Row],[Email]],Table2[Email],Table2[FullName],"") -> VO Dinh Que Chau | E160: 5 | F160: 102 | G160: =IFERROR(_xlfn.XLOOKUP(OfficeForms.Table[[#This Row],[Email]],EE!C:C,EE!H:H,"Missing"),"Missing") -> Female | H160: DBL
A161: 160 | B161: nhoanglamtam@amaris.com | C161: =_xlfn.XLOOKUP(OfficeForms.Table[[#This Row],[Email]],Table2[Email],Table2[FullName],"") -> HOANG Lam Tam Nhu | E161: 5 | F161: 95 | G161: =IFERROR(_xlfn.XLOOKUP(OfficeForms.Table[[#This Row],[Email]],EE!C:C,EE!H:H,"Missing"),"Missing") -> Female | H161: DBL
A162: 161 | B162: utrinhlethao@mantu.com | C162: =_xlfn.XLOOKUP(OfficeForms.Table[[#This Row],[Email]],Table2[Email],Table2[FullName],"") -> TRINH LE THAO Uyen | E162: 5 | F162: 94 | G162: =IFERROR(_xlfn.XLOOKUP(OfficeForms.Table[[#This Row],[Email]],EE!C:C,EE!H:H,"Missing"),"Missing") -> Female | H162: DBL
A163: 162 | B163: tnguyen38@mantu.com | C163: =_xlfn.XLOOKUP(OfficeForms.Table[[#This Row],[Email]],Table2[Email],Table2[FullName],"") -> NGUYEN The Anh | E163: 5 | F163: 106 | G163: =IFERROR(_xlfn.XLOOKUP(OfficeForms.Table[[#This Row],[Email]],EE!C:C,EE!H:H,"Missing"),"Missing") -> Male | H163: TWN
A164: 163 | B164: blam@mantu.com | C164: =_xlfn.XLOOKUP(OfficeForms.Table[[#This Row],[Email]],Table2[Email],Table2[FullName],"") -> LAM Bao Quyen | E164: 5 | F164: 102 | G164: =IFERROR(_xlfn.XLOOKUP(OfficeForms.Table[[#This Row],[Email]],EE!C:C,EE!H:H,"Missing"),"Missing") -> Female | H164: DBL
... A182: 181 | B182: dle2@mantu.com | C182: =_xlfn.XLOOKUP(OfficeForms.Table[[#This Row],[Email]],Table2[Email],Table2[FullName],"") -> LE Dinh Van | E182: 6 | F182: 136 | G182: =IFERROR(_xlfn.XLOOKUP(OfficeForms.Table[[#This Row],[Email]],EE!C:C,EE!H:H,"Missing"),"Missing") -> Male | H182: DBL
A183: 182 | B183: bhuynh@mantu.com | C183: =_xlfn.XLOOKUP(OfficeForms.Table[[#This Row],[Email]],Table2[Email],Table2[FullName],"") -> HUYNH Ba Nghi | E183: Own Transportation | F183: 136 | G183: =IFERROR(_xlfn.XLOOKUP(OfficeForms.Table[[#This Row],[Email]],EE!C:C,EE!H:H,"Missing"),"Missing") -> Male | H183: DBL
A184: 183 | B184: mpham@mantu.com | C184: =_xlfn.XLOOKUP(OfficeForms.Table[[#This Row],[Email]],Table2[Email],Table2[FullName],"") -> PHAM Minh Tuan | E184: 6 | F184: 135 | G184: =IFERROR(_xlfn.XLOOKUP(OfficeForms.Table[[#This Row],[Email]],EE!C:C,EE!H:H,"Missing"),"Missing") -> Male | H184: DBL
A185: 184 | B185: htran1@mantu.com | C185: =_xlfn.XLOOKUP(OfficeForms.Table[[#This Row],[Email]],Table2[Email],Table2[FullName],"") -> TRAN Thai Hung | D185: 1. Lưu Hồng Phương Thủy - Female - 27/10/1990 - 06619007476 2. Trần Hồng Như Ý - Female - 13/7/2025 - 079325017288 | E185: 6 | F185: 143 | G185: =IFERROR(_xlfn.XLOOKUP(OfficeForms.Table[[#This Row],[Email]],EE!C:C,EE!H:H,"Missing"),"Missing") -> Male | H185: DBL
A186: 185 | B186: tta@mantu.com | C186: =_xlfn.XLOOKUP(OfficeForms.Table[[#This Row],[Email]],Table2[Email],Table2[FullName],"") -> TA Thi My Hanh | E186: 6 | F186: 129 | G186: =IFERROR(_xlfn.XLOOKUP(OfficeForms.Table[[#This Row],[Email]],EE!C:C,EE!H:H,"Missing"),"Missing") -> Female | H186: DBL
A187: 186 | B187: tnguyen44@mantu.com | C187: =_xlfn.XLOOKUP(OfficeForms.Table[[#This Row],[Email]],Table2[Email],Table2[FullName],"") -> NGUYEN Thanh Hoang | E187: 6 | F187: 144 | G187: =IFERROR(_xlfn.XLOOKUP(OfficeForms.Table[[#This Row],[Email]],EE!C:C,EE!H:H,"Missing"),"Missing") -> Male | H187: DBL
A188: 187 | B188: aphan2@mantu.com | C188: =_xlfn.XLOOKUP(OfficeForms.Table[[#This Row],[Email]],Table2[Email],Table2[FullName],"") -> PHAN Anh Quan | E188: 6 | F188: 134 | G188: =IFERROR(_xlfn.XLOOKUP(OfficeForms.Table[[#This Row],[Email]],EE!C:C,EE!H:H,"Missing"),"Missing") -> Male | H188: DBL
A189: 188 | B189: cbui@mantu.com | C189: =_xlfn.XLOOKUP(OfficeForms.Table[[#This Row],[Email]],Table2[Email],Table2[FullName],"") -> BUI Cuong | E189: 6 | F189: 134 | G189: =IFERROR(_xlfn.XLOOKUP(OfficeForms.Table[[#This Row],[Email]],EE!C:C,EE!H:H,"Missing"),"Missing") -> Male | H189: DBL
A190: 189 | B190: pnguyenduy@mantu.com | C190: =_xlfn.XLOOKUP(OfficeForms.Table[[#This Row],[Email]],Table2[Email],Table2[FullName],"") -> NGUYEN Duy Phuong | E190: 6 | F190: 133 | G190: =IFERROR(_xlfn.XLOOKUP(OfficeForms.Table[[#This Row],[Email]],EE!C:C,EE!H:H,"Missing"),"Missing") -> Male | H190: DBL
A191: 190 | B191: nnguyen3@mantu.com | C191: =_xlfn.XLOOKUP(OfficeForms.Table[[#This Row],[Email]],Table2[Email],Table2[FullName],"") -> NGUYEN Ngoc Thao My | E191: 6 | F191: 129 | G191: =IFERROR(_xlfn.XLOOKUP(OfficeForms.Table[[#This Row],[Email]],EE!C:C,EE!H:H,"Missing"),"Missing") -> Female | H191: DBL
A192: 191 | B192: phoang@mantu.com | C192: =_xlfn.XLOOKUP(OfficeForms.Table[[#This Row],[Email]],Table2[Email],Table2[FullName],"") -> HOANG Phu Loc | E192: 6 | F192: 133 | G192: =IFERROR(_xlfn.XLOOKUP(OfficeForms.Table[[#This Row],[Email]],EE!C:C,EE!H:H,"Missing"),"Missing") -> Male | H192: DBL
...

Sheet Bus leader
A1: Bus No | B1: Leader Mail | C1: Leader Name | D1: Leader Phone
A2: 1 | B2: congdanh.bui@amaris.com | C2: Cong Danh BUI | D2: 0902891404
A3: 2 | B3: hla@amaris.com | C3: Thuy My Hao LA | D3: 0375225989
A4: 3 | B4: vanhieu.nguyen@amaris.com | C4: Van Hieu NGUYEN | D4: 0397459642
A5: 4 | B5: pnguyen4@amaris.com | C5: Thi Minh Phuong NGUYEN | D5: 0945745944 | K5: thanhson.nguyen@amaris.com | L5: NGUYEN Thanh Son | M5: 0392497315
A6: 5 | B6: knguyen8@mantu.com | C6: Trung Kien NGUYEN | D6: 0355327017
A7: 6 | B7: tngo@mantu.com | C7: NGO Trinh Quynh Nhu | D7: 0886311686
A8: 7 | B8: tran.ngocquoc@amaris.com | C8: Ngoc Quoc TRAN | D8: 0799010869
A9: 8 | B9: bhoang@mantu.com | C9: HOANG Bao An | D9: 0339526385

Sheet Room
A1: Name | B1: Are you planning to join the company trip? | C1: Please enter your ID/Passport number. | D1: Please enter your phone number (just in case we need to get in touch) | E1: Are you bringing any partner or family members along? | F1: If yes, please provide the details for each guest below | G1: How do you plan to travel to the trip location? | H1: Anything else we should know? | I1: Gov | J1: Dep | K1: N+1 | L1: Status | M1: With Fam | N1: C Fam | O1: A Fam | P1: Fam Q | Q1: Total Hc | R1: Bus No. | S1: Room No. | T1: Gender | AA1: Are you planning to join the company trip? | AB1: (All) | AI1: Are you planning to join the company trip? | AJ1: (All)
A2: Pham Khanh Linh TRAN | B2: Yes, count me in! | C2: 044199002375 | D2: 0823387274 | E2: No | G2: I’ll take the company bus | I2: Amaris Consulting | J2: Consultants | K2: HA Phuong Thao | L2: In | M2: No | N2: 0 | O2: 0 | P2: 0 | Q2: 1 | R2: 1 | S2: 1 | T2: =_xlfn.XLOOKUP(A2,Master!#REF!,Master!G:G) -> #REF!
A3: Do Thuy Tien PHAM | B3: Yes, count me in! | C3: 070194001945 | D3: 0396744435 | E3: No | G3: I’ll take the company bus | I3: Amaris Consulting | J3: Consultants | K3: HO Nguyen Hong Uyen | L3: In | M3: No | N3: 0 | O3: 0 | P3: 0 | Q3: 1 | R3: 1 | S3: 1 | T3: =_xlfn.XLOOKUP(A3,Master!#REF!,Master!G:G) -> #REF! | W3: {=_xlfn.UNIQUE(S2:S272)} -> 1 | AA3: Bus No. | AB3: Room No. | AC3: Name | AD3: Sum of Fam Q | AE3: Sum of Total Hc | AI3: Gender | AJ3: Room No. | AK3: With Fam | AL3: Bus No. | AM3: Name | AN3: Sum of Fam Q | AO3: Sum of Total Hc
A4: Hoang Ha Quyen NGUYEN | B4: Yes, count me in! | C4: 077300001719 | D4: 0968963049 | E4: No | G4: I’ll take the company bus | I4: Amaris Consulting | J4: Consultants | K4: HO Nguyen Hong Uyen | L4: In | M4: No | N4: 0 | O4: 0 | P4: 0 | Q4: 1 | R4: 1 | S4: 2 | T4: =_xlfn.XLOOKUP(A4,Master!#REF!,Master!G:G) -> #REF! | W4: 2 | AA4: 1 | AB4: 1 | AC4: Do Thuy Tien PHAM | AD4: 0 | AE4: 1 | AI4: Female | AJ4: 1 | AN4: 0 | AO4: 2 | AP4: =AO4 -> 2
A5: Thien Trang DOAN | B5: Yes, count me in! | C5: 091300011455 | D5: 0918626459 | E5: No | G5: I’ll take the company bus | H5: If there’s a single room, I wanna stay alone (if any) | I5: Amaris Consulting | J5: Consultants | K5: HO Nguyen Hong Uyen | L5: In | M5: No | N5: 0 | O5: 0 | P5: 0 | Q5: 1 | R5: 1 | S5: 2 | T5: =_xlfn.XLOOKUP(A5,Master!#REF!,Master!G:G) -> #REF! | W5: 3 | AA5: 1 | AB5: 1 | AC5: Pham Khanh Linh TRAN | AD5: 0 | AE5: 1 | AI5: Female | AJ5: 2 | AN5: 0 | AO5: 2 | AP5: =AO5 -> 2
A6: Minh Thuan LE | B6: Yes, count me in! | C6: 086099002987 | D6: 0968933873 | E6: No | G6: I’ll take the company bus | I6: Amaris Consulting | J6: Consultants | K6: HA Phuong Thao | L6: In | M6: No | N6: 0 | O6: 0 | P6: 0 | Q6: 1 | R6: 1 | S6: 3 | T6: =_xlfn.XLOOKUP(A6,Master!#REF!,Master!G:G) -> #REF! | W6: 4 | AA6: 1 | AB6: 2 | AC6: Hoang Ha Quyen NGUYEN | AD6: 0 | AE6: 1 | AI6: Female | AJ6: 31 | AN6: 0 | AO6: 2 | AP6: =AO6 -> 2
A7: Van Thanh Thuan NGUYEN | B7: Yes, count me in! | C7: 080095004933 | D7: 0793485644 | E7: No | G7: I’ll take the company bus | H7: I'd like to request to be booked in the same room as the IVB team. | I7: Amaris Consulting | J7: Consultants | K7: HA Phuong Thao | L7: In | M7: No | N7: 0 | O7: 0 | P7: 0 | Q7: 1 | R7: 1 | S7: 3 | T7: =_xlfn.XLOOKUP(A7,Master!#REF!,Master!G:G) -> #REF! | W7: 5 | AA7: 1 | AB7: 2 | AC7: Thien Trang DOAN | AD7: 0 | AE7: 1 | AI7: Female | AJ7: 32 | AN7: 0 | AO7: 2 | AP7: =AO7 -> 2
A8: Duc Minh CAO | B8: Yes, count me in! | C8: 080202010719 | D8: 0942198738 | E8: No | G8: I’ll take the company bus | I8: Amaris Consulting | J8: Consultants | K8: HA Phuong Thao | L8: In | M8: No | N8: 0 | O8: 0 | P8: 0 | Q8: 1 | R8: 1 | S8: 4 | T8: =_xlfn.XLOOKUP(A8,Master!#REF!,Master!G:G) -> #REF! | W8: 6 | AA8: 1 | AB8: 4 | AC8: Duc Minh CAO | AD8: 0 | AE8: 1 | AI8: Female | AJ8: 33 | AN8: 0 | AO8: 2 | AP8: =AO8 -> 2
A9: Hoang Tu LA | B9: Yes, count me in! | C9: 083097005277 | D9: 0386788883 | E9: No | G9: I’ll take the company bus | I9: Amaris Consulting | J9: Consultants | K9: HA Phuong Thao | L9: In | M9: No | N9: 0 | O9: 0 | P9: 0 | Q9: 1 | R9: 1 | S9: 4 | T9: =_xlfn.XLOOKUP(A9,Master!#REF!,Master!G:G) -> #REF! | W9: 7 | AA9: 1 | AB9: 4 | AC9: Hoang Tu LA | AD9: 0 | AE9: 1 | AI9: Female | AJ9: 34 | AN9: 0 | AO9: 2 | AP9: =AO9 -> 2
A10: Trung Nghia CAO | B10: Yes, count me in! | C10: 051094000961 | D10: 0938945445 | E10: No | G10: I’ll take the company bus | I10: Amaris Consulting | J10: Consultants | K10: HA Phuong Thao | L10: In | M10: No | N10: 0 | O10: 0 | P10: 0 | Q10: 1 | R10: 1 | S10: 5 | T10: =_xlfn.XLOOKUP(A10,Master!#REF!,Master!G:G) -> #REF! | W10: 8 | AA10: 1 | AB10: 5 | AC10: Trung Nghia CAO | AD10: 0 | AE10: 1 | AI10: Female | AJ10: 44 | AN10: 0 | AO10: 2 | AP10: =AO10 -> 2
A11: Van Do TRAN | B11: Yes, count me in! | C11: 089097020361 | D11: 0967513840 | E11: No | G11: I’ll take the company bus | I11: Amaris Consulting | J11: Consultants | K11: HA Phuong Thao | L11: In | M11: No | N11: 0 | O11: 0 | P11: 0 | Q11: 1 | R11: 1 | S11: 5 | T11: =_xlfn.XLOOKUP(A11,Master!#REF!,Master!G:G) -> #REF! | W11: 9 | AA11: 1 | AB11: 5 | AC11: Van Do TRAN | AD11: 0 | AE11: 1 | AI11: Female | AJ11: 45 | AN11: 0 | AO11: 2 | AP11: =AO11 -> 2
A12: Quang Trinh HA | B12: Yes, count me in! | C12: 087099016549 | D12: 0826759579 | E12: No | G12: I’ll take the company bus | I12: Amaris Consulting | J12: Consultants | K12: HA Phuong Thao | L12: In | M12: No | N12: 0 | O12: 0 | P12: 0 | Q12: 1 | R12: 1 | S12: 6 | T12: =_xlfn.XLOOKUP(A12,Master!#REF!,Master!G:G) -> #REF! | W12: 10 | AA12: 1 | AB12: 6 | AC12: Binh Nam MAI | AD12: 0 | AE12: 1 | AI12: Female | AJ12: 60 | AN12: 0 | AO12: 2 | AP12: =AO12 -> 2
A13: Binh Nam MAI | B13: Yes, count me in! | C13: 044099000541 | D13: 0948527910 | E13: No | G13: I’ll take the company bus | I13: Amaris Consulting | J13: Consultants | K13: HA Phuong Thao | L13: In | M13: No | N13: 0 | O13: 0 | P13: 0 | Q13: 1 | R13: 1 | S13: 6 | T13: =_xlfn.XLOOKUP(A13,Master!#REF!,Master!G:G) -> #REF! | W13: 11 | AA13: 1 | AB13: 6 | AC13: Quang Trinh HA | AD13: 0 | AE13: 1 | AI13: Female | AJ13: 61 | AN13: 0 | AO13: 2 | AP13: =AO13 -> 2
A14: Ngô Tấn Thành | B14: Yes, count me in! | C14: 089200015516 | D14: +84 329 382 782 | E14: No | G14: I’ll take the company bus | H14: Team chị My | I14: Amaris Consulting | J14: Consultants | K14: HA Phuong Thao | L14: In | M14: No | N14: 0 | O14: 0 | P14: 0 | Q14: 1 | R14: 1 | S14: 7 | T14: =_xlfn.XLOOKUP(A14,Master!#REF!,Master!G:G) -> #REF! | W14: 12 | AA14: 1 | AB14: 7 | AC14: Hong Chuong NGUYEN | AD14: 0 | AE14: 1 | AI14: Female | AJ14: 62 | AN14: 0 | AO14: 2 | AP14: =AO14 -> 2
A15: Hong Chuong NGUYEN | B15: Yes, count me in! | C15: 083084008265 | D15: 0989600669 | E15: No | G15: I’ll take the company bus | I15: Amaris Consulting | J15: Consultants | K15: HA Phuong Thao | L15: In | M15: No | N15: 0 | O15: 0 | P15: 0 | Q15: 1 | R15: 1 | S15: 7 | T15: =_xlfn.XLOOKUP(A15,Master!#REF!,Master!G:G) -> #REF! | W15: 13 | AA15: 1 | AB15: 7 | AC15: Ngô Tấn Thành | AD15: 0 | AE15: 1 | AI15: Female | AJ15: 68 | AN15: 0 | AO15: 1 | AP15: =AO15 -> 1
A16: Nguyễn Lê Thành | B16: Yes, count me in! | C16: 062201003205 | D16: +84 931 182 688 | E16: No | G16: I’ll take the company bus | I16: Amaris Consulting | J16: Consultants | K16: HA Phuong Thao | L16: In | M16: No | N16: 0 | O16: 0 | P16: 0 | Q16: 1 | R16: 1 | S16: 8 | T16: =_xlfn.XLOOKUP(A16,Master!#REF!,Master!G:G) -> #REF! | W16: 14 | AA16: 1 | AB16: 8 | AC16: Ngoc Tuan NGUYEN | AD16: 0 | AE16: 1 | AI16: Female | AJ16: 69 | AN16: 0 | AO16: 2 | AP16: =AO16 -> 2
A17: Ngoc Tuan NGUYEN | B17: Yes, count me in! | C17: 051099011537 | D17: 0973724249 | E17: No | G17: I’ll take the company bus | I17: Amaris Consulting | J17: Consultants | K17: HO Nguyen Hong Uyen | L17: In | M17: No | N17: 0 | O17: 0 | P17: 0 | Q17: 1 | R17: 1 | S17: 8 | T17: =_xlfn.XLOOKUP(A17,Master!#REF!,Master!G:G) -> #REF! | W17: 15 | AA17: 1 | AB17: 8 | AC17: Nguyễn Lê Thành | AD17: 0 | AE17: 1 | AI17: Female | AJ17: 82 | AN17: 0 | AO17: 2 | AP17: =AO17 -> 2
A18: Thanh Nhan PHAN | B18: Yes, count me in! | C18: 079096015213 | D18: 0392357076 | E18: No | G18: I’ll take the company bus | I18: Amaris Consulting | J18: Consultants | K18: HO Nguyen Hong Uyen | L18: In | M18: No | N18: 0 | O18: 0 | P18: 0 | Q18: 1 | R18: 1 | S18: 9 | T18: =_xlfn.XLOOKUP(A18,Master!#REF!,Master!G:G) -> #REF! | W18: 16 | AA18: 1 | AB18: 9 | AC18: Thanh Nhan PHAN | AD18: 0 | AE18: 1 | AI18: Female | AJ18: 83 | AN18: 0 | AO18: 2 | AP18: =AO18 -> 2
A19: Xuan Dat HOANG | B19: Yes, count me in! | C19: 066201016152 | D19: 0393688714 | E19: No | G19: I’ll take the company bus | I19: Amaris Consulting | J19: Consultants | K19: HO Nguyen Hong Uyen | L19: In | M19: No | N19: 0 | O19: 0 | P19: 0 | Q19: 1 | R19: 1 | S19: 9 | T19: =_xlfn.XLOOKUP(A19,Master!#REF!,Master!G:G) -> #REF! | W19: 17 | AA19: 1 | AB19: 9 | AC19: Xuan Dat HOANG | AD19: 0 | AE19: 1 | AI19: Female | AJ19: 84 | AN19: 0 | AO19: 2 | AP19: =AO19 -> 2
A20: Hong Son DAO | B20: Yes, count me in! | C20: 075200024308 | D20: 0938316793 | E20: No | G20: I’ll take the company bus | I20: Amaris Consulting | J20: Consultants | K20: HO Nguyen Hong Uyen | L20: In | M20: No | N20: 0 | O20: 0 | P20: 0 | Q20: 1 | R20: 1 | S20: 10 | T20: =_xlfn.XLOOKUP(A20,Master!#REF!,Master!G:G) -> #REF! | W20: 18 | AA20: 1 | AB20: 10 | AC20: Hong Son DAO | AD20: 0 | AE20: 1 | AI20: Female | AJ20: 85 | AN20: 0 | AO20: 2 | AP20: =AO20 -> 2
A21: Thanh Son NGUYEN | B21: Yes, count me in! | C21: 051098005098 | D21: 0392497315 | E21: No | G21: I’ll take the company bus | I21: Amaris Consulting | J21: Consultants | K21: HO Nguyen Hong Uyen | L21: In | M21: No | N21: 0 | O21: 0 | P21: 0 | Q21: 1 | R21: 1 | S21: 10 | T21: =_xlfn.XLOOKUP(A21,Master!#REF!,Master!G:G) -> #REF! | W21: 19 | AA21: 1 | AB21: 10 | AC21: Thanh Son NGUYEN | AD21: 0 | AE21: 1 | AI21: Female | AJ21: 86 | AN21: 0 | AO21: 2 | AP21: =AO21 -> 2
A22: Thanh Phuoc LE | B22: Yes, count me in! | C22: 068096007001 | D22: 0357556867 | E22: No | G22: I’ll take the company bus | I22: Amaris Consulting | J22: Consultants | K22: HO Nguyen Hong Uyen | L22: In | M22: No | N22: 0 | O22: 0 | P22: 0 | Q22: 1 | R22: 1 | S22: 11 | T22: =_xlfn.XLOOKUP(A22,Master!#REF!,Master!G:G) -> #REF! | W22: 20 | AA22: 1 | AB22: 11 | AC22: Le Man Dat NGUYEN | AD22: 0 | AE22: 1 | AI22: Female | AJ22: 87 | AN22: 0 | AO22: 2 | AP22: =AO22 -> 2
A23: Le Man Dat NGUYEN | B23: Yes, count me in! | C23: 086200001291 | D23: 0337804259 | E23: No | G23: I’ll take the company bus | I23: Amaris Consulting | J23: Consultants | K23: HO Nguyen Hong Uyen | L23: In | M23: No | N23: 0 | O23: 0 | P23: 0 | Q23: 1 | R23: 1 | S23: 11 | T23: =_xlfn.XLOOKUP(A23,Master!#REF!,Master!G:G) -> #REF! | W23: 21 | AA23: 1 | AB23: 11 | AC23: Thanh Phuoc LE | AD23: 0 | AE23: 1 | AI23: Female | AJ23: 88 | AN23: 0 | AO23: 2 | AP23: =AO23 -> 2
A24: Thanh Loc NGUYEN | B24: Yes, count me in! | C24: 046097000064 | D24: 0333515756 | E24: No | G24: I’ll take the company bus | I24: Amaris Consulting | J24: Consultants | K24: HO Nguyen Hong Uyen | L24: In | M24: No | N24: 0 | O24: 0 | P24: 0 | Q24: 1 | R24: 1 | S24: 12 | T24: =_xlfn.XLOOKUP(A24,Master!#REF!,Master!G:G) -> #REF! | W24: 22 | AA24: 1 | AB24: 12 | AC24: Thanh Loc NGUYEN | AD24: 0 | AE24: 1 | AI24: Female | AJ24: 89 | AN24: 0 | AO24: 2 | AP24: =AO24 -> 2
A25: Van Thanh Danh KHUAT | B25: Yes, count me in! | C25: 077203004018 | D25: 0971007831 | E25: No | G25: I’ll take the company bus | I25: Amaris Consulting | J25: Consultants | K25: HO Nguyen Hong Uyen | L25: In | M25: No | N25: 0 | O25: 0 | P25: 0 | Q25: 1 | R25: 1 | S25: 12 | T25: =_xlfn.XLOOKUP(A25,Master!#REF!,Master!G:G) -> #REF! | W25: 23 | AA25: 1 | AB25: 12 | AC25: Van Thanh Danh KHUAT | AD25: 0 | AE25: 1 | AI25: Female | AJ25: 94 | AN25: 0 | AO25: 2 | AP25: =AO25 -> 2
A26: Huu Vinh NGUYEN | B26: Yes, count me in! | C26: 089200019968 | D26: 0974086701 | E26: No | G26: I’ll take the company bus | I26: Amaris Consulting | J26: Consultants | K26: HO Nguyen Hong Uyen | L26: In | M26: No | N26: 0 | O26: 0 | P26: 0 | Q26: 1 | R26: 1 | S26: 13 | T26: =_xlfn.XLOOKUP(A26,Master!#REF!,Master!G:G) -> #REF! | W26: 24 | AA26: 1 | AB26: 13 | AC26: Huu Vinh NGUYEN | AD26: 0 | AE26: 1 | AI26: Female | AJ26: 95 | AN26: 0 | AO26: 2 | AP26: =AO26 -> 2
... A30: Quang Nien NGUYEN | B30: Yes, count me in! | C30: 058201000239 | D30: 0855586358 | E30: No | G30: I’ll take the company bus | I30: Amaris Consulting | J30: Consultants | K30: HO Nguyen Hong Uyen | L30: In | M30: No | N30: 0 | O30: 0 | P30: 0 | Q30: 1 | R30: 1 | S30: 15 | T30: =_xlfn.XLOOKUP(A30,Master!#REF!,Master!G:G) -> #REF! | W30: 28 | AA30: 1 | AB30: 15 | AC30: Cong Danh BUI | AD30: 0 | AE30: 1 | AI30: Female | AJ30: 99 | AN30: 0 | AO30: 2 | AP30: =AO30 -> 2
A31: Cong Danh BUI | B31: Yes, count me in! | C31: 079201014939 | D31: 0902891404 | E31: No | G31: I’ll take the company bus | H31: Motion sickness pills | I31: Amaris Consulting | J31: Consultants | K31: NGUYEN Tien Nam | L31: In | M31: No | N31: 0 | O31: 0 | P31: 0 | Q31: 1 | R31: 1 | S31: 15 | T31: =_xlfn.XLOOKUP(A31,Master!#REF!,Master!G:G) -> #REF! | W31: 29 | AA31: 1 | AB31: 15 | AC31: Quang Nien NGUYEN | AD31: 0 | AE31: 1 | AI31: Female | AJ31: 100 | AN31: 0 | AO31: 2 | AP31: =AO31 -> 2
A32: Huynh Chi Tin VO | B32: Yes, count me in! | C32: 079095022758 | D32: 0777104166 | E32: No | G32: I’ll take the company bus | I32: Amaris Consulting | J32: Consultants | K32: NGUYEN Tien Nam | L32: In | M32: No | N32: 0 | O32: 0 | P32: 0 | Q32: 1 | R32: 1 | S32: 16 | T32: =_xlfn.XLOOKUP(A32,Master!#REF!,Master!G:G) -> #REF! | W32: 30 | AA32: 1 | AB32: 16 | AC32: Huynh Chi Tin VO | AD32: 0 | AE32: 1 | AI32: Female | AJ32: 101 | AN32: 0 | AO32: 2 | AP32: =AO32 -> 2
A33: Quang Trung DO | B33: Yes, count me in! | C33: 064200012749 | D33: 0396402696 | E33: No | G33: I’ll take the company bus | I33: Amaris Consulting | J33: Consultants | K33: NGUYEN Tien Nam | L33: In | M33: No | N33: 0 | O33: 0 | P33: 0 | Q33: 1 | R33: 1 | S33: 16 | T33: =_xlfn.XLOOKUP(A33,Master!#REF!,Master!G:G) -> #REF! | W33: 31 | AA33: 1 | AB33: 16 | AC33: Quang Trung DO | AD33: 0 | AE33: 1 | AI33: Female | AJ33: 102 | AN33: 0 | AO33: 2 | AP33: =AO33 -> 2
A34: Van Trien DANG | B34: Yes, count me in! | C34: 068097008720 | D34: 0981212098 | E34: No | G34: I’ll take the company bus | I34: Amaris Consulting | J34: Consultants | K34: HOANG Thien | L34: In | M34: No | N34: 0 | O34: 0 | P34: 0 | Q34: 1 | R34: 7 | S34: 17 | T34: =_xlfn.XLOOKUP(A34,Master!#REF!,Master!G:G) -> #REF! | W34: 32 | AA34: 1 | AB34: 85 | AC34: Nguyen Hong Uyen HO | AD34: 0 | AE34: 1 | AI34: Female | AJ34: 103 | AN34: 0 | AO34: 2 | AP34: =AO34 -> 2
A35: Cong Khanh HUYNH | B35: Yes, count me in! | C35: 087201004021 | D35: 0777905219 | E35: No | G35: I’ll take the company bus | I35: Amaris Consulting | J35: Consultants | K35: HUYNH Chi Cuong | L35: In | M35: No | N35: 0 | O35: 0 | P35: 0 | Q35: 1 | R35: 2 | S35: 17 | T35: =_xlfn.XLOOKUP(A35,Master!#REF!,Master!G:G) -> #REF! | W35: 33 | AA35: 1 | AB35: 85 | AC35: Phuong Thao HA | AD35: 0 | AE35: 1 | AI35: Female | AJ35: 104 | AN35: 0 | AO35: 2 | AP35: =AO35 -> 2
A36: Thanh Dat NGUYEN | B36: Yes, count me in! | C36: 075096016711 | D36: 0932980033 | E36: No | G36: I’ll take the company bus | I36: Amaris Consulting | J36: Consultants | K36: HOANG Thien | L36: In | M36: No | N36: 0 | O36: 0 | P36: 0 | Q36: 1 | R36: 7 | S36: 18 | T36: =_xlfn.XLOOKUP(A36,Master!#REF!,Master!G:G) -> #REF! | W36: 34 | AA36: 1 | AB36: 86 | AC36: Thanh Hang VU | AD36: 0 | AE36: 1 | AI36: Female | AJ36: 116 | AN36: 0 | AO36: 2 | AP36: =AO36 -> 2
A37: Song Toan VU | B37: Yes, count me in! | C37: 048095001773 | D37: 0335353685 | E37: No | G37: I’ll take the company bus | I37: Amaris Consulting | J37: Consultants | K37: HOANG Thien | L37: In | M37: No | N37: 0 | O37: 0 | P37: 0 | Q37: 1 | R37: 7 | S37: 18 | T37: =_xlfn.XLOOKUP(A37,Master!#REF!,Master!G:G) -> #REF! | W37: 35 | AA37: 1 | AB37: 90 | AC37: NGUYEN Tien Nam | AD37: 0 | AE37: 1 | AI37: Female | AJ37: 117 | AN37: 0 | AO37: 2 | AP37: =AO37 -> 2
A38: Quang Tin TRAN | B38: Yes, count me in! | C38: 058095001270 | D38: 0349687204 | E38: No | G38: I’ll take the company bus | I38: Amaris Consulting | J38: Consultants | K38: HOANG Thien | L38: In | M38: No | N38: 0 | O38: 0 | P38: 0 | Q38: 1 | R38: 7 | S38: 19 | T38: =_xlfn.XLOOKUP(A38,Master!#REF!,Master!G:G) -> #REF! | W38: 36 | AA38: 1 | AB38: 3 | AC38: Minh Thuan LE | AD38: 0 | AE38: 1 | AI38: Female | AJ38: 118 | AN38: 0 | AO38: 2 | AP38: =AO38 -> 2
A39: Vo Tuong Duy | B39: Yes, count me in! | C39: 079200028676 | D39: 0397974403 | E39: No | G39: I’ll take the company bus | I39: Amaris Consulting | J39: Consultants | K39: HOANG Thien | L39: In (Exit confirmed) | M39: No | P39: 0 | Q39: 1 | R39: 7 | S39: 19 | T39: =_xlfn.XLOOKUP(A39,Master!#REF!,Master!G:G) -> #REF! | W39: 37 | AA39: 1 | AB39: 3 | AC39: Van Thanh Thuan NGUYEN | AD39: 0 | AE39: 1 | AI39: Female | AJ39: 119 | AN39: 0 | AO39: 2 | AP39: =AO39 -> 2
A40: Ngoc Thanh PHAM | B40: Yes, count me in! | C40: 060094011465 | D40: 0333950268 | E40: No | G40: I’ll take the company bus | I40: Amaris Consulting | J40: Consultants | K40: HUYNH Chi Cuong | L40: In | M40: No | N40: 0 | O40: 0 | P40: 0 | Q40: 1 | R40: 2 | S40: 20 | T40: =_xlfn.XLOOKUP(A40,Master!#REF!,Master!G:G) -> #REF! | W40: 38 | AA40: 1 | AB40: 73 | AC40: Thanh Tai NGUYEN | AD40: 2 | AE40: 3 | AI40: Female | AJ40: 122 | AN40: 0 | AO40: 2 | AP40: =AO40 -> 2
A41: Xuan Vu TRAN | B41: Yes, count me in! | C41: 046098001181 | D41: 0327360123 | E41: No | G41: I’ll take the company bus | I41: Amaris Consulting | J41: Consultants | K41: HUYNH Chi Cuong | L41: In | M41: No | N41: 0 | O41: 0 | P41: 0 | Q41: 1 | R41: 2 | S41: 20 | T41: =_xlfn.XLOOKUP(A41,Master!#REF!,Master!G:G) -> #REF! | W41: 39 | AA41: 1 Total | AD41: 2 | AE41: 39 | AI41: Female | AJ41: 123 | AN41: 0 | AO41: 3 | AP41: =AO41 -> 3
A42: Nhu Hai Luu PHAN | B42: Yes, count me in! | C42: 060099011492 | D42: 0379738098 | E42: No | G42: I’ll take the company bus | I42: Amaris Consulting | J42: Consultants | K42: LA Thuy My Hao | L42: In | M42: No | N42: 0 | O42: 0 | P42: 0 | Q42: 1 | R42: 2 | S42: 21 | T42: =_xlfn.XLOOKUP(A42,Master!#REF!,Master!G:G) -> #REF! | W42: 40 | AA42: 2 | AB42: 17 | AC42: Cong Khanh HUYNH | AD42: 0 | AE42: 1 | AI42: Female | AJ42: 124 | AN42: 0 | AO42: 2 | AP42: =AO42 -> 2
A43: Hoai Sang CAO | B43: Yes, count me in! | C43: 095203009143 | D43: 0944552050 | E43: No | G43: I’ll take the company bus | I43: Amaris Consulting | J43: Consultants | K43: LA Thuy My Hao | L43: In | M43: No | N43: 0 | O43: 0 | P43: 0 | Q43: 1 | R43: 2 | S43: 21 | T43: =_xlfn.XLOOKUP(A43,Master!#REF!,Master!G:G) -> #REF! | W43: 57 | AA43: 2 | AB43: 17 | AC43: Van Trien DANG | AD43: 0 | AE43: 1 | AI43: Female | AJ43: 125 | AN43: 0 | AO43: 2 | AP43: =AO43 -> 2
A44: Huynh Duy Duc NGUYEN | B44: Yes, count me in! | C44: 064201016123 | D44: 0979409417 | E44: No | G44: I’ll take the company bus | I44: Amaris Consulting | J44: Consultants | K44: LA Thuy My Hao | L44: In | M44: No | N44: 0 | O44: 0 | P44: 0 | Q44: 1 | R44: 2 | S44: 22 | T44: =_xlfn.XLOOKUP(A44,Master!#REF!,Master!G:G) -> #REF! | W44: 41 | AA44: 2 | AB44: 18 | AC44: Song Toan VU | AD44: 0 | AE44: 1 | AI44: Female | AJ44: 126 | AN44: 0 | AO44: 2 | AP44: =AO44 -> 2
A45: Quoc Linh TRAN | B45: Yes, count me in! | C45: 096099005690 | D45: 0379218610 | E45: No | G45: I’ll take the company bus | I45: Amaris Consulting | J45: Consultants | K45: LA Thuy My Hao | L45: In | M45: No | N45: 0 | O45: 0 | P45: 0 | Q45: 1 | R45: 2 | S45: 22 | T45: =_xlfn.XLOOKUP(A45,Master!#REF!,Master!G:G) -> #REF! | W45: 42 | AA45: 2 | AB45: 18 | AC45: Thanh Dat NGUYEN | AD45: 0 | AE45: 1 | AI45: Female | AJ45: 127 | AN45: 0 | AO45: 2 | AP45: =AO45 -> 2
A46: Van Hao LE | B46: Yes, count me in! | C46: 089097008685 | D46: 0378462578 | E46: No | G46: I’ll take the company bus | I46: Amaris Consulting | J46: Consultants | K46: LA Thuy My Hao | L46: In | M46: No | N46: 0 | O46: 0 | P46: 0 | Q46: 1 | R46: 2 | S46: 23 | T46: =_xlfn.XLOOKUP(A46,Master!#REF!,Master!G:G) -> #REF! | W46: 43 | AA46: 2 | AB46: 19 | AC46: Quang Tin TRAN | AD46: 0 | AE46: 1 | AI46: Female | AJ46: 128 | AN46: 0 | AO46: 2 | AP46: =AO46 -> 2
A47: Minh Phuoc NGUYEN | B47: Yes, count me in! | C47: 079094018368 | D47: 0937686998 | E47: No | G47: I’ll take the company bus | I47: Amaris Consulting | J47: Consultants | K47: LA Thuy My Hao | L47: In | M47: No | N47: 0 | O47: 0 | P47: 0 | Q47: 1 | R47: 2 | S47: 23 | T47: =_xlfn.XLOOKUP(A47,Master!#REF!,Master!G:G) -> #REF! | W47: 44 | AA47: 2 | AB47: 19 | AC47: Vo Tuong Duy | AD47: 0 | AE47: 1 | AI47: Female | AJ47: 129 | AN47: 0 | AO47: 2 | AP47: =AO47 -> 2
A48: Duy Nhat NGUYEN | B48: Yes, count me in! | C48: 072200007361 | D48: 0967524457 | E48: No | G48: I’ll take the company bus | I48: Amaris Consulting | J48: Consultants | K48: LA Thuy My Hao | L48: In | M48: No | N48: 0 | O48: 0 | P48: 0 | Q48: 1 | R48: 2 | S48: 24 | T48: =_xlfn.XLOOKUP(A48,Master!#REF!,Master!G:G) -> #REF! | W48: 45 | AA48: 2 | AB48: 20 | AC48: Ngoc Thanh PHAM | AD48: 0 | AE48: 1 | AI48: Female | AJ48: 130 | AN48: 0 | AO48: 2 | AP48: =AO48 -> 2
A49: Huu Ngan MAI | B49: Yes, count me in! | C49: 049202002958 | D49: 0343734096 | E49: No | G49: I’ll take the company bus | I49: Amaris Consulting | J49: Consultants | K49: LA Thuy My Hao | L49: In | M49: No | N49: 0 | O49: 0 | P49: 0 | Q49: 1 | R49: 2 | S49: 24 | T49: =_xlfn.XLOOKUP(A49,Master!#REF!,Master!G:G) -> #REF! | W49: 46 | AA49: 2 | AB49: 20 | AC49: Xuan Vu TRAN | AD49: 0 | AE49: 1 | AI49: Female | AJ49: 131 | AN49: 0 | AO49: 2 | AP49: =AO49 -> 2
A50: Minh Quan DANG | B50: Yes, count me in! | C50: 089201001783 | D50: 0941967745 | E50: No | G50: I’ll take the company bus | I50: Amaris Consulting | J50: Consultants | K50: LA Thuy My Hao | L50: In | M50: No | N50: 0 | O50: 0 | P50: 0 | Q50: 1 | R50: 2 | S50: 25 | T50: =_xlfn.XLOOKUP(A50,Master!#REF!,Master!G:G) -> #REF! | W50: 47 | AA50: 2 | AB50: 21 | AC50: Hoai Sang CAO | AD50: 0 | AE50: 1 | AI50: Male | AJ50: 3 | AN50: 0 | AO50: 2 | AP50: =AO50 -> 2
A51: Huu Nghia PHAM | B51: Yes, count me in! | C51: 064098000457 | D51: 0363543388 | E51: No | G51: I’ll take the company bus | I51: Amaris Consulting | J51: Consultants | K51: LA Thuy My Hao | L51: In | M51: No | N51: 0 | O51: 0 | P51: 0 | Q51: 1 | R51: 2 | S51: 25 | T51: =_xlfn.XLOOKUP(A51,Master!#REF!,Master!G:G) -> #REF! | W51: 48 | AA51: 2 | AB51: 21 | AC51: Nhu Hai Luu PHAN | AD51: 0 | AE51: 1 | AI51: Male | AJ51: 4 | AN51: 0 | AO51: 2 | AP51: =AO51 -> 2
A52: Duy Phong NGUYEN | B52: Yes, count me in! | C52: 049200016142 | D52: 0396428796 | E52: No | G52: I’ll take the company bus | I52: Amaris Consulting | J52: Consultants | K52: LA Thuy My Hao | L52: In | M52: No | N52: 0 | O52: 0 | P52: 0 | Q52: 1 | R52: 2 | S52: 26 | T52: =_xlfn.XLOOKUP(A52,Master!#REF!,Master!G:G) -> #REF! | W52: 49 | AA52: 2 | AB52: 22 | AC52: Huynh Duy Duc NGUYEN | AD52: 0 | AE52: 1 | AI52: Male | AJ52: 5 | AN52: 0 | AO52: 2 | AP52: =AO52 -> 2
A53: Tuan Thanh TRAN | B53: Yes, count me in! | C53: 042200003160 | D53: 0971850315 | E53: No | G53: I’ll take the company bus | I53: Amaris Consulting | J53: Consultants | K53: LA Thuy My Hao | L53: In | M53: No | N53: 0 | O53: 0 | P53: 0 | Q53: 1 | R53: 2 | S53: 26 | T53: =_xlfn.XLOOKUP(A53,Master!#REF!,Master!G:G) -> #REF! | W53: 50 | AA53: 2 | AB53: 22 | AC53: Quoc Linh TRAN | AD53: 0 | AE53: 1 | AI53: Male | AJ53: 6 | AN53: 0 | AO53: 2 | AP53: =AO53 -> 2
... A55: Thanh Duc LE | B55: Yes, count me in! | C55: 079200038775 | D55: 0339310132 | E55: No | G55: I’ll take the company bus | I55: Amaris Consulting | J55: Consultants | K55: LA Thuy My Hao | L55: In | M55: No | N55: 0 | O55: 0 | P55: 0 | Q55: 1 | R55: 2 | S55: 27 | T55: =_xlfn.XLOOKUP(A55,Master!#REF!,Master!G:G) -> #REF! | W55: 52 | AA55: 2 | AB55: 23 | AC55: Van Hao LE | AD55: 0 | AE55: 1 | AI55: Male | AJ55: 8 | AN55: 0 | AO55: 2 | AP55: =AO55 -> 2
A56: Tran Nhat Duc NGUYEN | B56: Yes, count me in! | C56: 056200011360 | D56: 0869885812 | E56: No | G56: I’ll take the company bus | I56: Amaris Consulting | J56: Consultants | K56: LA Thuy My Hao | L56: In | M56: No | N56: 0 | O56: 0 | P56: 0 | Q56: 1 | R56: 2 | S56: 28 | T56: =_xlfn.XLOOKUP(A56,Master!#REF!,Master!G:G) -> #REF! | W56: 53 | Y56: 65 | AA56: 2 | AB56: 24 | AC56: Duy Nhat NGUYEN | AD56: 0 | AE56: 1 | AI56: Male | AJ56: 9 | AN56: 0 | AO56: 2 | AP56: =AO56 -> 2
A57: Minh Tri DO | B57: Yes, count me in! | C57: minhtri.do@amaris.com | D57: 0935919461 | E57: No | G57: I’ll take the company bus | I57: Amaris Consulting | J57: Consultants | K57: LA Thuy My Hao | L57: In | M57: No | N57: 0 | O57: 0 | P57: 0 | Q57: 1 | R57: 2 | S57: 28 | T57: =_xlfn.XLOOKUP(A57,Master!#REF!,Master!G:G) -> #REF! | W57: 54 | Y57: 66 | AA57: 2 | AB57: 24 | AC57: Huu Ngan MAI | AD57: 0 | AE57: 1 | AI57: Male | AJ57: 10 | AN57: 0 | AO57: 2 | AP57: =AO57 -> 2
A58: Tien Manh NGUYEN | B58: Yes, count me in! | C58: 252203000013 | D58: 0829622879 | E58: No | G58: I’ll take the company bus | I58: Amaris Consulting | J58: Consultants | K58: LA Thuy My Hao | L58: In | M58: No | N58: 0 | O58: 0 | P58: 0 | Q58: 1 | R58: 2 | S58: 29 | T58: =_xlfn.XLOOKUP(A58,Master!#REF!,Master!G:G) -> #REF! | W58: 55 | Y58: 66 | AA58: 2 | AB58: 25 | AC58: Huu Nghia PHAM | AD58: 0 | AE58: 1 | AI58: Male | AJ58: 11 | AN58: 0 | AO58: 2 | AP58: =AO58 -> 2
A59: Quoc Trung KIEU | B59: Yes, count me in! | C59: 079200044816 | D59: 0932535781 | E59: No | G59: I’ll take the company bus | I59: Amaris Consulting | J59: Consultants | K59: LA Thuy My Hao | L59: In | M59: No | N59: 0 | O59: 0 | P59: 0 | Q59: 1 | R59: 2 | S59: 29 | T59: =_xlfn.XLOOKUP(A59,Master!#REF!,Master!G:G) -> #REF! | W59: 56 | Y59: 67 | AA59: 2 | AB59: 25 | AC59: Minh Quan DANG | AD59: 0 | AE59: 1 | AI59: Male | AJ59: 12 | AN59: 0 | AO59: 2 | AP59: =AO59 -> 2
A60: DINH Thanh Viet | B60: Yes, count me in! | C60: 052200005034 | D60: +84 377130331 | E60: No | G60: I’ll take the company bus | I60: Amaris Consulting | J60: Consultants | K60: LA Thuy My Hao | L60: In | M60: No | N60: 0 | O60: 0 | P60: 0 | Q60: 1 | R60: 2 | S60: 30 | T60: =_xlfn.XLOOKUP(A60,Master!#REF!,Master!G:G) -> #REF! | W60: 58 | Y60: 67 | AA60: 2 | AB60: 26 | AC60: Duy Phong NGUYEN | AD60: 0 | AE60: 1 | AI60: Male | AJ60: 13 | AN60: 0 | AO60: 2 | AP60: =AO60 -> 2
A61: Chi Cuong HUYNH | B61: Yes, count me in! | C61: 079095014706 | D61: 0937251707 | E61: No | G61: I’ll take the company bus | H61: Dị ứng cồn | I61: Amaris Consulting | J61: Consultants | K61: NGUYEN The Trinh | L61: In | M61: No | N61: 0 | O61: 0 | P61: 0 | Q61: 1 | R61: 2 | S61: 30 | T61: =_xlfn.XLOOKUP(A61,Master!#REF!,Master!G:G) -> #REF! | W61: 59 | AA61: 2 | AB61: 26 | AC61: Tuan Thanh TRAN | AD61: 0 | AE61: 1 | AI61: Male | AJ61: 14 | AN61: 0 | AO61: 2 | AP61: =AO61 -> 2
A62: Thi Thanh Huong LE | B62: Yes, count me in! | C62: 079302009777 | D62: 0703264721 | E62: No | G62: I’ll take the company bus | I62: Amaris Consulting | J62: Consultants | K62: HUYNH Chi Cuong | L62: In | M62: No | N62: 0 | O62: 0 | P62: 0 | Q62: 1 | R62: 2 | S62: 31 | T62: =_xlfn.XLOOKUP(A62,Master!#REF!,Master!G:G) -> #REF! | W62: 60 | AA62: 2 | AB62: 27 | AC62: Huy Tri NGUYEN | AD62: 0 | AE62: 1 | AI62: Male | AJ62: 15 | AN62: 0 | AO62: 2 | AP62: =AO62 -> 2
A63: Phuong Hang LE THI | B63: Yes, count me in! | C63: 079186021679 | D63: 0866876722 | E63: No | G63: I’ll take the company bus | I63: Amaris Consulting | J63: Consultants | K63: LA Thuy My Hao | L63: In | M63: No | N63: 0 | O63: 0 | P63: 0 | Q63: 1 | R63: 2 | S63: 31 | T63: =_xlfn.XLOOKUP(A63,Master!#REF!,Master!G:G) -> #REF! | W63: 62 | AA63: 2 | AB63: 27 | AC63: Thanh Duc LE | AD63: 0 | AE63: 1 | AI63: Male | AJ63: 16 | AN63: 0 | AO63: 2 | AP63: =AO63 -> 2
A64: Thi Tram Ngan TRAN | B64: Yes, count me in! | C64: 087300002383 | D64: 0939053112 | E64: No | G64: I’ll take the company bus | I64: Amaris Consulting | J64: Consultants | K64: LA Thuy My Hao | L64: In | M64: No | N64: 0 | O64: 0 | P64: 0 | Q64: 1 | R64: 2 | S64: 32 | T64: =_xlfn.XLOOKUP(A64,Master!#REF!,Master!G:G) -> #REF! | W64: 61 | AA64: 2 | AB64: 28 | AC64: Minh Tri DO | AD64: 0 | AE64: 1 | AI64: Male | AJ64: 17 | AN64: 0 | AO64: 2 | AP64: =AO64 -> 2
A65: Ngoc My HA | B65: Yes, count me in! | C65: 082300007349 | D65: 0888745255 | E65: No | G65: I’ll take the company bus | I65: Amaris Consulting | J65: Consultants | K65: LA Thuy My Hao | L65: In | M65: No | N65: 0 | O65: 0 | P65: 0 | Q65: 1 | R65: 2 | S65: 32 | T65: =_xlfn.XLOOKUP(A65,Master!#REF!,Master!G:G) -> #REF! | W65: 69 | AA65: 2 | AB65: 28 | AC65: Tran Nhat Duc NGUYEN | AD65: 0 | AE65: 1 | AI65: Male | AJ65: 18 | AN65: 0 | AO65: 2 | AP65: =AO65 -> 2
A66: Ngoc Thuy Trang PHAM | B66: Yes, count me in! | C66: 079300022868 | D66: 0707653589 | E66: No | G66: I’ll take the company bus | I66: Amaris Consulting | J66: Consultants | K66: LA Thuy My Hao | L66: In | M66: No | N66: 0 | O66: 0 | P66: 0 | Q66: 1 | R66: 2 | S66: 33 | T66: =_xlfn.XLOOKUP(A66,Master!#REF!,Master!G:G) -> #REF! | W66: 63 | AA66: 2 | AB66: 29 | AC66: Quoc Trung KIEU | AD66: 0 | AE66: 1 | AI66: Male | AJ66: 19 | AN66: 0 | AO66: 2 | AP66: =AO66 -> 2
A67: Thai An PHAM THUY | B67: Yes, count me in! | C67: 095304000976 | D67: 0913854054 | E67: No | G67: I’ll take the company bus | I67: Amaris Consulting | J67: Consultants | K67: LA Thuy My Hao | L67: In | M67: No | N67: 0 | O67: 0 | P67: 0 | Q67: 1 | R67: 2 | S67: 33 | T67: =_xlfn.XLOOKUP(A67,Master!#REF!,Master!G:G) -> #REF! | W67: 64 | AA67: 2 | AB67: 29 | AC67: Tien Manh NGUYEN | AD67: 0 | AE67: 1 | AI67: Male | AJ67: 20 | AN67: 0 | AO67: 2 | AP67: =AO67 -> 2
A68: Tu Uyen DINH THI | B68: Yes, count me in! | C68: 070302002356 | D68: 0383899275 | E68: No | G68: I’ll take the company bus | I68: Amaris Consulting | J68: Consultants | K68: LA Thuy My Hao | L68: In | M68: No | N68: 0 | O68: 0 | P68: 0 | Q68: 1 | R68: 2 | S68: 34 | T68: =_xlfn.XLOOKUP(A68,Master!#REF!,Master!G:G) -> #REF! | W68: 65 | AA68: 2 | AB68: 30 | AC68: Chi Cuong HUYNH | AD68: 0 | AE68: 1 | AI68: Male | AJ68: 21 | AN68: 0 | AO68: 2 | AP68: =AO68 -> 2
A69: Ngoc Tran TA THI | B69: Yes, count me in! | C69: 089196003991 | D69: 0369040747 | E69: No | G69: I’ll take the company bus | I69: Amaris Consulting | J69: Consultants | K69: LA Thuy My Hao | L69: In | M69: No | N69: 0 | O69: 0 | P69: 0 | Q69: 1 | R69: 2 | S69: 34 | T69: =_xlfn.XLOOKUP(A69,Master!#REF!,Master!G:G) -> #REF! | W69: 66 | AA69: 2 | AB69: 30 | AC69: DINH Thanh Viet | AD69: 0 | AE69: 1 | AI69: Male | AJ69: 22 | AN69: 0 | AO69: 2 | AP69: =AO69 -> 2
A70: Tri Hung NGUYEN | B70: Yes, count me in! | C70: 040099011473 | D70: 0946650045 | E70: No | G70: I’ll take the company bus | I70: Amaris Consulting | J70: Consultants | K70: NGUYEN Hoang Tuan Anh | L70: In | M70: No | N70: 0 | O70: 0 | P70: 0 | Q70: 1 | R70: 3 | S70: 35 | T70: =_xlfn.XLOOKUP(A70,Master!#REF!,Master!G:G) -> #REF! | W70: 67 | AA70: 2 | AB70: 31 | AC70: Phuong Hang LE THI | AD70: 0 | AE70: 1 | AI70: Male | AJ70: 23 | AN70: 0 | AO70: 2 | AP70: =AO70 -> 2
A71: Hoang Tuan Anh NGUYEN | B71: Yes, count me in! | C71: 079096034588 | D71: 0938282487 | E71: No | G71: I’ll take the company bus | I71: Amaris Consulting | J71: Consultants | K71: NGUYEN The Trinh | L71: In | M71: No | N71: 0 | O71: 0 | P71: 0 | Q71: 1 | R71: 3 | S71: 35 | T71: =_xlfn.XLOOKUP(A71,Master!#REF!,Master!G:G) -> #REF! | W71: 68 | AA71: 2 | AB71: 31 | AC71: Thi Thanh Huong LE | AD71: 0 | AE71: 1 | AI71: Male | AJ71: 24 | AN71: 0 | AO71: 2 | AP71: =AO71 -> 2
A72: That Viet Anh TON | B72: Yes, count me in! | C72: 079096027174 | D72: 0934297931 | E72: No | G72: I’ll take the company bus | I72: Amaris Consulting | J72: Consultants | K72: NGUYEN Hoang Tuan Anh | L72: In | M72: No | N72: 0 | O72: 0 | P72: 0 | Q72: 1 | R72: 3 | S72: 36 | T72: =_xlfn.XLOOKUP(A72,Master!#REF!,Master!G:G) -> #REF! | W72: 70 | AA72: 2 | AB72: 32 | AC72: Ngoc My HA | AD72: 0 | AE72: 1 | AI72: Male | AJ72: 25 | AN72: 0 | AO72: 2 | AP72: =AO72 -> 2
A73: Truong An NGUYEN | B73: Yes, count me in! | C73: 075095021646 | D73: 0352680918 | E73: No | G73: I’ll take the company bus | I73: Amaris Consulting | J73: Consultants | K73: NGUYEN Hoang Tuan Anh | L73: In | M73: No | N73: 0 | O73: 0 | P73: 0 | Q73: 1 | R73: 3 | S73: 36 | T73: =_xlfn.XLOOKUP(A73,Master!#REF!,Master!G:G) -> #REF! | W73: 71 | AA73: 2 | AB73: 32 | AC73: Thi Tram Ngan TRAN | AD73: 0 | AE73: 1 | AI73: Male | AJ73: 26 | AN73: 0 | AO73: 2 | AP73: =AO73 -> 2
... A78: Van Tien CAO | B78: Yes, count me in! | C78: 067098004566 | D78: 0584106886 | E78: No | G78: I’ll take the company bus | I78: Amaris Consulting | J78: Consultants | K78: TRAN Thi Ha My | L78: In | M78: No | N78: 0 | O78: 0 | P78: 0 | Q78: 1 | R78: 3 | S78: 39 | T78: =_xlfn.XLOOKUP(A78,Master!#REF!,Master!G:G) -> #REF! | W78: 76 | AA78: 2 | AB78: 87 | AC78: Thuy My Hao LA | AD78: 0 | AE78: 1 | AI78: Male | AJ78: 35 | AN78: 0 | AO78: 2 | AP78: =AO78 -> 2
A79: Phuong VU | B79: Yes, count me in! | C79: 089096021770 | D79: 0962359719 | E79: No | G79: I’ll take the company bus | I79: Amaris Consulting | J79: Consultants | K79: TRAN Thi Ha My | L79: In | M79: No | N79: 0 | O79: 0 | P79: 0 | Q79: 1 | R79: 3 | S79: 39 | T79: =_xlfn.XLOOKUP(A79,Master!#REF!,Master!G:G) -> #REF! | W79: 77 | AA79: 2 Total | AD79: 0 | AE79: 37 | AI79: Male | AJ79: 36 | AN79: 0 | AO79: 2 | AP79: =AO79 -> 2
A80: Minh Tan TRAN | B80: Yes, count me in! | C80: 082097013452 | D80: 0332548027 | E80: No | G80: I’ll take the company bus | I80: Amaris Consulting | J80: Consultants | K80: TRAN Thi Ha My | L80: In | M80: No | N80: 0 | O80: 0 | P80: 0 | Q80: 1 | R80: 3 | S80: 40 | T80: =_xlfn.XLOOKUP(A80,Master!#REF!,Master!G:G) -> #REF! | W80: 78 | AA80: 3 | AB80: 35 | AC80: Hoang Tuan Anh NGUYEN | AD80: 0 | AE80: 1 | AI80: Male | AJ80: 37 | AN80: 0 | AO80: 2 | AP80: =AO80 -> 2
A81: Xuan Thuong TRINH | B81: Yes, count me in! | C81: 049092003884 | D81: 0973718347 | E81: No | G81: I’ll take the company bus | I81: Amaris Consulting | J81: Consultants | K81: TRAN Thi Ha My | L81: In | M81: No | N81: 0 | O81: 0 | P81: 0 | Q81: 1 | R81: 4 | S81: 57 | T81: =_xlfn.XLOOKUP(A81,Master!#REF!,Master!G:G) -> #REF! | W81: 79 | AA81: 3 | AB81: 35 | AC81: Tri Hung NGUYEN | AD81: 0 | AE81: 1 | AI81: Male | AJ81: 38 | AN81: 0 | AO81: 2 | AP81: =AO81 -> 2
A82: Van Hieu NGUYEN | B82: Yes, count me in! | C82: 052096015341 | D82: 0397459642 | E82: No | G82: I’ll take the company bus | I82: Amaris Consulting | J82: Consultants | K82: TRAN Thi Ha My | L82: In | M82: No | N82: 0 | O82: 0 | P82: 0 | Q82: 1 | R82: 3 | S82: 41 | T82: =_xlfn.XLOOKUP(A82,Master!#REF!,Master!G:G) -> #REF! | W82: 80 | AA82: 3 | AB82: 36 | AC82: That Viet Anh TON | AD82: 0 | AE82: 1 | AI82: Male | AJ82: 39 | AN82: 0 | AO82: 2 | AP82: =AO82 -> 2
A83: Kim Gia Huy NGUYEN | B83: Yes, count me in! | C83: 079099027044 | D83: 0335618057 | E83: No | G83: I’ll take the company bus | I83: Amaris Consulting | J83: Consultants | K83: TRAN Thi Ha My | L83: In | M83: No | N83: 0 | O83: 0 | P83: 0 | Q83: 1 | R83: 3 | S83: 41 | T83: =_xlfn.XLOOKUP(A83,Master!#REF!,Master!G:G) -> #REF! | W83: 81 | AA83: 3 | AB83: 36 | AC83: Truong An NGUYEN | AD83: 0 | AE83: 1 | AI83: Male | AJ83: 40 | AN83: 0 | AO83: 2 | AP83: =AO83 -> 2
A84: Thanh Xuan BUI | B84: Yes, count me in! | C84: 075090010849 | D84: 0778836595 | E84: No | G84: I’ll take the company bus | I84: Amaris Consulting | J84: Consultants | K84: TRAN Thi Ha My | L84: In | M84: No | N84: 0 | O84: 0 | P84: 0 | Q84: 1 | R84: 3 | S84: 42 | T84: =_xlfn.XLOOKUP(A84,Master!#REF!,Master!G:G) -> #REF! | W84: 82 | AA84: 3 | AB84: 37 | AC84: Nam Kha LE | AD84: 0 | AE84: 1 | AI84: Male | AJ84: 41 | AN84: 0 | AO84: 2 | AP84: =AO84 -> 2
A85: Van Tinh PHAM | B85: Yes, count me in! | C85: 052092015218 | D85: 0346726479 | E85: No | G85: I’ll take the company bus | I85: Amaris Consulting | J85: Consultants | K85: TRAN Thi Ha My | L85: In | M85: No | N85: 0 | O85: 0 | P85: 0 | Q85: 1 | R85: 3 | S85: 42 | T85: =_xlfn.XLOOKUP(A85,Master!#REF!,Master!G:G) -> #REF! | W85: 83 | AA85: 3 | AB85: 37 | AC85: Tan Hoang NGUYEN | AD85: 0 | AE85: 1 | AI85: Male | AJ85: 42 | AN85: 0 | AO85: 2 | AP85: =AO85 -> 2
A86: Thi Phuong Thao VU | B86: Yes, count me in! | C86: 035198005801 | D86: 0961393725 | E86: Yes | F86: Cao Thi Truc Duyen - Female - 15/06/1997 - 083197002767 | G86: I’ll take the company bus | I86: Amaris Consulting | J86: Consultants | K86: TRAN Thi Ha My | L86: In | M86: Yes | N86: 0 | O86: 1 | P86: 1 | Q86: 2 | R86: 3 | S86: 43 | T86: =_xlfn.XLOOKUP(A86,Master!#REF!,Master!G:G) -> #REF! | W86: 84 | AA86: 3 | AB86: 38 | AC86: Bao Khang HA | AD86: 0 | AE86: 1 | AI86: Male | AJ86: 46 | AN86: 0 | AO86: 2 | AP86: =AO86 -> 2
A87: Thi Nguyet NONG | B87: Yes, count me in! | C87: 091301010042 | D87: 0768811159 | E87: No | G87: I’ll take the company bus | I87: Amaris Consulting | J87: Consultants | K87: NGUYEN Hoang Tuan Anh | L87: In | M87: No | N87: 0 | O87: 0 | P87: 0 | Q87: 1 | R87: 3 | S87: 44 | T87: =_xlfn.XLOOKUP(A87,Master!#REF!,Master!G:G) -> #REF! | W87: 85 | AA87: 3 | AB87: 38 | AC87: Thanh Duy CHAU | AD87: 0 | AE87: 1 | AI87: Male | AJ87: 47 | AN87: 0 | AO87: 2 | AP87: =AO87 -> 2
A88: Thi Viet Trinh NGUYEN | B88: Yes, count me in! | C88: 075193013225 | D88: 0356055190 | E88: No | G88: I’ll take the company bus | I88: Amaris Consulting | J88: Consultants | K88: TRAN Thi Ha My | L88: In | M88: No | N88: 0 | O88: 0 | P88: 0 | Q88: 1 | R88: 3 | S88: 44 | T88: =_xlfn.XLOOKUP(A88,Master!#REF!,Master!G:G) -> #REF! | W88: 86 | AA88: 3 | AB88: 39 | AC88: Phuong VU | AD88: 0 | AE88: 1 | AI88: Male | AJ88: 48 | AN88: 0 | AO88: 2 | AP88: =AO88 -> 2
A89: Khanh Gia CHUNG | B89: Yes, count me in! | C89: 079301006935 | D89: 0779911643 | E89: No | G89: I’ll take the company bus | I89: Amaris Consulting | J89: Consultants | K89: TRAN Thi Ha My | L89: In | M89: No | N89: 0 | O89: 0 | P89: 0 | Q89: 1 | R89: 3 | S89: 45 | T89: =_xlfn.XLOOKUP(A89,Master!#REF!,Master!G:G) -> #REF! | W89: 87 | AA89: 3 | AB89: 39 | AC89: Van Tien CAO | AD89: 0 | AE89: 1 | AI89: Male | AJ89: 50 | AN89: 0 | AO89: 2 | AP89: =AO89 -> 2
A90: Ngoc Trang Dai TRAN | B90: Yes, count me in! | C90: 084197000010 | D90: 0936610147 | E90: No | G90: I’ll take the company bus | I90: Amaris Consulting | J90: Consultants | K90: TRAN Thi Ha My | L90: In | M90: No | N90: 0 | O90: 0 | P90: 0 | Q90: 1 | R90: 3 | S90: 45 | T90: =_xlfn.XLOOKUP(A90,Master!#REF!,Master!G:G) -> #REF! | W90: 88 | AA90: 3 | AB90: 40 | AC90: Minh Tan TRAN | AD90: 0 | AE90: 1 | AI90: Male | AJ90: 51 | AN90: 0 | AO90: 2 | AP90: =AO90 -> 2
A91: Thanh Trung NGUYEN | B91: Yes, count me in! | C91: 031202004177 | D91: 0886895676 | E91: No | G91: I’ll take the company bus | I91: Amaris Consulting | J91: Consultants | K91: HUYNH Minh Khoi | L91: In | M91: No | N91: 0 | O91: 0 | P91: 0 | Q91: 1 | R91: 4 | S91: 46 | T91: =_xlfn.XLOOKUP(A91,Master!#REF!,Master!G:G) -> #REF! | W91: 89 | AA91: 3 | AB91: 40 | AC91: Xuan Thuong TRINH | AD91: 0 | AE91: 1 | AI91: Male | AJ91: 52 | AN91: 0 | AO91: 2 | AP91: =AO91 -> 2
A92: Nguyen Ngoc NGUYEN SY | B92: Yes, count me in! | C92: 079202021638 | D92: 0899337446 | E92: No | G92: I’ll take the company bus | I92: Amaris Consulting | J92: Consultants | K92: HUYNH Minh Khoi | L92: In | M92: No | N92: 0 | O92: 0 | P92: 0 | Q92: 1 | R92: 4 | S92: 46 | T92: =_xlfn.XLOOKUP(A92,Master!#REF!,Master!G:G) -> #REF! | W92: 90 | AA92: 3 | AB92: 41 | AC92: Kim Gia Huy NGUYEN | AD92: 0 | AE92: 1 | AI92: Male | AJ92: 53 | AN92: 0 | AO92: 2 | AP92: =AO92 -> 2
A93: Anh Quoc PHAM | B93: Yes, count me in! | C93: 079201003742 | D93: 0896116155 | E93: No | G93: I’ll take the company bus | I93: Amaris Consulting | J93: Consultants | K93: HUYNH Minh Khoi | L93: In | M93: No | N93: 0 | O93: 0 | P93: 0 | Q93: 1 | R93: 4 | S93: 47 | T93: =_xlfn.XLOOKUP(A93,Master!#REF!,Master!G:G) -> #REF! | W93: 92 | AA93: 3 | AB93: 41 | AC93: Van Hieu NGUYEN | AD93: 0 | AE93: 1 | AI93: Male | AJ93: 54 | AN93: 0 | AO93: 2 | AP93: =AO93 -> 2
A94: Hai Binh DANG | B94: Yes, count me in! | C94: 031202010766 | D94: 0981412159 | E94: No | G94: I’ll take the company bus | I94: Amaris Consulting | J94: Consultants | K94: HUYNH Minh Khoi | L94: In | M94: No | N94: 0 | O94: 0 | P94: 0 | Q94: 1 | R94: 4 | S94: 47 | T94: =_xlfn.XLOOKUP(A94,Master!#REF!,Master!G:G) -> #REF! | W94: 93 | AA94: 3 | AB94: 42 | AC94: Thanh Xuan BUI | AD94: 0 | AE94: 1 | AI94: Male | AJ94: 55 | AN94: 0 | AO94: 2 | AP94: =AO94 -> 2
A95: Trung Tin THAI | B95: Yes, count me in! | C95: 064201004428 | D95: 0337399029 | E95: No | G95: I’ll take the company bus | I95: Amaris Consulting | J95: Consultants | K95: HUYNH Minh Khoi | L95: In | M95: No | N95: 0 | O95: 0 | P95: 0 | Q95: 1 | R95: 4 | S95: 48 | T95: =_xlfn.XLOOKUP(A95,Master!#REF!,Master!G:G) -> #REF! | W95: 94 | AA95: 3 | AB95: 42 | AC95: Van Tinh PHAM | AD95: 0 | AE95: 1 | AI95: Male | AJ95: 56 | AN95: 0 | AO95: 2 | AP95: =AO95 -> 2
A96: Nhat DANG MINH | B96: Yes, count me in! | C96: 048203001699 | D96: 0905054228 | E96: No | G96: I’ll take the company bus | I96: Amaris Consulting | J96: Consultants | K96: HUYNH Minh Khoi | L96: In | M96: No | N96: 0 | O96: 0 | P96: 0 | Q96: 1 | R96: 4 | S96: 48 | T96: =_xlfn.XLOOKUP(A96,Master!#REF!,Master!G:G) -> #REF! | W96: 95 | AA96: 3 | AB96: 43 | AC96: Thi Phuong Thao VU | AD96: 1 | AE96: 2 | AI96: Male | AJ96: 57 | AN96: 0 | AO96: 2 | AP96: =AO96 -> 2
A97: Trung Kien PHAM | B97: Yes, count me in! | C97: 030098008566 | D97: 0348997157 | E97: Yes | F97: TRẦN DIỆP HUY - 046098011753 - 0766669006 - Male - 07/01/1998 | G97: I’ll take the company bus | I97: Amaris Consulting | J97: Consultants | K97: NGUYEN Duc Quy | L97: In | M97: Yes | N97: 0 | O97: 1 | P97: 1 | Q97: 2 | R97: 4 | S97: 49 | T97: =_xlfn.XLOOKUP(A97,Master!#REF!,Master!G:G) -> #REF! | W97: 96 | AA97: 3 | AB97: 44 | AC97: Thi Nguyet NONG | AD97: 0 | AE97: 1 | AI97: Male | AJ97: 58 | AN97: 0 | AO97: 2 | AP97: =AO97 -> 2
A98: Chien Hao CAO | B98: Yes, count me in! | C98: 066200009584 | D98: 0764290520 | E98: No | G98: I’ll take the company bus | I98: Amaris Consulting | J98: Consultants | K98: NGUYEN Thi Minh Phuong | L98: In | M98: No | N98: 0 | O98: 0 | P98: 0 | Q98: 1 | R98: 4 | S98: 50 | T98: =_xlfn.XLOOKUP(A98,Master!#REF!,Master!G:G) -> #REF! | W98: 97 | AA98: 3 | AB98: 44 | AC98: Thi Viet Trinh NGUYEN | AD98: 0 | AE98: 1 | AI98: Male | AJ98: 59 | AN98: 0 | AO98: 2 | AP98: =AO98 -> 2
A99: Do Nhat Minh PHAM | B99: Yes, count me in! | C99: 079099034668 | D99: 0906659850 | E99: No | G99: I’ll take the company bus | I99: Amaris Consulting | J99: Consultants | K99: NGUYEN Thi Minh Phuong | L99: In | M99: No | N99: 0 | O99: 0 | P99: 0 | Q99: 1 | R99: 4 | S99: 50 | T99: =_xlfn.XLOOKUP(A99,Master!#REF!,Master!G:G) -> #REF! | W99: 98 | AA99: 3 | AB99: 45 | AC99: Khanh Gia CHUNG | AD99: 0 | AE99: 1 | AI99: Male | AJ99: 63 | AN99: 0 | AO99: 2 | AP99: =AO99 -> 2
A100: Duy Hanh LE | B100: Yes, count me in! | C100: 079090028751 | D100: 0937308357 | E100: No | G100: I’ll take the company bus | I100: Amaris Consulting | J100: Consultants | K100: NGUYEN Thi Minh Phuong | L100: In | M100: No | N100: 0 | O100: 0 | P100: 0 | Q100: 1 | R100: 4 | S100: 51 | T100: =_xlfn.XLOOKUP(A100,Master!#REF!,Master!G:G) -> #REF! | W100: 99 | AA100: 3 | AB100: 45 | AC100: Ngoc Trang Dai TRAN | AD100: 0 | AE100: 1 | AI100: Male | AJ100: 64 | AN100: 0 | AO100: 2 | AP100: =AO100 -> 2
A101: Huu Thinh NGUYEN | B101: Yes, count me in! | C101: 066096004066 | D101: 0868415847 | E101: No | G101: I’ll take the company bus | I101: Amaris Consulting | J101: Consultants | K101: NGUYEN Thi Minh Phuong | L101: In | M101: No | N101: 0 | O101: 0 | P101: 0 | Q101: 1 | R101: 4 | S101: 51 | T101: =_xlfn.XLOOKUP(A101,Master!#REF!,Master!G:G) -> #REF! | W101: 100 | AA101: 3 | AB101: 86 | AC101: The Trinh NGUYEN | AD101: 0 | AE101: 1 | AI101: Male | AJ101: 65 | AN101: 0 | AO101: 2 | AP101: =AO101 -> 2
A102: Duc Thanh VAN | B102: Yes, count me in! | C102: 079090038513 | D102: 0356154210 | E102: No | G102: I’ll take the company bus | I102: Amaris Consulting | J102: Consultants | K102: NGUYEN Thi Minh Phuong | L102: In | M102: No | N102: 0 | O102: 0 | P102: 0 | Q102: 1 | R102: 4 | S102: 52 | T102: =_xlfn.XLOOKUP(A102,Master!#REF!,Master!G:G) -> #REF! | W102: 101 | AA102: 3 | AB102: 87 | AC102: Thi Ha My TRAN | AD102: 0 | AE102: 1 | AI102: Male | AJ102: 66 | AN102: 0 | AO102: 2 | AP102: =AO102 -> 2
A103: Duan NGUYEN LE | B103: Yes, count me in! | C103: 080096010523 | D103: 0966441600 | E103: No | G103: I’ll take the company bus | I103: Amaris Consulting | J103: Consultants | K103: NGUYEN Thi Minh Phuong | L103: In | M103: No | N103: 0 | O103: 0 | P103: 0 | Q103: 1 | R103: 4 | S103: 52 | T103: =_xlfn.XLOOKUP(A103,Master!#REF!,Master!G:G) -> #REF! | W103: 102 | AA103: 3 | AB103: 71 | AC103: Cong Tuan VAN | AD103: 1 | AE103: 2 | AI103: Male | AJ103: 67 | AN103: 0 | AO103: 2 | AP103: =AO103 -> 2
A104: Hoang Long NGUYEN | B104: Yes, count me in! | C104: 056098000238 | D104: 0392707949 | E104: No | G104: I’ll take the company bus | I104: Amaris Consulting | J104: Consultants | K104: NGUYEN Thi Minh Phuong | L104: In | M104: No | N104: 0 | O104: 0 | P104: 0 | Q104: 1 | R104: 4 | S104: 53 | T104: =_xlfn.XLOOKUP(A104,Master!#REF!,Master!G:G) -> #REF! | W104: 103 | AA104: 3 | AB104: 72 | AC104: Nham Quy TRAN | AD104: 1 | AE104: 2 | AI104: Male | AJ104: 68 | AN104: 0 | AO104: 1 | AP104: =AO104 -> 1
A105: Tan Hoang - Bi NGUYEN | B105: Yes, count me in! | C105: 079203011720 | D105: 0938080935 | E105: No | G105: I’ll take the company bus | I105: Amaris Consulting | J105: Consultants | K105: NGUYEN Thi Minh Phuong | L105: In | M105: No | N105: 0 | O105: 0 | P105: 0 | Q105: 1 | R105: 4 | S105: 53 | T105: =_xlfn.XLOOKUP(A105,Master!#REF!,Master!G:G) -> #REF! | W105: 104 | AA105: 3 | AB105: 74 | AC105: Anh Tuan - Tl NGUYEN | AD105: 3 | AE105: 4 | AI105: Male | AJ105: 78 | AN105: 0 | AO105: 2 | AP105: =AO105 -> 2
A106: Thai Hien LUONG | B106: Yes, count me in! | C106: 048087005724 | D106: 0968678149 | E106: No | G106: I’ll take the company bus | I106: Amaris Consulting | J106: Consultants | K106: NGUYEN Duc Quy | L106: In | M106: No | N106: 0 | O106: 0 | P106: 0 | Q106: 1 | R106: 4 | S106: 54 | T106: =_xlfn.XLOOKUP(A106,Master!#REF!,Master!G:G) -> #REF! | W106: 105 | AA106: 3 | AB106: 75 | AC106: Huy Hoang NGUYEN | AD106: 3 | AE106: 4 | AI106: Male | AJ106: 79 | AN106: 0 | AO106: 2 | AP106: =AO106 -> 2
A107: Van Ket VO | B107: Yes, count me in! | C107: 051091012099 | D107: 0902898110 | E107: No | G107: I’ll take the company bus | I107: Amaris Consulting | J107: Consultants | K107: NGUYEN Duc Quy | L107: In | M107: No | N107: 0 | O107: 0 | P107: 0 | Q107: 1 | R107: 4 | S107: 54 | T107: =_xlfn.XLOOKUP(A107,Master!#REF!,Master!G:G) -> #REF! | W107: 106 | AA107: 3 | AB107: 76 | AC107: Cong Quan PHAM | AD107: 2 | AE107: 3 | AI107: Male | AJ107: 80 | AN107: 0 | AO107: 2 | AP107: =AO107 -> 2
A108: Vu Phuong NGUYEN | B108: Yes, count me in! | C108: 086096004777 | D108: 0705731919 | E108: No | G108: I’ll take the company bus | I108: Amaris Consulting | J108: Consultants | K108: NGUYEN Duc Quy | L108: In | M108: No | N108: 0 | O108: 0 | P108: 0 | Q108: 1 | R108: 4 | S108: 55 | T108: =_xlfn.XLOOKUP(A108,Master!#REF!,Master!G:G) -> #REF! | W108: 107 | AA108: 3 Total | AD108: 11 | AE108: 39 | AI108: Male | AJ108: 81 | AN108: 0 | AO108: 2 | AP108: =AO108 -> 2
...

Sheet Update
A1: Name | B1: Are you planning to join the company trip? | C1: Please enter your ID/Passport number. | D1: Please enter your phone number (just in case we need to get in touch) | E1: Are you bringing any partner or family members along? | F1: If yes, please provide the details for each guest below | G1: How do you plan to travel to the trip location? | H1: Anything else we should know? | I1: Gov | J1: Dep | K1: N+1 | L1: Status | M1: With Fam | N1: C Fam | O1: A Fam | P1: Fam Q | Q1: Total Hc | R1: Bus No. | S1: Room No. | Y1: With Fam | Z1: No
A2: Pham Khanh Linh TRAN | B2: Yes, count me in! | C2: 044199002375 | D2: 0823387274 | E2: No | G2: I’ll take the company bus | I2: Amaris Consulting | J2: Consultants | K2: HA Phuong Thao | L2: In | M2: No | N2: 0 | O2: 0 | P2: 0 | Q2: 1 | R2: 3 | S2: 45
A3: Do Thuy Tien PHAM | B3: Yes, count me in! | C3: 070194001945 | D3: 0396744435 | E3: No | G3: I’ll take the company bus | I3: Amaris Consulting | J3: Consultants | K3: HO Nguyen Hong Uyen | L3: In | M3: No | N3: 0 | O3: 0 | P3: 0 | Q3: 1 | R3: 1 | S3: 1 | Y3: Row Labels | Z3: Sum of Total Hc | AB3: =MAX(Z:Z) -> 256
A4: Hoang Ha Quyen NGUYEN | B4: Yes, count me in! | C4: 077300001719 | D4: 0968963049 | E4: No | G4: I’ll take the company bus | I4: Amaris Consulting | J4: Consultants | K4: HO Nguyen Hong Uyen | L4: In | M4: No | N4: 0 | O4: 0 | P4: 0 | Q4: 1 | R4: 1 | S4: 2 | Y4: 1 | Z4: 2 | AC4: =Z4 -> 2
A5: Thien Trang DOAN | B5: Yes, count me in! | C5: 091300011455 | D5: 0918626459 | E5: No | G5: I’ll take the company bus | H5: If there’s a single room, I wanna stay alone (if any) | I5: Amaris Consulting | J5: Consultants | K5: HO Nguyen Hong Uyen | L5: In | M5: No | N5: 0 | O5: 0 | P5: 0 | Q5: 1 | R5: 1 | S5: 2 | Y5: 2 | Z5: 2 | AC5: =Z5 -> 2
A6: Minh Thuan LE | B6: Yes, count me in! | C6: 086099002987 | D6: 0968933873 | E6: No | G6: I’ll take the company bus | I6: Amaris Consulting | J6: Consultants | K6: HA Phuong Thao | L6: In | M6: No | N6: 0 | O6: 0 | P6: 0 | Q6: 1 | R6: 1 | S6: 3 | Y6: 3 | Z6: 2 | AC6: =Z6 -> 2
A7: Van Thanh Thuan NGUYEN | B7: Yes, count me in! | C7: 080095004933 | D7: 0793485644 | E7: No | G7: I’ll take the company bus | H7: I'd like to request to be booked in the same room as the IVB team. | I7: Amaris Consulting | J7: Consultants | K7: HA Phuong Thao | L7: In | M7: No | N7: 0 | O7: 0 | P7: 0 | Q7: 1 | R7: 1 | S7: 3 | Y7: 4 | Z7: 2 | AC7: =Z7 -> 2
A8: Duc Minh CAO | B8: Yes, count me in! | C8: 080202010719 | D8: 0942198738 | E8: No | G8: I’ll take the company bus | I8: Amaris Consulting | J8: Consultants | K8: HA Phuong Thao | L8: In | M8: No | N8: 0 | O8: 0 | P8: 0 | Q8: 1 | R8: 1 | S8: 4 | Y8: 5 | Z8: 2 | AC8: =Z8 -> 2
A9: Hoang Tu LA | B9: Yes, count me in! | C9: 083097005277 | D9: 0386788883 | E9: No | G9: I’ll take the company bus | I9: Amaris Consulting | J9: Consultants | K9: HA Phuong Thao | L9: In | M9: No | N9: 0 | O9: 0 | P9: 0 | Q9: 1 | R9: 1 | S9: 4 | Y9: 6 | Z9: 2 | AC9: =Z9 -> 2
A10: Trung Nghia CAO | B10: Yes, count me in! | C10: 051094000961 | D10: 0938945445 | E10: No | G10: I’ll take the company bus | I10: Amaris Consulting | J10: Consultants | K10: HA Phuong Thao | L10: In | M10: No | N10: 0 | O10: 0 | P10: 0 | Q10: 1 | R10: 1 | S10: 5 | Y10: 7 | Z10: 2 | AC10: =Z10 -> 2
A11: Van Do TRAN | B11: Yes, count me in! | C11: 089097020361 | D11: 0967513840 | E11: No | G11: I’ll take the company bus | I11: Amaris Consulting | J11: Consultants | K11: HA Phuong Thao | L11: In | M11: No | N11: 0 | O11: 0 | P11: 0 | Q11: 1 | R11: 1 | S11: 5 | Y11: 8 | Z11: 2 | AC11: =Z11 -> 2
A12: Quang Trinh HA | B12: Yes, count me in! | C12: 087099016549 | D12: 0826759579 | E12: No | G12: I’ll take the company bus | I12: Amaris Consulting | J12: Consultants | K12: HA Phuong Thao | L12: In | M12: No | N12: 0 | O12: 0 | P12: 0 | Q12: 1 | R12: 1 | S12: 6 | Y12: 9 | Z12: 2 | AC12: =Z12 -> 2
A13: Binh Nam MAI | B13: Yes, count me in! | C13: 044099000541 | D13: 0948527910 | E13: No | G13: I’ll take the company bus | I13: Amaris Consulting | J13: Consultants | K13: HA Phuong Thao | L13: In | M13: No | N13: 0 | O13: 0 | P13: 0 | Q13: 1 | R13: 1 | S13: 6 | Y13: 10 | Z13: 2 | AC13: =Z13 -> 2
A14: Ngô Tấn Thành | B14: Yes, count me in! | C14: 089200015516 | D14: +84 329 382 782 | E14: No | G14: I’ll take the company bus | H14: Team chị My | I14: Amaris Consulting | J14: Consultants | K14: HA Phuong Thao | L14: In | M14: No | N14: 0 | O14: 0 | P14: 0 | Q14: 1 | R14: 1 | S14: 7 | Y14: 11 | Z14: 2 | AC14: =Z14 -> 2
A15: Hong Chuong NGUYEN | B15: Yes, count me in! | C15: 083084008265 | D15: 0989600669 | E15: No | G15: I’ll take the company bus | I15: Amaris Consulting | J15: Consultants | K15: HA Phuong Thao | L15: In | M15: No | N15: 0 | O15: 0 | P15: 0 | Q15: 1 | R15: 1 | S15: 7 | Y15: 12 | Z15: 2 | AC15: =Z15 -> 2
A16: Nguyễn Lê Thành | B16: Yes, count me in! | C16: 062201003205 | D16: +84 931 182 688 | E16: No | G16: I’ll take the company bus | I16: Amaris Consulting | J16: Consultants | K16: HA Phuong Thao | L16: In | M16: No | N16: 0 | O16: 0 | P16: 0 | Q16: 1 | R16: 1 | S16: 8 | Y16: 13 | Z16: 2 | AC16: =Z16 -> 2
A17: Ngoc Tuan NGUYEN | B17: Yes, count me in! | C17: 051099011537 | D17: 0973724249 | E17: No | G17: I’ll take the company bus | I17: Amaris Consulting | J17: Consultants | K17: HO Nguyen Hong Uyen | L17: In | M17: No | N17: 0 | O17: 0 | P17: 0 | Q17: 1 | R17: 1 | S17: 8 | Y17: 14 | Z17: 2 | AC17: =Z17 -> 2
A18: Thanh Nhan PHAN | B18: Yes, count me in! | C18: 079096015213 | D18: 0392357076 | E18: No | G18: I’ll take the company bus | I18: Amaris Consulting | J18: Consultants | K18: HO Nguyen Hong Uyen | L18: In | M18: No | N18: 0 | O18: 0 | P18: 0 | Q18: 1 | R18: 1 | S18: 9 | Y18: 15 | Z18: 2 | AC18: =Z18 -> 2
A19: Xuan Dat HOANG | B19: Yes, count me in! | C19: 066201016152 | D19: 0393688714 | E19: No | G19: I’ll take the company bus | I19: Amaris Consulting | J19: Consultants | K19: HO Nguyen Hong Uyen | L19: In | M19: No | N19: 0 | O19: 0 | P19: 0 | Q19: 1 | R19: 1 | S19: 9 | Y19: 16 | Z19: 2 | AC19: =Z19 -> 2
A20: Hong Son DAO | B20: Yes, count me in! | C20: 075200024308 | D20: 0938316793 | E20: No | G20: I’ll take the company bus | I20: Amaris Consulting | J20: Consultants | K20: HO Nguyen Hong Uyen | L20: In | M20: No | N20: 0 | O20: 0 | P20: 0 | Q20: 1 | R20: 1 | S20: 10 | Y20: 17 | Z20: 2 | AC20: =Z20 -> 2
A21: Thanh Son NGUYEN | B21: Yes, count me in! | C21: 051098005098 | D21: 0392497315 | E21: No | G21: I’ll take the company bus | I21: Amaris Consulting | J21: Consultants | K21: HO Nguyen Hong Uyen | L21: In | M21: No | N21: 0 | O21: 0 | P21: 0 | Q21: 1 | R21: 1 | S21: 10 | Y21: 18 | Z21: 2 | AC21: =Z21 -> 2
A22: Thanh Phuoc LE | B22: Yes, count me in! | C22: 068096007001 | D22: 0357556867 | E22: No | G22: I’ll take the company bus | I22: Amaris Consulting | J22: Consultants | K22: HO Nguyen Hong Uyen | L22: In | M22: No | N22: 0 | O22: 0 | P22: 0 | Q22: 1 | R22: 1 | S22: 11 | Y22: 19 | Z22: 2 | AC22: =Z22 -> 2
A23: Le Man Dat NGUYEN | B23: Yes, count me in! | C23: 086200001291 | D23: 0337804259 | E23: No | G23: I’ll take the company bus | I23: Amaris Consulting | J23: Consultants | K23: HO Nguyen Hong Uyen | L23: In | M23: No | N23: 0 | O23: 0 | P23: 0 | Q23: 1 | R23: 1 | S23: 11 | Y23: 20 | Z23: 2 | AC23: =Z23 -> 2
A24: Thanh Loc NGUYEN | B24: Yes, count me in! | C24: 046097000064 | D24: 0333515756 | E24: No | G24: I’ll take the company bus | I24: Amaris Consulting | J24: Consultants | K24: HO Nguyen Hong Uyen | L24: In | M24: No | N24: 0 | O24: 0 | P24: 0 | Q24: 1 | R24: 1 | S24: 12 | Y24: 21 | Z24: 2 | AC24: =Z24 -> 2
A25: Van Thanh Danh KHUAT | B25: Yes, count me in! | C25: 077203004018 | D25: 0971007831 | E25: No | G25: I’ll take the company bus | I25: Amaris Consulting | J25: Consultants | K25: HO Nguyen Hong Uyen | L25: In | M25: No | N25: 0 | O25: 0 | P25: 0 | Q25: 1 | R25: 1 | S25: 12 | Y25: 22 | Z25: 2 | AC25: =Z25 -> 2
A26: Huu Vinh NGUYEN | B26: Yes, count me in! | C26: 089200019968 | D26: 0974086701 | E26: No | G26: I’ll take the company bus | I26: Amaris Consulting | J26: Consultants | K26: HO Nguyen Hong Uyen | L26: In | M26: No | N26: 0 | O26: 0 | P26: 0 | Q26: 1 | R26: 1 | S26: 13 | Y26: 23 | Z26: 2 | AC26: =Z26 -> 2
... A30: Quang Nien NGUYEN | B30: Yes, count me in! | C30: 058201000239 | D30: 0855586358 | E30: No | G30: I’ll take the company bus | I30: Amaris Consulting | J30: Consultants | K30: HO Nguyen Hong Uyen | L30: In | M30: No | N30: 0 | O30: 0 | P30: 0 | Q30: 1 | R30: 1 | S30: 15 | Y30: 27 | Z30: 2 | AC30: =Z30 -> 2
A31: Cong Danh BUI | B31: Yes, count me in! | C31: 079201014939 | D31: 0902891404 | E31: No | G31: I’ll take the company bus | H31: Motion sickness pills | I31: Amaris Consulting | J31: Consultants | K31: NGUYEN Tien Nam | L31: In | M31: No | N31: 0 | O31: 0 | P31: 0 | Q31: 1 | R31: 1 | S31: 15 | Y31: 28 | Z31: 2 | AC31: =Z31 -> 2
A32: Huynh Chi Tin VO | B32: Yes, count me in! | C32: 079095022758 | D32: 0777104166 | E32: No | G32: I’ll take the company bus | I32: Amaris Consulting | J32: Consultants | K32: NGUYEN Tien Nam | L32: In | M32: No | N32: 0 | O32: 0 | P32: 0 | Q32: 1 | R32: 1 | S32: 16 | Y32: 29 | Z32: 2 | AC32: =Z32 -> 2
A33: Quang Trung DO | B33: Yes, count me in! | C33: 064200012749 | D33: 0396402696 | E33: No | G33: I’ll take the company bus | I33: Amaris Consulting | J33: Consultants | K33: NGUYEN Tien Nam | L33: In | M33: No | N33: 0 | O33: 0 | P33: 0 | Q33: 1 | R33: 1 | S33: 16 | Y33: 30 | Z33: 2 | AC33: =Z33 -> 2
A34: Thanh Tai NGUYEN | B34: Yes, count me in! | C34: 051090016586 | D34: 0988383049 | E34: Yes | F34: 1. Nguyen Thu Huyen - Female - 1991 - TBD 2. Nguyen Kha Han - Female - 2017 - TBD | G34: I’ll take the company bus | I34: Amaris Consulting | J34: Consultants | K34: HO Nguyen Hong Uyen | L34: In | M34: Yes | N34: 1 | O34: 1 | P34: 2 | Q34: 3 | R34: 1 | S34: 73 | Y34: 31 | Z34: 2 | AC34: =Z34 -> 2
A35: Nguyen Hong Uyen HO | B35: Yes, count me in! | C35: 079197003545 | D35: 0901936418 | E35: No | G35: I’ll take the company bus | I35: Amaris Consulting | J35: Managers | K35: NGUYEN Thai Ly | L35: In | M35: No | N35: 0 | O35: 0 | P35: 0 | Q35: 1 | R35: 1 | S35: 85 | Y35: 32 | Z35: 2 | AC35: =Z35 -> 2
A36: Phuong Thao HA | B36: Yes, count me in! | C36: 079197023976 | D36: 0909324150 | E36: No | G36: I’ll take the company bus | I36: Amaris Consulting | J36: Managers | K36: NGUYEN Thai Ly | L36: In | M36: No | N36: 0 | O36: 0 | P36: 0 | Q36: 1 | R36: 1 | S36: 88 | Y36: 33 | Z36: 2 | AC36: =Z36 -> 2
A37: Thanh Hang VU | B37: Yes, count me in! | C37: 001188049157 | D37: 0901401929 | E37: No | G37: I’ll take the company bus | I37: Amaris Consulting | J37: Directors | K37: THEVELIN Chloe | L37: In | M37: No | N37: 0 | O37: 0 | P37: 0 | Q37: 1 | R37: 1 | S37: 85 | Y37: 34 | Z37: 2 | AC37: =Z37 -> 2
A38: NGUYEN Tien Nam | B38: Yes, count me in! | C38: 077097008033 | D38: 0979040971 | E38: No | G38: I’ll take the company bus | I38: Amaris Consulting | J38: Managers | K38: NGUYEN Thai Ly | L38: In | M38: No | N38: 0 | O38: 0 | P38: 0 | Q38: 1 | R38: 1 | S38: 90 | Y38: 35 | Z38: 2 | AC38: =Z38 -> 2
A39: Cong Khanh HUYNH | B39: Yes, count me in! | C39: 087201004021 | D39: 0777905219 | E39: No | G39: I’ll take the company bus | I39: Amaris Consulting | J39: Consultants | K39: HUYNH Chi Cuong | L39: In | M39: No | N39: 0 | O39: 0 | P39: 0 | Q39: 1 | R39: 2 | S39: 17 | Y39: 36 | Z39: 2 | AC39: =Z39 -> 2
A40: Ngoc Thanh PHAM | B40: Yes, count me in! | C40: 060094011465 | D40: 0333950268 | E40: No | G40: I’ll take the company bus | I40: Amaris Consulting | J40: Consultants | K40: HUYNH Chi Cuong | L40: In | M40: No | N40: 0 | O40: 0 | P40: 0 | Q40: 1 | R40: 2 | S40: 20 | Y40: 37 | Z40: 2 | AC40: =Z40 -> 2
A41: Xuan Vu TRAN | B41: Yes, count me in! | C41: 046098001181 | D41: 0327360123 | E41: No | G41: I’ll take the company bus | I41: Amaris Consulting | J41: Consultants | K41: HUYNH Chi Cuong | L41: In | M41: No | N41: 0 | O41: 0 | P41: 0 | Q41: 1 | R41: 2 | S41: 20 | Y41: 38 | Z41: 2 | AC41: =Z41 -> 2
A42: Duy Nguyen VO NGOC | B42: Yes, count me in! | C42: 079201007186 | D42: 0919990145 | E42: No | G42: I’ll take the company bus | I42: Amaris Consulting | J42: Consultants | K42: LA Thuy My Hao | L42: In | M42: No | N42: 0 | O42: 0 | P42: 0 | Q42: 1 | R42: 2 | S42: 17 | Y42: 39 | Z42: 2 | AC42: =Z42 -> 2
A43: Chi Hau NGUYEN | B43: Yes, count me in! | C43: 086203010658 | D43: 0799549878 | E43: No | G43: I’ll take the company bus | I43: Amaris Consulting | J43: Consultants | K43: LA Thuy My Hao | L43: In | M43: No | N43: 0 | O43: 0 | P43: 0 | Q43: 1 | R43: 2 | S43: 18 | Y43: 40 | Z43: 2 | AC43: =Z43 -> 2
A44: Dai Duong PHAN | B44: Yes, count me in! | C44: 052201013763 | D44: 0398324011 | E44: No | G44: I’ll take the company bus | I44: Amaris Consulting | J44: Consultants | K44: LA Thuy My Hao | L44: In | M44: No | N44: 0 | O44: 0 | P44: 0 | Q44: 1 | R44: 2 | S44: 18 | Y44: 41 | Z44: 2 | AC44: =Z44 -> 2
A45: Dinh Anh Quoc HOANG | B45: Yes, count me in! | C45: 079202006608 | D45: 0983941396 | E45: No | G45: I’ll take the company bus | I45: Amaris Consulting | J45: Consultants | K45: LA Thuy My Hao | L45: In | M45: No | N45: 0 | O45: 0 | P45: 0 | Q45: 1 | R45: 2 | S45: 19 | Y45: 42 | Z45: 2 | AC45: =Z45 -> 2
A46: Dinh Lam TRAN | B46: Yes, count me in! | C46: 066200002973 | D46: 0769781003 | E46: No | G46: I’ll take the company bus | H46: I have a mild seafood allergy | I46: Amaris Consulting | J46: Consultants | K46: LA Thuy My Hao | L46: In | M46: No | N46: 0 | O46: 0 | P46: 0 | Q46: 1 | R46: 2 | S46: 19 | Y46: 44 | Z46: 2 | AC46: =Z46 -> 2
A47: Nhu Hai Luu PHAN | B47: Yes, count me in! | C47: 060099011492 | D47: 0379738098 | E47: No | G47: I’ll take the company bus | I47: Amaris Consulting | J47: Consultants | K47: LA Thuy My Hao | L47: In | M47: No | N47: 0 | O47: 0 | P47: 0 | Q47: 1 | R47: 2 | S47: 21 | Y47: 45 | Z47: 2 | AC47: =Z47 -> 2
A48: Hoai Sang CAO | B48: Yes, count me in! | C48: 095203009143 | D48: 0944552050 | E48: No | G48: I’ll take the company bus | I48: Amaris Consulting | J48: Consultants | K48: LA Thuy My Hao | L48: In | M48: No | N48: 0 | O48: 0 | P48: 0 | Q48: 1 | R48: 2 | S48: 21 | Y48: 46 | Z48: 2 | AC48: =Z48 -> 2
A49: Huynh Duy Duc NGUYEN | B49: Yes, count me in! | C49: 064201016123 | D49: 0979409417 | E49: No | G49: I’ll take the company bus | I49: Amaris Consulting | J49: Consultants | K49: LA Thuy My Hao | L49: In | M49: No | N49: 0 | O49: 0 | P49: 0 | Q49: 1 | R49: 2 | S49: 22 | Y49: 47 | Z49: 2 | AC49: =Z49 -> 2
A50: Quoc Linh TRAN | B50: Yes, count me in! | C50: 096099005690 | D50: 0379218610 | E50: No | G50: I’ll take the company bus | I50: Amaris Consulting | J50: Consultants | K50: LA Thuy My Hao | L50: In | M50: No | N50: 0 | O50: 0 | P50: 0 | Q50: 1 | R50: 2 | S50: 22 | Y50: 48 | Z50: 2 | AC50: =Z50 -> 2
A51: Van Hao LE | B51: Yes, count me in! | C51: 089097008685 | D51: 0378462578 | E51: No | G51: I’ll take the company bus | I51: Amaris Consulting | J51: Consultants | K51: LA Thuy My Hao | L51: In | M51: No | N51: 0 | O51: 0 | P51: 0 | Q51: 1 | R51: 2 | S51: 23 | Y51: 50 | Z51: 2 | AC51: =Z51 -> 2
A52: Minh Phuoc NGUYEN | B52: Yes, count me in! | C52: 079094018368 | D52: 0937686998 | E52: No | G52: I’ll take the company bus | I52: Amaris Consulting | J52: Consultants | K52: LA Thuy My Hao | L52: In | M52: No | N52: 0 | O52: 0 | P52: 0 | Q52: 1 | R52: 2 | S52: 23 | Y52: 51 | Z52: 2 | AC52: =Z52 -> 2
A53: Duy Nhat NGUYEN | B53: Yes, count me in! | C53: 072200007361 | D53: 0967524457 | E53: No | G53: I’ll take the company bus | I53: Amaris Consulting | J53: Consultants | K53: LA Thuy My Hao | L53: In | M53: No | N53: 0 | O53: 0 | P53: 0 | Q53: 1 | R53: 2 | S53: 24 | Y53: 52 | Z53: 2 | AC53: =Z53 -> 2
A54: Huu Ngan MAI | B54: Yes, count me in! | C54: 049202002958 | D54: 0343734096 | E54: No | G54: I’ll take the company bus | I54: Amaris Consulting | J54: Consultants | K54: LA Thuy My Hao | L54: In | M54: No | N54: 0 | O54: 0 | P54: 0 | Q54: 1 | R54: 2 | S54: 24 | Y54: 53 | Z54: 2 | AC54: =Z54 -> 2
A55: Minh Quan DANG | B55: Yes, count me in! | C55: 089201001783 | D55: 0941967745 | E55: No | G55: I’ll take the company bus | I55: Amaris Consulting | J55: Consultants | K55: LA Thuy My Hao | L55: In | M55: No | N55: 0 | O55: 0 | P55: 0 | Q55: 1 | R55: 2 | S55: 25 | Y55: 54 | Z55: 2 | AC55: =Z55 -> 2
A56: Huu Nghia PHAM | B56: Yes, count me in! | C56: 064098000457 | D56: 0363543388 | E56: No | G56: I’ll take the company bus | I56: Amaris Consulting | J56: Consultants | K56: LA Thuy My Hao | L56: In | M56: No | N56: 0 | O56: 0 | P56: 0 | Q56: 1 | R56: 2 | S56: 25 | Y56: 55 | Z56: 2 | AC56: =Z56 -> 2
A57: Duy Phong NGUYEN | B57: Yes, count me in! | C57: 049200016142 | D57: 0396428796 | E57: No | G57: I’ll take the company bus | I57: Amaris Consulting | J57: Consultants | K57: LA Thuy My Hao | L57: In | M57: No | N57: 0 | O57: 0 | P57: 0 | Q57: 1 | R57: 2 | S57: 26 | Y57: 56 | Z57: 2 | AC57: =Z57 -> 2
A58: Tuan Thanh TRAN | B58: Yes, count me in! | C58: 042200003160 | D58: 0971850315 | E58: No | G58: I’ll take the company bus | I58: Amaris Consulting | J58: Consultants | K58: LA Thuy My Hao | L58: In | M58: No | N58: 0 | O58: 0 | P58: 0 | Q58: 1 | R58: 2 | S58: 26 | Y58: 57 | Z58: 2 | AC58: =Z58 -> 2
... A60: Thanh Duc LE | B60: Yes, count me in! | C60: 079200038775 | D60: 0339310132 | E60: No | G60: I’ll take the company bus | I60: Amaris Consulting | J60: Consultants | K60: LA Thuy My Hao | L60: In | M60: No | N60: 0 | O60: 0 | P60: 0 | Q60: 1 | R60: 2 | S60: 27 | Y60: 59 | Z60: 2 | AC60: =Z60 -> 2
A61: Chi Cuong HUYNH | B61: Yes, count me in! | C61: 079095014706 | D61: 0937251707 | E61: No | G61: I’ll take the company bus | H61: Dị ứng cồn | I61: Amaris Consulting | J61: Consultants | K61: NGUYEN The Trinh | L61: In | M61: No | N61: 0 | O61: 0 | P61: 0 | Q61: 1 | R61: 2 | S61: 30 | Y61: 60 | Z61: 2 | AC61: =Z61 -> 2
A62: Thi Thanh Huong LE | B62: Yes, count me in! | C62: 079302009777 | D62: 0703264721 | E62: No | G62: I’ll take the company bus | I62: Amaris Consulting | J62: Consultants | K62: HUYNH Chi Cuong | L62: In | M62: No | N62: 0 | O62: 0 | P62: 0 | Q62: 1 | R62: 2 | S62: 31 | Y62: 61 | Z62: 2 | AC62: =Z62 -> 2
A63: Tran Nhat Duc NGUYEN | B63: Yes, count me in! | C63: 056200011360 | D63: 0869885812 | E63: No | G63: I’ll take the company bus | I63: Amaris Consulting | J63: Consultants | K63: LA Thuy My Hao | L63: In | M63: No | N63: 0 | O63: 0 | P63: 0 | Q63: 1 | R63: 2 | S63: 28 | Y63: 62 | Z63: 2 | AC63: =Z63 -> 2
A64: Minh Tri DO | B64: Yes, count me in! | C64: minhtri.do@amaris.com | D64: 0935919461 | E64: No | G64: I’ll take the company bus | I64: Amaris Consulting | J64: Consultants | K64: LA Thuy My Hao | L64: In | M64: No | N64: 0 | O64: 0 | P64: 0 | Q64: 1 | R64: 2 | S64: 28 | Y64: 63 | Z64: 2 | AC64: =Z64 -> 2
A65: Tien Manh NGUYEN | B65: Yes, count me in! | C65: 252203000013 | D65: 0829622879 | E65: No | G65: I’ll take the company bus | I65: Amaris Consulting | J65: Consultants | K65: LA Thuy My Hao | L65: In | M65: No | N65: 0 | O65: 0 | P65: 0 | Q65: 1 | R65: 2 | S65: 29 | Y65: 64 | Z65: 2 | AC65: =Z65 -> 2
A66: Quoc Trung KIEU | B66: Yes, count me in! | C66: 079200044816 | D66: 0932535781 | E66: No | G66: I’ll take the company bus | I66: Amaris Consulting | J66: Consultants | K66: LA Thuy My Hao | L66: In | M66: No | N66: 0 | O66: 0 | P66: 0 | Q66: 1 | R66: 2 | S66: 29 | Y66: 65 | Z66: 2 | AC66: =Z66 -> 2
A67: DINH Thanh Viet | B67: Yes, count me in! | C67: 052200005034 | D67: +84 377130331 | E67: No | G67: I’ll take the company bus | I67: Amaris Consulting | J67: Consultants | K67: LA Thuy My Hao | L67: In | M67: No | N67: 0 | O67: 0 | P67: 0 | Q67: 1 | R67: 2 | S67: 30 | Y67: 66 | Z67: 2 | AC67: =Z67 -> 2
A68: Phuong Hang LE THI | B68: Yes, count me in! | C68: 079186021679 | D68: 0866876722 | E68: No | G68: I’ll take the company bus | I68: Amaris Consulting | J68: Consultants | K68: LA Thuy My Hao | L68: In | M68: No | N68: 0 | O68: 0 | P68: 0 | Q68: 1 | R68: 2 | S68: 31 | Y68: 67 | Z68: 2 | AC68: =Z68 -> 2
A69: Thi Tram Ngan TRAN | B69: Yes, count me in! | C69: 087300002383 | D69: 0939053112 | E69: No | G69: I’ll take the company bus | I69: Amaris Consulting | J69: Consultants | K69: LA Thuy My Hao | L69: In | M69: No | N69: 0 | O69: 0 | P69: 0 | Q69: 1 | R69: 2 | S69: 32 | Y69: 68 | Z69: 2 | AC69: =Z69 -> 2
A70: Ngoc My HA | B70: Yes, count me in! | C70: 082300007349 | D70: 0888745255 | E70: No | G70: I’ll take the company bus | I70: Amaris Consulting | J70: Consultants | K70: LA Thuy My Hao | L70: In | M70: No | N70: 0 | O70: 0 | P70: 0 | Q70: 1 | R70: 2 | S70: 32 | Y70: 69 | Z70: 2 | AC70: =Z70 -> 2
A71: Ngoc Thuy Trang PHAM | B71: Yes, count me in! | C71: 079300022868 | D71: 0707653589 | E71: No | G71: I’ll take the company bus | I71: Amaris Consulting | J71: Consultants | K71: LA Thuy My Hao | L71: In | M71: No | N71: 0 | O71: 0 | P71: 0 | Q71: 1 | R71: 2 | S71: 33 | Y71: 78 | Z71: 2 | AC71: =Z71 -> 2
A72: Thai An PHAM THUY | B72: Yes, count me in! | C72: 095304000976 | D72: 0913854054 | E72: No | G72: I’ll take the company bus | I72: Amaris Consulting | J72: Consultants | K72: LA Thuy My Hao | L72: In | M72: No | N72: 0 | O72: 0 | P72: 0 | Q72: 1 | R72: 2 | S72: 33 | Y72: 79 | Z72: 2 | AC72: =Z72 -> 2
A73: Tu Uyen DINH THI | B73: Yes, count me in! | C73: 070302002356 | D73: 0383899275 | E73: No | G73: I’ll take the company bus | I73: Amaris Consulting | J73: Consultants | K73: LA Thuy My Hao | L73: In | M73: No | N73: 0 | O73: 0 | P73: 0 | Q73: 1 | R73: 2 | S73: 34 | Y73: 80 | Z73: 2 | AC73: =Z73 -> 2
... A92: Van Tinh PHAM | B92: Yes, count me in! | C92: 052092015218 | D92: 0346726479 | E92: No | G92: I’ll take the company bus | I92: Amaris Consulting | J92: Consultants | K92: TRAN Thi Ha My | L92: In | M92: No | N92: 0 | O92: 0 | P92: 0 | Q92: 1 | R92: 3 | S92: 42 | Y92: 101 | Z92: 2 | AC92: =Z92 -> 2
A93: Thi Phuong Thao VU | B93: Yes, count me in! | C93: 035198005801 | D93: 0961393725 | E93: Yes | F93: Cao Thi Truc Duyen - Female - 15/06/1997 - 083197002767 | G93: I’ll take the company bus | I93: Amaris Consulting | J93: Consultants | K93: TRAN Thi Ha My | L93: In | M93: Yes | N93: 0 | O93: 1 | P93: 1 | Q93: 2 | R93: 3 | S93: 43 | Y93: 102 | Z93: 2 | AC93: =Z93 -> 2
A94: Thi Nguyet NONG | B94: Yes, count me in! | C94: 091301010042 | D94: 0768811159 | E94: No | G94: I’ll take the company bus | I94: Amaris Consulting | J94: Consultants | K94: NGUYEN Hoang Tuan Anh | L94: In | M94: No | N94: 0 | O94: 0 | P94: 0 | Q94: 1 | R94: 1 | S94: 45 | Y94: 103 | Z94: 2 | AC94: =Z94 -> 2
A95: Thi Viet Trinh NGUYEN | B95: Yes, count me in! | C95: 075193013225 | D95: 0356055190 | E95: No | G95: I’ll take the company bus | I95: Amaris Consulting | J95: Consultants | K95: TRAN Thi Ha My | L95: In | M95: No | N95: 0 | O95: 0 | P95: 0 | Q95: 1 | R95: 3 | S95: 44 | Y95: 104 | Z95: 2 | AC95: =Z95 -> 2
A96: Khanh Gia CHUNG | B96: Yes, count me in! | C96: 079301006935 | D96: 0779911643 | E96: No | G96: I’ll take the company bus | I96: Amaris Consulting | J96: Consultants | K96: TRAN Thi Ha My | L96: In | M96: No | N96: 0 | O96: 0 | P96: 0 | Q96: 1 | R96: 3 | S96: 1 | Y96: 106 | Z96: 2 | AC96: =Z96 -> 2
A97: Ngoc Trang Dai TRAN | B97: Yes, count me in! | C97: 084197000010 | D97: 0936610147 | E97: No | G97: I’ll take the company bus | I97: Amaris Consulting | J97: Consultants | K97: TRAN Thi Ha My | L97: In | M97: No | N97: 0 | O97: 0 | P97: 0 | Q97: 1 | R97: 3 | S97: 61 | Y97: 107 | Z97: 2 | AC97: =Z97 -> 2
A98: Cong Tuan VAN | B98: Yes, count me in! | C98: 052092002529 | D98: 0977794203 | E98: Yes | F98: Nguyen Thi Viet Le - Female - 20/11/1997 - 049197010026 | G98: I’ll take the company bus | I98: Amaris Consulting | J98: Consultants | K98: TRAN Thi Ha My | L98: In | M98: Yes | N98: 0 | O98: 1 | P98: 1 | Q98: 2 | R98: 3 | S98: 71 | Y98: 108 | Z98: 2 | AC98: =Z98 -> 2
A99: Nham Quy TRAN | B99: Yes, count me in! | C99: 052092016286 | D99: 0972326052 | E99: Yes | F99: Lam Vi Phuong - Female - 25/05/1994 - 084194007540 | G99: I’ll take the company bus | I99: Amaris Consulting | J99: Consultants | K99: TRAN Thi Ha My | L99: In | M99: Yes | N99: 0 | O99: 1 | P99: 1 | Q99: 2 | R99: 3 | S99: 72 | Y99: 109 | Z99: 2 | AC99: =Z99 -> 2
A100: Anh Tuan - Tl NGUYEN | B100: Yes, count me in! | C100: 079085007940 | D100: 0878886446 | E100: Yes | F100: 1. TRẦN THỊ KIM THUỶ Ngày sinh: 07/10/1998 CCCD: 079198004873 2. NGUYỄN NGỌC KIM ANH Ngày sinh: 04/09/2022 CCCD: 079322018996 3. NGUYỄN NGỌC TUỆ NHI Ngày sinh: 01/03/2024 CCCD: 079324006070 | G100: I’ll take the company bus | I100: Amaris Consulting | J100: Consultants | K100: TRAN Thi Ha My | L100: In | M100: Yes | N100: 2 | O100: 1 | P100: 3 | Q100: 4 | R100: 3 | S100: 74 | Y100: 110 | Z100: 2 | AC100: =Z100 -> 2
A101: Huy Hoang NGUYEN | B101: Yes, count me in! | C101: 049092003884 | D101: 0975193219 | E101: Yes | F101: 1. Lương Thị Lưu - Female - 06/03/1993 - 040193036578 2. Nguyễn Lương Hoàng Yến - Female - 19/10/2021 - 086321006062 3. Nguyễn Lương Thanh Thảo - Female - 06/03/2024 - 086324001119 | G101: I’ll take the company bus | I101: Amaris Consulting | J101: Consultants | K101: TRAN Thi Ha My | L101: In | M101: Yes | N101: 2 | O101: 1 | P101: 3 | Q101: 4 | R101: 3 | S101: 75 | Y101: 111 | Z101: 2 | AC101: =Z101 -> 2
A102: Cong Quan PHAM | B102: Yes, count me in! | C102: 049095015282 | D102: 0386987100 | E102: Yes | F102: 1. Ung Thụy Song Quỳnh - Female - 11/11/1995 - 049195000151 2. Phạm Công Quang - Male - 26/05/2024 - 049224004390 | G102: I’ll take the company bus | I102: Amaris Consulting | J102: Consultants | K102: TRAN Thi Ha My | L102: In | M102: Yes | N102: 1 | O102: 1 | P102: 2 | Q102: 3 | R102: 3 | S102: 76 | Y102: 112 | Z102: 2 | AC102: =Z102 -> 2
A103: Thi Ha My TRAN | B103: Yes, count me in! | C103: 040195009694 | D103: 0966272279 | E103: No | G103: I’ll take the company bus | I103: Amaris Consulting | J103: Delivery | K103: NGUYEN The Trinh | L103: In | M103: No | N103: 0 | O103: 0 | P103: 0 | Q103: 1 | R103: 3 | S103: 61 | Y103: 113 | Z103: 2 | AC103: =Z103 -> 2
A104: Thanh Trung NGUYEN | B104: Yes, count me in! | C104: 031202004177 | D104: 0886895676 | E104: No | G104: I’ll take the company bus | I104: Amaris Consulting | J104: Consultants | K104: HUYNH Minh Khoi | L104: In | M104: No | N104: 0 | O104: 0 | P104: 0 | Q104: 1 | R104: 4 | S104: 46 | Y104: 114 | Z104: 2 | AC104: =Z104 -> 2
A105: Nguyen Ngoc NGUYEN SY | B105: Yes, count me in! | C105: 079202021638 | D105: 0899337446 | E105: No | G105: I’ll take the company bus | I105: Amaris Consulting | J105: Consultants | K105: HUYNH Minh Khoi | L105: In | M105: No | N105: 0 | O105: 0 | P105: 0 | Q105: 1 | R105: 4 | S105: 46 | Y105: 115 | Z105: 2 | AC105: =Z105 -> 2
A106: Anh Quoc PHAM | B106: Yes, count me in! | C106: 079201003742 | D106: 0896116155 | E106: No | G106: I’ll take the company bus | I106: Amaris Consulting | J106: Consultants | K106: HUYNH Minh Khoi | L106: In | M106: No | N106: 0 | O106: 0 | P106: 0 | Q106: 1 | R106: 4 | S106: 47 | Y106: 116 | Z106: 2 | AC106: =Z106 -> 2
A107: Hai Binh DANG | B107: Yes, count me in! | C107: 031202010766 | D107: 0981412159 | E107: No | G107: I’ll take the company bus | I107: Amaris Consulting | J107: Consultants | K107: HUYNH Minh Khoi | L107: In | M107: No | N107: 0 | O107: 0 | P107: 0 | Q107: 1 | R107: 4 | S107: 47 | Y107: 117 | Z107: 2 | AC107: =Z107 -> 2
A108: Trung Tin THAI | B108: Yes, count me in! | C108: 064201004428 | D108: 0337399029 | E108: No | G108: I’ll take the company bus | I108: Amaris Consulting | J108: Consultants | K108: HUYNH Minh Khoi | L108: In | M108: No | N108: 0 | O108: 0 | P108: 0 | Q108: 1 | R108: 4 | S108: 48 | Y108: 118 | Z108: 2 | AC108: =Z108 -> 2
A109: Nhat DANG MINH | B109: Yes, count me in! | C109: 048203001699 | D109: 0905054228 | E109: No | G109: I’ll take the company bus | I109: Amaris Consulting | J109: Consultants | K109: HUYNH Minh Khoi | L109: In | M109: No | N109: 0 | O109: 0 | P109: 0 | Q109: 1 | R109: 4 | S109: 48 | Y109: 119 | Z109: 2 | AC109: =Z109 -> 2
A110: Trung Kien PHAM | B110: Yes, count me in! | C110: 030098008566 | D110: 0348997157 | E110: Yes | F110: TRẦN DIỆP HUY - 046098011753 - 0766669006 - Male - 07/01/1998 | G110: I’ll take the company bus | I110: Amaris Consulting | J110: Consultants | K110: NGUYEN Duc Quy | L110: In | M110: Yes | N110: 0 | O110: 1 | P110: 1 | Q110: 2 | R110: 4 | S110: 49 | Y110: 122 | Z110: 2 | AC110: =Z110 -> 2
A111: Chien Hao CAO | B111: Yes, count me in! | C111: 066200009584 | D111: 0764290520 | E111: No | G111: I’ll take the company bus | I111: Amaris Consulting | J111: Consultants | K111: NGUYEN Thi Minh Phuong | L111: In | M111: No | N111: 0 | O111: 0 | P111: 0 | Q111: 1 | R111: 4 | S111: 50 | Y111: 123 | Z111: 3 | AC111: =Z111 -> 3
A112: Do Nhat Minh PHAM | B112: Yes, count me in! | C112: 079099034668 | D112: 0906659850 | E112: No | G112: I’ll take the company bus | I112: Amaris Consulting | J112: Consultants | K112: NGUYEN Thi Minh Phuong | L112: In | M112: No | N112: 0 | O112: 0 | P112: 0 | Q112: 1 | R112: 4 | S112: 50 | Y112: 124 | Z112: 2 | AC112: =Z112 -> 2
A113: Duy Hanh LE | B113: Yes, count me in! | C113: 079090028751 | D113: 0937308357 | E113: No | G113: I’ll take the company bus | I113: Amaris Consulting | J113: Consultants | K113: NGUYEN Thi Minh Phuong | L113: In | M113: No | N113: 0 | O113: 0 | P113: 0 | Q113: 1 | R113: 4 | S113: 51 | Y113: 125 | Z113: 2 | AC113: =Z113 -> 2
A114: Huu Thinh NGUYEN | B114: Yes, count me in! | C114: 066096004066 | D114: 0868415847 | E114: No | G114: I’ll take the company bus | I114: Amaris Consulting | J114: Consultants | K114: NGUYEN Thi Minh Phuong | L114: In | M114: No | N114: 0 | O114: 0 | P114: 0 | Q114: 1 | R114: 4 | S114: 51 | Y114: 126 | Z114: 2 | AC114: =Z114 -> 2
A115: Duc Thanh VAN | B115: Yes, count me in! | C115: 079090038513 | D115: 0356154210 | E115: No | G115: I’ll take the company bus | I115: Amaris Consulting | J115: Consultants | K115: NGUYEN Thi Minh Phuong | L115: In | M115: No | N115: 0 | O115: 0 | P115: 0 | Q115: 1 | R115: 4 | S115: 52 | Y115: 127 | Z115: 2 | AC115: =Z115 -> 2
A116: Duan NGUYEN LE | B116: Yes, count me in! | C116: 080096010523 | D116: 0966441600 | E116: No | G116: I’ll take the company bus | I116: Amaris Consulting | J116: Consultants | K116: NGUYEN Thi Minh Phuong | L116: In | M116: No | N116: 0 | O116: 0 | P116: 0 | Q116: 1 | R116: 4 | S116: 52 | Y116: 128 | Z116: 2 | AC116: =Z116 -> 2
A117: Hoang Long NGUYEN | B117: Yes, count me in! | C117: 056098000238 | D117: 0392707949 | E117: No | G117: I’ll take the company bus | I117: Amaris Consulting | J117: Consultants | K117: NGUYEN Thi Minh Phuong | L117: In | M117: No | N117: 0 | O117: 0 | P117: 0 | Q117: 1 | R117: 4 | S117: 53 | Y117: 129 | Z117: 2 | AC117: =Z117 -> 2
A118: Tan Hoang - Bi NGUYEN | B118: Yes, count me in! | C118: 079203011720 | D118: 0938080935 | E118: No | G118: I’ll take the company bus | I118: Amaris Consulting | J118: Consultants | K118: NGUYEN Thi Minh Phuong | L118: In | M118: No | N118: 0 | O118: 0 | P118: 0 | Q118: 1 | R118: 4 | S118: 53 | Y118: 130 | Z118: 2 | AC118: =Z118 -> 2
A119: Thai Hien LUONG | B119: Yes, count me in! | C119: 048087005724 | D119: 0968678149 | E119: No | G119: I’ll take the company bus | I119: Amaris Consulting | J119: Consultants | K119: NGUYEN Duc Quy | L119: In | M119: No | N119: 0 | O119: 0 | P119: 0 | Q119: 1 | R119: 4 | S119: 54 | Y119: 131 | Z119: 2 | AC119: =Z119 -> 2
A120: Van Ket VO | B120: Yes, count me in! | C120: 051091012099 | D120: 0902898110 | E120: No | G120: I’ll take the company bus | I120: Amaris Consulting | J120: Consultants | K120: NGUYEN Duc Quy | L120: In | M120: No | N120: 0 | O120: 0 | P120: 0 | Q120: 1 | R120: 4 | S120: 54 | Y120: 132 | Z120: 2 | AC120: =Z120 -> 2
A121: Vu Phuong NGUYEN | B121: Yes, count me in! | C121: 086096004777 | D121: 0705731919 | E121: No | G121: I’ll take the company bus | I121: Amaris Consulting | J121: Consultants | K121: NGUYEN Duc Quy | L121: In | M121: No | N121: 0 | O121: 0 | P121: 0 | Q121: 1 | R121: 4 | S121: 56 | Y121: 133 | Z121: 2 | AC121: =Z121 -> 2
A122: Hai Thien NGUYEN | B122: Yes, count me in! | C122: 37598 | D122: 0385094422 | E122: No | G122: I’ll take the company bus | I122: Amaris Consulting | J122: Consultants | K122: NGUYEN Thi Minh Phuong | L122: In | M122: No | N122: 0 | O122: 0 | P122: 0 | Q122: 1 | R122: 4 | S122: 56 | Y122: 134 | Z122: 2 | AC122: =Z122 -> 2
...

Sheet Bus
A1: Are you planning to join the company trip? | B1: Yes, count me in! | O1: Gia đình | Q1: 1 xe 45 người | AE1: Are you planning to join the company trip? | AF1: Yes, count me in!
O2: Count
A3: How do you plan to travel to the trip location? | B3: Bus No. | C3: Gov | D3: Dep | E3: N+1 | F3: Name | G3: Sum of C Fam | H3: Sum of A Fam | I3: Sum of Total Hc | J3: Bus No. | K3: Room No, | L3: With Fam | O3: Bus | P3: Current | Q3: Remaining | R3: Note | S3: Bus Leader | T3: Leader Mail | V3: Cong Danh BUI | W3: 902891404 | AE3: Gender | AF3: With Fam | AG3: Room No. | AH3: Gov | AI3: Dep | AJ3: N+1 | AK3: Email | AL3: Name | AM3: Sum of C Fam | AN3: Sum of A Fam | AO3: Sum of Fam Q | AP3: Sum of Total Hc
A4: I’ll arrange my own transportation | B4: (blank) | G4: 1 | H4: 2 | I4: 13 | L4: =IF(E4="",0,IF(I4=1,0.5,1)) -> 0 | O4: 1 | P4: =SUMIFS(I:I,B:B,Table5[[#This Row],[Bus]]) -> 38 | Q4: =45-Table5[[#This Row],[Current]] -> 7 | R4: Uyên + Thảo + | S4: Cong Danh BUI | U4: 1 | V4: congdanh.bui@amaris.com | W4: Cong Danh BUI | X4: 902891404 | AE4: Female | AF4: No | AG4: 1 | AH4: Amaris Consulting | AI4: Consultants | AJ4: HO Nguyen Hong Uyen | AK4: thuytien.phamdo@amaris.com | AL4: Do Thuy Tien PHAM | AM4: 0 | AN4: 0 | AO4: 0 | AP4: 1
A5: I’ll arrange my own transportation Total | G5: 1 | H5: 2 | I5: 13 | L5: =IF(E5="",0,IF(I5=1,0.5,1)) -> 0 | O5: 2 | P5: =SUMIFS(I:I,B:B,Table5[[#This Row],[Bus]]) -> 37 | Q5: =45-Table5[[#This Row],[Current]] -> 8 | R5: Hoang Thien + Huynh Chi cuong + Hao la | S5: Thuy My Hao LA | U5: 2 | V5: hla@amaris.com | W5: Thuy My Hao LA | X5: 375225989 | AE5: Female | AF5: No | AG5: 1 | AH5: Amaris Consulting | AI5: Consultants | AJ5: TRAN Thi Ha My | AK5: khanhgia.chung@amaris.com | AL5: Khanh Gia CHUNG | AM5: 0 | AN5: 0 | AO5: 0 | AP5: 1
A6: I’ll take the company bus | B6: 1 | G6: 1 | H6: 1 | I6: 38 | L6: =IF(E6="",0,IF(I6=1,0.5,1)) -> 0 | O6: 3 | P6: =SUMIFS(I:I,B:B,Table5[[#This Row],[Bus]]) -> 38 | Q6: =45-Table5[[#This Row],[Current]] -> 7 | R6: Nguyen Hoang Tuan Anh + Tran Thi Ha My (1/2) | S6: Van Hieu NGUYEN | U6: 3 | V6: vanhieu.nguyen@amaris.com | W6: Van Hieu NGUYEN | X6: 397459642 | AE6: Female | AF6: No | AG6: 2 | AH6: Amaris Consulting | AI6: Consultants | AJ6: HO Nguyen Hong Uyen | AK6: hoangha.nguyen@amaris.com | AL6: Hoang Ha Quyen NGUYEN | AM6: 0 | AN6: 0 | AO6: 0 | AP6: 1
A7: I’ll take the company bus | B7: 2 | G7: 0 | H7: 0 | I7: 37 | L7: =IF(E7="",0,IF(I7=1,0.5,1)) -> 0 | O7: 4 | P7: =SUMIFS(I:I,B:B,Table5[[#This Row],[Bus]]) -> 37 | Q7: =45-Table5[[#This Row],[Current]] -> 8 | R7: Nguyen Thi Minh Phuong + Tran Thi Ha My + ACT + Hiếu | S7: Thi Minh Phuong NGUYEN | U7: 4 | V7: pnguyen4@amaris.com | W7: Thi Minh Phuong NGUYEN | X7: 945745944 | AE7: Female | AF7: No | AG7: 2 | AH7: Amaris Consulting | AI7: Consultants | AJ7: HO Nguyen Hong Uyen | AK7: thientrang.doan@amaris.com | AL7: Thien Trang DOAN | AM7: 0 | AN7: 0 | AO7: 0 | AP7: 1
A8: I’ll take the company bus | B8: 3 | G8: 5 | H8: 6 | I8: 38 | L8: =IF(E8="",0,IF(I8=1,0.5,1)) -> 0 | O8: 5 | P8: =SUMIFS(I:I,B:B,Table5[[#This Row],[Bus]]) -> 31 | Q8: =45-Table5[[#This Row],[Current]] -> 14 | R8: Finance + CA | S8: Trung Kien NGUYEN | U8: 5 | V8: knguyen8@mantu.com | W8: Trung Kien NGUYEN | X8: 355327017 | AE8: Female | AF8: No | AG8: 31 | AH8: Amaris Consulting | AI8: Consultants | AJ8: HUYNH Chi Cuong | AK8: thithanh.le@amaris.com | AL8: Thi Thanh Huong LE | AM8: 0 | AN8: 0 | AO8: 0 | AP8: 1
A9: I’ll take the company bus | B9: 4 | G9: 0 | H9: 2 | I9: 37 | L9: =IF(E9="",0,IF(I9=1,0.5,1)) -> 0 | O9: 6 | P9: =SUMIFS(I:I,B:B,Table5[[#This Row],[Bus]]) -> 37 | Q9: =45-Table5[[#This Row],[Current]] -> 8 | R9: IT | S9: NGO Trinh Quynh Nhu | U9: 6 | V9: tngo@mantu.com | W9: NGO Trinh Quynh Nhu | X9: 886311686 | AE9: Female | AF9: No | AG9: 31 | AH9: Amaris Consulting | AI9: Consultants | AJ9: LA Thuy My Hao | AK9: phuonghang.lethi@amaris.com | AL9: Phuong Hang LE THI | AM9: 0 | AN9: 0 | AO9: 0 | AP9: 1
A10: I’ll take the company bus | B10: 5 | G10: 0 | H10: 1 | I10: 31 | L10: =IF(E10="",0,IF(I10=1,0.5,1)) -> 0 | O10: 7 | P10: =SUMIFS(I:I,B:B,Table5[[#This Row],[Bus]]) -> 29 | Q10: =45-Table5[[#This Row],[Current]] -> 16 | R10: Xe chờ + Hảo + Ly + HR | S10: Ngoc Quoc TRAN | U10: 7 | V10: tran.ngocquoc@amaris.com | W10: Ngoc Quoc TRAN | X10: 799010869 | AE10: Female | AF10: No | AG10: 32 | AH10: Amaris Consulting | AI10: Consultants | AJ10: LA Thuy My Hao | AK10: ngocmy.ha@amaris.com | AL10: Ngoc My HA | AM10: 0 | AN10: 0 | AO10: 0 | AP10: 1
A11: I’ll take the company bus | B11: 6 | G11: 1 | H11: 1 | I11: 37 | L11: =IF(E11="",0,IF(I11=1,0.5,1)) -> 0 | O11: 8 | P11: =SUMIFS(I:I,B:B,Table5[[#This Row],[Bus]]) -> 34 | Q11: =45-Table5[[#This Row],[Current]] -> 11 | R11: R-Team + Thomas Buc | S11: Diem Thien Nga - Micky HUYNH | U11: 8 | V11: nhuynh@mantu.com | W11: Diem Thien Nga - Micky HUYNH | X11: 763889811 | AE11: Female | AF11: No | AG11: 32 | AH11: Amaris Consulting | AI11: Consultants | AJ11: LA Thuy My Hao | AK11: tramngan.tranthi@amaris.com | AL11: Thi Tram Ngan TRAN | AM11: 0 | AN11: 0 | AO11: 0 | AP11: 1
A12: I’ll take the company bus | B12: 7 | G12: 0 | H12: 0 | I12: 29 | L12: =IF(E12="",0,IF(I12=1,0.5,1)) -> 0 | AE12: Female | AF12: No | AG12: 33 | AH12: Amaris Consulting | AI12: Consultants | AJ12: LA Thuy My Hao | AK12: ngocthuy.pham@amaris.com | AL12: Ngoc Thuy Trang PHAM | AM12: 0 | AN12: 0 | AO12: 0 | AP12: 1
A13: I’ll take the company bus | B13: 8 | C13: ACT | D13: ACT Sales & Pre-sales | E13: MAVANI Amit | F13: Kieu Anh HOANG | G13: 0 | H13: 0 | I13: 1 | L13: =IF(E13="",0,IF(I13=1,0.5,1)) -> 0.5 | AE13: Female | AF13: No | AG13: 33 | AH13: Amaris Consulting | AI13: Consultants | AJ13: LA Thuy My Hao | AK13: thaian.phamthuy@amaris.com | AL13: Thai An PHAM THUY | AM13: 0 | AN13: 0 | AO13: 0 | AP13: 1
A14: I’ll take the company bus | B14: 8 | C14: ACT | D14: ACT Sales & Pre-sales | E14: MAVANI Amit | F14: Triet HUYNH MINH | G14: 0 | H14: 0 | I14: 1 | L14: =IF(E14="",0,IF(I14=1,0.5,1)) -> 0.5 | AE14: Female | AF14: No | AG14: 34 | AH14: Amaris Consulting | AI14: Consultants | AJ14: LA Thuy My Hao | AK14: ngoctran.tathi@amaris.com | AL14: Ngoc Tran TA THI | AM14: 0 | AN14: 0 | AO14: 0 | AP14: 1
A15: I’ll take the company bus | B15: 8 | C15: Administrative & Finance | D15: Operational Finance | E15: DE LACOMBE Romain | F15: Geoffrey DUTERTRE | G15: 0 | H15: 0 | I15: 1 | L15: =IF(E15="",0,IF(I15=1,0.5,1)) -> 0.5 | R15: To update | AE15: Female | AF15: No | AG15: 34 | AH15: Amaris Consulting | AI15: Consultants | AJ15: LA Thuy My Hao | AK15: tuuyen.dinhthi@amaris.com | AL15: Tu Uyen DINH THI | AM15: 0 | AN15: 0 | AO15: 0 | AP15: 1
A16: I’ll take the company bus | B16: 8 | C16: Amaris Consulting | D16: Consultants | E16: VETTUKAD Amit | F16: Phuong Thao NGUYEN | G16: 0 | H16: 0 | I16: 1 | L16: =IF(E16="",0,IF(I16=1,0.5,1)) -> 0.5 | R16: Thai Ly + Tien Nam | S16: 2 Trang + c Phương + a Hoang | AE16: Female | AF16: No | AG16: 44 | AH16: Amaris Consulting | AI16: Consultants | AJ16: TRAN Thi Ha My | AK16: thiviet.nguyen@amaris.com | AL16: Thi Viet Trinh NGUYEN | AM16: 0 | AN16: 0 | AO16: 0 | AP16: 1
A17: I’ll take the company bus | B17: 8 | C17: Amaris Consulting | D17: Consulting Talent Acquisition | E17: GUILLOTON Eve | F17: Ho Khanh Vy NGUYEN | G17: 0 | H17: 0 | I17: 1 | L17: =IF(E17="",0,IF(I17=1,0.5,1)) -> 0.5 | R17: Ha MY + Thao + Uyen | AE17: Female | AF17: No | AG17: 44 | AH17: Amaris Consulting | AI17: Consultants | AJ17: TRAN Thi Ha My | AK17: tranthuy.lu@amaris.com | AL17: Tran Thuy Linh LU | AM17: 0 | AN17: 0 | AO17: 0 | AP17: 1
A18: I’ll take the company bus | B18: 8 | C18: Amaris Consulting | D18: Consulting Talent Acquisition | E18: HONG Nguyen Tu Nhi | F18: Thi Anh Thu TRAN | G18: 0 | H18: 0 | I18: 1 | L18: =IF(E18="",0,IF(I18=1,0.5,1)) -> 0.5 | R18: Hoang Thien + Huynh Chi cuong + Hao la + Tuan Anh | AE18: Female | AF18: No | AG18: 45 | AH18: Amaris Consulting | AI18: Consultants | AJ18: HA Phuong Thao | AK18: phamkhanh.tran@amaris.com | AL18: Pham Khanh Linh TRAN | AM18: 0 | AN18: 0 | AO18: 0 | AP18: 1
A19: I’ll take the company bus | B19: 8 | C19: Amaris Consulting | D19: Consulting Talent Acquisition | E19: NGUYEN Ho Khanh Vy | F19: Dang Thuy Duong NGUYEN | G19: 0 | H19: 0 | I19: 1 | L19: =IF(E19="",0,IF(I19=1,0.5,1)) -> 0.5 | R19: Duc Quy + Minh Phương | AE19: Female | AF19: No | AG19: 45 | AH19: Amaris Consulting | AI19: Consultants | AJ19: NGUYEN Hoang Tuan Anh | AK19: thinguyet.nong@amaris.com | AL19: Thi Nguyet NONG | AM19: 0 | AN19: 0 | AO19: 0 | AP19: 1
A20: I’ll take the company bus | B20: 8 | C20: Amaris Consulting | D20: Consulting Talent Acquisition | E20: NGUYEN Ho Khanh Vy | F20: Hoang Bich Tran NGUYEN | G20: 0 | H20: 1 | I20: 2 | L20: =IF(E20="",0,IF(I20=1,0.5,1)) -> 1 | AE20: Female | AF20: No | AG20: 60 | AH20: Amaris Consulting | AI20: Consultants | AJ20: NGUYEN Thai Ly | AK20: kimanh.do@amaris.com | AL20: Kim Anh DO | AM20: 0 | AN20: 0 | AO20: 0 | AP20: 1
A21: I’ll take the company bus | B21: 8 | C21: Amaris Consulting | D21: Consulting Talent Acquisition | E21: NGUYEN Ho Khanh Vy | F21: Nguyen Tu Nhi HONG | G21: 0 | H21: 0 | I21: 1 | L21: =IF(E21="",0,IF(I21=1,0.5,1)) -> 0.5 | AE21: Female | AF21: No | AG21: 60 | AH21: Amaris Consulting | AI21: Consultants | AJ21: NGUYEN Thi Minh Phuong | AK21: phuong.nguyenthiquynh@amaris.com | AL21: Thi Quynh Phuong NGUYEN | AM21: 0 | AN21: 0 | AO21: 0 | AP21: 1
A22: I’ll take the company bus | B22: 8 | C22: Amaris Consulting | D22: Consulting Talent Acquisition | E22: NGUYEN Ho Khanh Vy | F22: Thai An PHAM | G22: 0 | H22: 1 | I22: 2 | L22: =IF(E22="",0,IF(I22=1,0.5,1)) -> 1 | AE22: Female | AF22: No | AG22: 61 | AH22: Amaris Consulting | AI22: Consultants | AJ22: TRAN Thi Ha My | AK22: qtran5@amaris.com | AL22: Trần Quỳnh Anh | AM22: 0 | AN22: 0 | AO22: 0 | AP22: 1
A23: I’ll take the company bus | B23: 8 | C23: Amaris Consulting | D23: Consulting Talent Acquisition | E23: NGUYEN Hoang Bich Tran | F23: Hoang Dung LE | G23: 0 | H23: 0 | I23: 1 | L23: =IF(E23="",0,IF(I23=1,0.5,1)) -> 0.5 | O23: Bus | P23: Current | Q23: Remaining | R23: Note | AE23: Female | AF23: No | AG23: 61 | AH23: Amaris Consulting | AI23: Delivery | AJ23: NGUYEN The Trinh | AK23: my.tran@amaris.com | AL23: Thi Ha My TRAN | AM23: 0 | AN23: 0 | AO23: 0 | AP23: 1
A24: I’ll take the company bus | B24: 8 | C24: Amaris Consulting | D24: Consulting Talent Acquisition | E24: NGUYEN Hoang Bich Tran | F24: Le Khanh Chi PHAM | G24: 0 | H24: 0 | I24: 1 | L24: =IF(E24="",0,IF(I24=1,0.5,1)) -> 0.5 | O24: 1 | P24: =SUMIFS(I:I,B:B,Table5[[#This Row],[Bus]]) -> 0 | Q24: =45-Table5[[#This Row],[Current]] -> #VALUE! | R24: NGUYEN Thai Ly + HA Phuong Thao + HO Nguyen Hong Uyen + Nguyen Tien Nam | AE24: Female | AF24: No | AG24: 62 | AH24: Amaris Consulting | AI24: Consultants | AJ24: TRAN Thi Ha My | AK24: khanhlinh.dangngoc@amaris.com | AL24: Ngoc Khanh Linh DANG | AM24: 0 | AN24: 0 | AO24: 0 | AP24: 1
A25: I’ll take the company bus | B25: 8 | C25: Amaris Consulting | D25: Consulting Talent Acquisition | E25: NGUYEN Hoang Bich Tran | F25: Tran Thao Vy PHAM | G25: 0 | H25: 0 | I25: 1 | L25: =IF(E25="",0,IF(I25=1,0.5,1)) -> 0.5 | O25: 2 | P25: =SUMIFS(I:I,B:B,Table5[[#This Row],[Bus]]) -> 0 | Q25: =45-Table5[[#This Row],[Current]] -> #VALUE! | R25: Hoang Thien + Huynh Chi cuong + Hao la | AE25: Female | AF25: No | AG25: 62 | AH25: Amaris Consulting | AI25: Consultants | AJ25: TRAN Thi Ha My | AK25: thihue.do@amaris.com | AL25: Thi Hue DO | AM25: 0 | AN25: 0 | AO25: 0 | AP25: 1
A26: I’ll take the company bus | B26: 8 | C26: Amaris Consulting | D26: Consulting Talent Acquisition | E26: PHAM Thai An | F26: Hieu Minh DO | G26: 0 | H26: 0 | I26: 1 | L26: =IF(E26="",0,IF(I26=1,0.5,1)) -> 0.5 | O26: 3 | P26: =SUMIFS(I:I,B:B,Table5[[#This Row],[Bus]]) -> 0 | Q26: =45-Table5[[#This Row],[Current]] -> #VALUE! | R26: Nguyen Hoang Tuan Anh + Tran Thi Ha My (1/2) + Nguyen Tien Nam | AE26: Female | AF26: No | AG26: 68 | AH26: Amaris Consulting | AI26: Managers | AJ26: VU Thanh Hang | AK26: nly@amaris.com | AL26: Thai Ly NGUYEN | AM26: 0 | AN26: 0 | AO26: 0 | AP26: 1
A27: I’ll take the company bus | B27: 8 | C27: Amaris Consulting | D27: Delivery | E27: GALLOT Brice | F27: Trung Hieu NGUYEN | G27: 0 | H27: 0 | I27: 1 | L27: =IF(E27="",0,IF(I27=1,0.5,1)) -> 0.5 | O27: 4 | P27: =SUMIFS(I:I,B:B,Table5[[#This Row],[Bus]]) -> 0 | Q27: =45-Table5[[#This Row],[Current]] -> #VALUE! | R27: Nguyen Thi Minh Phuong + Tran Thi Ha My + Delivery | AE27: Female | AF27: No | AG27: 69 | AH27: Amaris Consulting | AI27: Consultants | AJ27: TRAN Thi Ha My | AK27: baongoc.nguyen@amaris.com | AL27: NGUYEN Bao Ngoc | AM27: 0 | AN27: 0 | AO27: 0 | AP27: 1
A28: I’ll take the company bus | B28: 8 | C28: Amaris Consulting | D28: Delivery | E28: NGUYEN Trung Hieu | F28: Tu NGUYEN ANH | G28: 0 | H28: 0 | I28: 1 | L28: =IF(E28="",0,IF(I28=1,0.5,1)) -> 0.5 | O28: 5 | P28: =SUMIFS(I:I,B:B,Table5[[#This Row],[Bus]]) -> 0 | Q28: =45-Table5[[#This Row],[Current]] -> #VALUE! | R28: Finance + CA | AE28: Female | AF28: No | AG28: 69 | AH28: Amaris Consulting | AI28: Consultants | AJ28: TRAN Thi Ha My | AK28: thikhanh.nguyen@amaris.com | AL28: Thi Khanh NGUYEN | AM28: 0 | AN28: 0 | AO28: 0 | AP28: 1
A29: I’ll take the company bus | B29: 8 | C29: Amaris Consulting | D29: Managers | E29: NGUYEN Thai Ly | F29: NGUYEN Tien Nam | G29: 0 | H29: 0 | I29: 1 | L29: =IF(E29="",0,IF(I29=1,0.5,1)) -> 0.5 | O29: 6 | P29: =SUMIFS(I:I,B:B,Table5[[#This Row],[Bus]]) -> 0 | Q29: =45-Table5[[#This Row],[Current]] -> #VALUE! | R29: IT | AE29: Female | AF29: No | AG29: 82 | AH29: Human Resources | AI29: Payroll Solutions | AJ29: COMAS Mireille | AK29: tle19@mantu.com | AL29: Thi My Tam - Cindy LE | AM29: 0 | AN29: 0 | AO29: 0 | AP29: 1
A30: I’ll take the company bus | B30: 8 | C30: Amaris Consulting | D30: Presales | E30: JOLLIOT Marie-Benoîte | F30: Arthur CAMARET | G30: 0 | H30: 0 | I30: 1 | L30: =IF(E30="",0,IF(I30=1,0.5,1)) -> 0.5 | O30: 7 | P30: =SUMIFS(I:I,B:B,Table5[[#This Row],[Bus]]) -> 0 | Q30: =45-Table5[[#This Row],[Current]] -> #VALUE! | R30: Xe chờ + Duc QUY | AE30: Female | AF30: No | AG30: 82 | AH30: Human Resources | AI30: People Operations | AJ30: NGUYEN Thuc Hao | AK30: nnguyen16@mantu.com | AL30: Le Kim Ngan NGUYEN | AM30: 0 | AN30: 0 | AO30: 0 | AP30: 1
A31: I’ll take the company bus | B31: 8 | C31: Amaris Consulting | D31: Presales | E31: CAMARET Arthur | F31: Clémence LIN | G31: 0 | H31: 0 | I31: 1 | L31: =IF(E31="",0,IF(I31=1,0.5,1)) -> 0.5 | O31: 8 | P31: =SUMIFS(I:I,B:B,Table5[[#This Row],[Bus]]) -> 0 | Q31: =45-Table5[[#This Row],[Current]] -> #VALUE! | R31: R-Team + Thomas Buc + Managers/Directors | AE31: Female | AF31: No | AG31: 83 | AH31: Human Resources | AI31: Compensation & Benefits | AJ31: CAP Kim Hoang | AK31: mdang1@mantu.com | AL31: Minh Thu DANG | AM31: 0 | AN31: 0 | AO31: 0 | AP31: 1
A32: I’ll take the company bus | B32: 8 | C32: Information Technology | D32: Engineering & Architecture | E32: BUZZACARO Alain | F32: Guillaume DUQUESNAY | G32: 0 | H32: 0 | I32: 1 | L32: =IF(E32="",0,IF(I32=1,0.5,1)) -> 0.5 | AE32: Female | AF32: No | AG32: 83 | AH32: Human Resources | AI32: People Operations | AJ32: NGUYEN Thuc Hao | AK32: tdoan2@mantu.com | AL32: Le Bao Tram - Rachel DOAN | AM32: 0 | AN32: 0 | AO32: 0 | AP32: 1
A33: I’ll take the company bus | B33: 8 | C33: Information Technology | D33: Help Desk | E33: NGO Ngoc Nam | F33: Dinh Tien Dung NGUYEN | G33: 0 | H33: 0 | I33: 1 | L33: =IF(E33="",0,IF(I33=1,0.5,1)) -> 0.5 | AE33: Female | AF33: No | AG33: 84 | AH33: Human Resources | AI33: People Analytics | AJ33: NGUYEN Thai Bao | AK33: lnguyenthiquynh@mantu.com | AL33: Thi Quynh Lien NGUYEN | AM33: 0 | AN33: 0 | AO33: 0 | AP33: 1
A34: I’ll take the company bus | B34: 8 | C34: Information Technology | D34: System & Network | E34: SIOUDI Mohamed Amine | F34: Bao An HOANG | G34: 0 | H34: 0 | I34: 1 | L34: =IF(E34="",0,IF(I34=1,0.5,1)) -> 0.5 | AE34: Female | AF34: No | AG34: 84 | AH34: Human Resources | AI34: People Operations | AJ34: RAYNAUD Claire | AK34: bcao@mantu.com | AL34: Bao Tram CAO | AM34: 0 | AN34: 0 | AO34: 0 | AP34: 1
A35: I’ll take the company bus | B35: 8 | C35: Information Technology | D35: Telephony | E35: MAI Tan Ha | F35: Thi Minh Phuong TRAN | G35: 0 | H35: 0 | I35: 1 | L35: =IF(E35="",0,IF(I35=1,0.5,1)) -> 0.5 | AE35: Female | AF35: No | AG35: 85 | AH35: Amaris Consulting | AI35: Directors | AJ35: THEVELIN Chloe | AK35: hvu3@amaris.com | AL35: Thanh Hang VU | AM35: 0 | AN35: 0 | AO35: 0 | AP35: 1
A36: I’ll take the company bus | B36: 8 | C36: Information Technology | D36: Telephony | E36: MAI Tan Ha | F36: Xuan Quang PHAN | G36: 0 | H36: 0 | I36: 1 | L36: =IF(E36="",0,IF(I36=1,0.5,1)) -> 0.5 | AE36: Female | AF36: No | AG36: 85 | AH36: Amaris Consulting | AI36: Managers | AJ36: NGUYEN Thai Ly | AK36: uhonguyenhong@amaris.com | AL36: Nguyen Hong Uyen HO | AM36: 0 | AN36: 0 | AO36: 0 | AP36: 1
A37: I’ll take the company bus | B37: 8 | C37: Information Technology | D37: User Experience | E37: LIM Chee Kiat | F37: Ngoc Nguyen Ngan - Emily NGUYEN | G37: 0 | H37: 0 | I37: 1 | L37: =IF(E37="",0,IF(I37=1,0.5,1)) -> 0.5 | AE37: Female | AF37: No | AG37: 86 | AH37: Amaris Consulting | AI37: Delivery | AJ37: NGUYEN The Trinh | AK37: hla@amaris.com | AL37: Thuy My Hao LA | AM37: 0 | AN37: 0 | AO37: 0 | AP37: 1
A38: I’ll take the company bus | B38: 8 | C38: Marketing & Conversation | D38: Design | E38: SANTANA Zulema | F38: Ho Bao Thy LE | G38: 0 | H38: 0 | I38: 1 | L38: =IF(E38="",0,IF(I38=1,0.5,1)) -> 0.5 | AE38: Female | AF38: No | AG38: 86 | AH38: Amaris Consulting | AI38: Managers | AJ38: NGUYEN Duc Quy | AK38: pnguyen4@amaris.com | AL38: Thi Minh Phuong NGUYEN | AM38: 0 | AN38: 0 | AO38: 0 | AP38: 1
A39: I’ll take the company bus | B39: 8 | C39: Marketing & Conversation | D39: Design | E39: SANTANA Zulema | F39: Tuong Khuyen LE | G39: 0 | H39: 0 | I39: 1 | L39: =IF(E39="",0,IF(I39=1,0.5,1)) -> 0.5 | AE39: Female | AF39: No | AG39: 87 | AH39: Amaris Consulting | AI39: Consultants | AJ39: TRAN Thi Ha My | AK39: ngoctrang.tran@amaris.com | AL39: Ngoc Trang Dai TRAN | AM39: 0 | AN39: 0 | AO39: 0 | AP39: 1
A40: I’ll take the company bus | B40: 8 | C40: Performance Management | D40: Operational Controlling | E40: BUC Thomas | F40: Thi Anh Minh TRAN | G40: 0 | H40: 0 | I40: 1 | L40: =IF(E40="",0,IF(I40=1,0.5,1)) -> 0.5 | AE40: Female | AF40: No | AG40: 87 | AH40: Amaris Consulting | AI40: Delivery | AJ40: VU Thanh Hang | AK40: tnguyen39@amaris.com | AL40: The Trinh NGUYEN | AM40: 0 | AN40: 0 | AO40: 0 | AP40: 1
A41: I’ll take the company bus | B41: 8 | C41: Performance Management | D41: Operational Controlling | E41: BUC Thomas | F41: Thi Thanh Nhan NGUYEN | G41: 0 | H41: 0 | I41: 1 | L41: =IF(E41="",0,IF(I41=1,0.5,1)) -> 0.5 | AE41: Female | AF41: No | AG41: 88 | AH41: Amaris Consulting | AI41: Managers | AJ41: NGUYEN Duc Quy | AK41: lmaianh@amaris.com | AL41: Thi Mai Anh LE | AM41: 0 | AN41: 0 | AO41: 0 | AP41: 1
A42: I’ll take the company bus | B42: 8 | C42: Performance Management | D42: Operational Controlling | E42: BUC Thomas | F42: Thu Hong NGUYEN | G42: 0 | H42: 0 | I42: 1 | L42: =IF(E42="",0,IF(I42=1,0.5,1)) -> 0.5 | AE42: Female | AF42: No | AG42: 88 | AH42: Amaris Consulting | AI42: Managers | AJ42: NGUYEN Thai Ly | AK42: pha1@amaris.com | AL42: Phuong Thao HA | AM42: 0 | AN42: 0 | AO42: 0 | AP42: 1
A43: I’ll take the company bus | B43: 8 | C43: Recruitment | D43: Corporate Acquisition | E43: CARRILLO GIRONA Marina | F43: Linh Chau PHAN | G43: 0 | H43: 0 | I43: 1 | L43: =IF(E43="",0,IF(I43=1,0.5,1)) -> 0.5 | AE43: Female | AF43: No | AG43: 89 | AH43: Amaris Consulting | AI43: Consultants | AJ43: HUYNH Minh Khoi | AK43: kimnha.dao@amaris.com | AL43: Kim Nha DAO | AM43: 0 | AN43: 0 | AO43: 0 | AP43: 1
A44: I’ll take the company bus | B44: 8 | C44: Recruitment | D44: Corporate Acquisition | E44: PHAN Linh Chau | F44: Le Minh Trang NGUYEN | G44: 0 | H44: 0 | I44: 1 | L44: =IF(E44="",0,IF(I44=1,0.5,1)) -> 0.5 | AE44: Female | AF44: No | AG44: 89 | AH44: Amaris Consulting | AI44: Consulting Talent Acquisition | AJ44: PHAM Thai An | AK44: hdo1@amaris.com | AL44: Hieu Minh DO | AM44: 0 | AN44: 0 | AO44: 0 | AP44: 1
A45: I’ll take the company bus Total | G45: 7 | H45: 13 | I45: 281 | L45: =IF(E45="",0,IF(I45=1,0.5,1)) -> 0 | AE45: Female | AF45: No | AG45: 94 | AH45: Administrative & Finance | AI45: Financial Business Controlling | AJ45: PHAN Thi Ha Trang | AK45: cnguyen@mantu.com | AL45: Chau Giang NGUYEN | AM45: 0 | AN45: 0 | AO45: 0 | AP45: 1
A46: Grand Total | G46: 8 | H46: 15 | I46: 294 | L46: =IF(E46="",0,IF(I46=1,0.5,1)) -> 0 | AE46: Female | AF46: No | AG46: 94 | AH46: Administrative & Finance | AI46: Financial Business Controlling | AJ46: RAVAIOLI Filippo | AK46: utrinhlethao@mantu.com | AL46: Uyen TRINH LE THAO | AM46: 0 | AN46: 0 | AO46: 0 | AP46: 1
L47: =IF(E47="",0,IF(I47=1,0.5,1)) -> 0 | AE47: Female | AF47: No | AG47: 95 | AH47: Administrative & Finance | AI47: Financial Business Controlling | AJ47: RAVAIOLI Filippo | AK47: nhoanglamtam@amaris.com | AL47: Lam Tam Nhu HOANG | AM47: 0 | AN47: 0 | AO47: 0 | AP47: 1
L48: =IF(E48="",0,IF(I48=1,0.5,1)) -> 0 | AE48: Female | AF48: No | AG48: 95 | AH48: Administrative & Finance | AI48: Group Accounting | AJ48: NGUYEN Vu Phuong Uyen | AK48: tluong1@mantu.com | AL48: Thi Tram Anh LUONG | AM48: 0 | AN48: 0 | AO48: 0 | AP48: 1
L49: =IF(E49="",0,IF(I49=1,0.5,1)) -> 0 | AE49: Female | AF49: No | AG49: 96 | AH49: Administrative & Finance | AI49: Financial Business Controlling | AJ49: BUI Quang Hung | AK49: tle8@amaris.com | AL49: Thi Tu Quyen LE | AM49: 0 | AN49: 0 | AO49: 0 | AP49: 1
L50: =IF(E50="",0,IF(I50=1,0.5,1)) -> 0 | AE50: Female | AF50: No | AG50: 96 | AH50: Administrative & Finance | AI50: Operational Finance | AJ50: DUTERTRE Geoffrey | AK50: hnguyen6@mantu.com | AL50: Ha Nhi NGUYEN | AM50: 0 | AN50: 0 | AO50: 0 | AP50: 1
L51: =IF(E51="",0,IF(I51=1,0.5,1)) -> 0 | AE51: Female | AF51: No | AG51: 97 | AH51: Administrative & Finance | AI51: Financial Business Controlling | AJ51: BUI Quang Hung | AK51: tnguyen38@amaris.com | AL51: Thi Thanh Thao NGUYEN | AM51: 0 | AN51: 0 | AO51: 0 | AP51: 1
L52: =IF(E52="",0,IF(I52=1,0.5,1)) -> 0 | AE52: Female | AF52: No | AG52: 97 | AH52: Administrative & Finance | AI52: Financial Business Controlling | AJ52: BUI Quang Hung | AK52: tvo4@amaris.com | AL52: Tran Phuong Nga VO | AM52: 0 | AN52: 0 | AO52: 0 | AP52: 1
L53: =IF(E53="",0,IF(I53=1,0.5,1)) -> 0 | AE53: Female | AF53: No | AG53: 98 | AH53: Administrative & Finance | AI53: Financial Business Controlling | AJ53: BUI Quang Hung | AK53: hnguyen13@amaris.com | AL53: Ho Ngoc Tran NGUYEN | AM53: 0 | AN53: 0 | AO53: 0 | AP53: 1
L54: =IF(E54="",0,IF(I54=1,0.5,1)) -> 0 | AE54: Female | AF54: No | AG54: 98 | AH54: Administrative & Finance | AI54: Financial Business Controlling | AJ54: BUI Quang Hung | AK54: hpham1@amaris.com | AL54: Hoang Mai Quyen PHAM | AM54: 0 | AN54: 0 | AO54: 0 | AP54: 1
L55: =IF(E55="",0,IF(I55=1,0.5,1)) -> 0 | AE55: Female | AF55: No | AG55: 99 | AH55: Administrative & Finance | AI55: Group & Corporate Controlling | AJ55: BUI Thi Ngoc Minh | AK55: ptruongthi@amaris.com | AL55: Thi Phuong Thao TRUONG | AM55: 0 | AN55: 0 | AO55: 0 | AP55: 1
L56: =IF(E56="",0,IF(I56=1,0.5,1)) -> 0 | AE56: Female | AF56: No | AG56: 99 | AH56: Administrative & Finance | AI56: Group & Corporate Controlling | AJ56: BUI Thi Ngoc Minh | AK56: qnguyen13@amaris.com | AL56: Quynh Mai NGUYEN | AM56: 0 | AN56: 0 | AO56: 0 | AP56: 1
L57: =IF(E57="",0,IF(I57=1,0.5,1)) -> 0 | AE57: Female | AF57: No | AG57: 100 | AH57: Administrative & Finance | AI57: Group & Corporate Controlling | AJ57: GUÉRET Thomas | AK57: bngocminh@mantu.com | AL57: BUI Thi Ngoc Minh | AM57: 0 | AN57: 0 | AO57: 0 | AP57: 1
L58: =IF(E58="",0,IF(I58=1,0.5,1)) -> 0 | AE58: Female | AF58: No | AG58: 100 | AH58: Administrative & Finance | AI58: Group Accounting | AJ58: PHAM Hoang Phuc | AK58: nphuonguyen@mantu.com | AL58: NGUYEN Vu Phuong Uyen | AM58: 0 | AN58: 0 | AO58: 0 | AP58: 1
... L204: =IF(E204="",0,IF(I204=1,0.5,1)) -> 0 | AE204: Male | AF204: No | AG204: 67 | AH204: Amaris Consulting | AI204: Consultants | AJ204: HOANG Thien | AK204: quangtin.tran@amaris.com | AL204: Quang Tin TRAN | AM204: 0 | AN204: 0 | AO204: 0 | AP204: 1
L205: =IF(E205="",0,IF(I205=1,0.5,1)) -> 0 | AE205: Male | AF205: No | AG205: 67 | AH205: Amaris Consulting | AI205: Consultants | AJ205: HOANG Thien | AK205: tuongduy.vo@amaris.com | AL205: Vo Tuong Duy | AO205: 0 | AP205: 1
L206: =IF(E206="",0,IF(I206=1,0.5,1)) -> 0 | AE206: Male | AF206: No | AG206: 68 | AH206: Amaris Consulting | AI206: Managers | AJ206: VU Thanh Hang | AK206: nducquy@amaris.com | AL206: Duc Quy NGUYEN | AM206: 0 | AN206: 0 | AO206: 0 | AP206: 1
L207: =IF(E207="",0,IF(I207=1,0.5,1)) -> 0 | AE207: Male | AF207: No | AG207: 78 | AH207: Amaris Consulting | AI207: Consultants | AJ207: HOANG Thien | AK207: haithanh.nguyenquoc@amaris.com | AL207: Quoc Hai Thanh NGUYEN | AM207: 0 | AN207: 0 | AO207: 0 | AP207: 1
L208: =IF(E208="",0,IF(I208=1,0.5,1)) -> 0 | AE208: Male | AF208: No | AG208: 78 | AH208: Amaris Consulting | AI208: Consultants | AJ208: LA Thuy My Hao | AK208: quochung.phung@amaris.com | AL208: Quoc Hung PHUNG | AM208: 0 | AN208: 0 | AO208: 0 | AP208: 1
L209: =IF(E209="",0,IF(I209=1,0.5,1)) -> 0 | AE209: Male | AF209: No | AG209: 79 | AH209: Amaris Consulting | AI209: Consultants | AJ209: TRAN Thi Ha My | AK209: tienhuynh.nguyen@amaris.com | AL209: Tien Huynh NGUYEN | AM209: 0 | AN209: 0 | AO209: 0 | AP209: 1
L210: =IF(E210="",0,IF(I210=1,0.5,1)) -> 0 | AE210: Male | AF210: No | AG210: 79 | AH210: Amaris Consulting | AI210: Consultants | AJ210: TRAN Thi Ha My | AK210: tran.ngocquoc@amaris.com | AL210: Ngoc Quoc TRAN | AM210: 0 | AN210: 0 | AO210: 0 | AP210: 1
L211: =IF(E211="",0,IF(I211=1,0.5,1)) -> 0 | AE211: Male | AF211: No | AG211: 80 | AH211: Human Resources | AI211: Compensation & Benefits | AJ211: CAP Kim Hoang | AK211: pvantai@mantu.com | AL211: Van Tai PHAM | AM211: 0 | AN211: 0 | AO211: 0 | AP211: 1
L212: =IF(E212="",0,IF(I212=1,0.5,1)) -> 0 | AE212: Male | AF212: No | AG212: 80 | AH212: Human Resources | AI212: Compensation & Benefits | AJ212: CAP Kim Hoang | AK212: qtran5@mantu.com | AL212: Minh Quang TRAN | AM212: 0 | AN212: 0 | AO212: 0 | AP212: 1
L213: =IF(E213="",0,IF(I213=1,0.5,1)) -> 0 | AE213: Male | AF213: No | AG213: 81 | AH213: Human Resources | AI213: Compensation & Benefits | AJ213: CAP Kim Hoang | AK213: tnguyen10@mantu.com | AL213: Tuan Khoi NGUYEN | AM213: 0 | AN213: 0 | AO213: 0 | AP213: 1
L214: =IF(E214="",0,IF(I214=1,0.5,1)) -> 0 | AE214: Male | AF214: No | AG214: 81 | AH214: Human Resources | AI214: People Operations | AJ214: CAO Bao Tram | AK214: nhao@mantu.com | AL214: Thuc Hao NGUYEN | AM214: 0 | AN214: 0 | AO214: 0 | AP214: 1
L215: =IF(E215="",0,IF(I215=1,0.5,1)) -> 0 | AE215: Male | AF215: No | AG215: 90 | AH215: Amaris Consulting | AI215: Delivery | AJ215: GALLOT Brice | AK215: tnguyen24@amaris.com | AL215: Trung Hieu NGUYEN | AM215: 0 | AN215: 0 | AO215: 0 | AP215: 1
L216: =IF(E216="",0,IF(I216=1,0.5,1)) -> 0 | AE216: Male | AF216: No | AG216: 90 | AH216: Amaris Consulting | AI216: Presales | AJ216: JOLLIOT Marie-Benoîte | AK216: acamaret@amaris.com | AL216: Arthur CAMARET | AM216: 0 | AN216: 0 | AO216: 0 | AP216: 1
L217: =IF(E217="",0,IF(I217=1,0.5,1)) -> 0 | AE217: Male | AF217: No | AG217: 91 | AH217: Amaris Consulting | AI217: Consultants | AJ217: HUYNH Minh Khoi | AK217: duchuy.phamnguyen@amaris.com | AL217: Nguyen Duc Huy PHAM | AM217: 0 | AN217: 0 | AO217: 0 | AP217: 1
... L274: =IF(E274="",0,IF(I274=1,0.5,1)) -> 0 | AE274: Male | AF274: Yes | AG274: 143 | AH274: Information Technology | AI274: Software Architecture | AJ274: MATYSIAK Hervé | AK274: htran1@mantu.com | AL274: Thai Hung TRAN | AM274: 1 | AN274: 1 | AO274: 2 | AP274: 3
L275: =IF(E275="",0,IF(I275=1,0.5,1)) -> 0 | AE275: Grand Total | AM275: 8 | AN275: 15 | AO275: 23 | AP275: 294
L276: =IF(E276="",0,IF(I276=1,0.5,1)) -> 0
L277: =IF(E277="",0,IF(I277=1,0.5,1)) -> 0
L278: =IF(E278="",0,IF(I278=1,0.5,1)) -> 0
L279: =IF(E279="",0,IF(I279=1,0.5,1)) -> 0
L280: =IF(E280="",0,IF(I280=1,0.5,1)) -> 0
L281: =IF(E281="",0,IF(I281=1,0.5,1)) -> 0
L282: =IF(E282="",0,IF(I282=1,0.5,1)) -> 0
L283: =IF(E283="",0,IF(I283=1,0.5,1)) -> 0
L284: =IF(E284="",0,IF(I284=1,0.5,1)) -> 0
L285: =IF(E285="",0,IF(I285=1,0.5,1)) -> 0
L286: =IF(E286="",0,IF(I286=1,0.5,1)) -> 0
L287: =IF(E287="",0,IF(I287=1,0.5,1)) -> 0
L288: =IF(E288="",0,IF(I288=1,0.5,1)) -> 0

Sheet EE
A1: EmployeeId | B1: FullName | C1: Email | D1: ManagerFullName | E1: Governance | F1: Department | G1: EmployeeStatus | H1: Gender
A2: 356 | B2: DUTERTRE Geoffrey | C2: gdutertre@mantu.com | D2: DE LACOMBE Romain | E2: Administrative & Finance | F2: Operational Finance | G2: In | H2: Male
A3: 23365 | B3: NGUYEN Xuan Tu | C3: xnguyen1@mantu.com | D3: MATYSIAK Hervé | E3: Information Technology | F3: Software Architecture | G3: In | H3: Male
A4: 6854 | B4: PHAM Bao Chung | C4: cpham@mantu.com | D4: DUQUESNAY Guillaume | E4: Information Technology | F4: Software Engineering | G4: In | H4: Male
A5: 5540 | B5: TRAN Thai Hung | C5: htran1@mantu.com | D5: MATYSIAK Hervé | E5: Information Technology | F5: Software Architecture | G5: In | H5: Male
A6: 6350 | B6: CAP Kim Hoang | C6: kcap@mantu.com | D6: GIRALT ARRES Sara | E6: Human Resources | F6: Compensation & Benefits | G6: In | H6: Female
A7: 10666 | B7: IVAN Alex Constantin | C7: aivan@mantu.com | D7: DUQUESNAY Guillaume | E7: Information Technology | F7: Software Engineering | G7: In | H7: Male
A8: 15646 | B8: LE Van Khanh | C8: vle2@mantu.com | D8: HUYNH Van Cop | E8: Information Technology | F8: Software Engineering | G8: In | H8: Male
A9: 7616 | B9: NGUYEN Hoang Duy | C9: hnguyen4@mantu.com | D9: HUYNH Van Cop | E9: Information Technology | F9: Software Engineering | G9: In | H9: Male
A10: 8057 | B10: HOANG Vinh Thang | C10: thoang@mantu.com | D10: VALCKE Marine | E10: Information Technology | F10: Digital Workplace | G10: In | H10: Male
A11: 7929 | B11: MATYSIAK Hervé | C11: hmatysiak@mantu.com | D11: BUZZACARO Alain | E11: Information Technology | F11: Software Architecture | G11: In | H11: Male
A12: 9700 | B12: CHAU Phu Qui | C12: pchau@mantu.com | D12: HUYNH Van Cop | E12: Information Technology | F12: Software Engineering | G12: In | H12: Male
A13: 9061 | B13: LUONG Thuan Thanh | C13: tluong@mantu.com | D13: DUQUESNAY Guillaume | E13: Information Technology | F13: Software Engineering | G13: In | H13: Male
... A447: 34261 | B447: VO Thi Ngoc Trong | C447: ngoctrong.vothi@amaris.com | D447: LA Thuy My Hao | E447: Amaris Consulting | F447: Consultants | G447: Out | H447: Female
B448: Trần Quỳnh Anh | C448: qtran5@amaris.com | D448: TRAN Thi Ha My | E448: Amaris Consulting | F448: Consultants | G448: In | H448: Female
B449: Tran Nhat Duc NGUYEN | C449: trannhat.nguyen@amaris.com | D449: LA Thuy My Hao | E449: Amaris Consulting | F449: Consultants | G449: In | H449: Male
B450: Ngô Tấn Thành | C450: tanthanh.ngo@amaris.com | D450: HA Phuong Thao | E450: Amaris Consulting | F450: Consultants | G450: In | H450: Male
B451: Minh Tri DO | C451: minhtri.do@amaris.com | D451: LA Thuy My Hao | E451: Amaris Consulting | F451: Consultants | G451: In | H451: Male
B452: Triet HUYNH MINH | C452: triet.huynhminh@amaris.com | D452: MAVANI Amit | E452: ACT | F452: ACT Sales & Pre-sales | G452: In | H452: Male
B453: Nguyễn Lê Thành | C453: lethanh.nguyen@amaris.com | D453: HA Phuong Thao | E453: Amaris Consulting | F453: Consultants | G453: In | H453: Male
B454: LUONG Thai Hien | C454: thaihien.luong@amaris.com | D454: NGUYEN Duc Quy | E454: Amaris Consulting | F454: Consultants | G454: In | H454: Male
B455: LIN Clémence | C455: clin1@amaris.com | D455: CAMARET Arthur | E455: Amaris Consulting | F455: Presales | G455: In | H455: Female
B456: DO Hoai Trinh | C456: hoaitrinh.do@amaris.com | E456: Amaris Consulting | F456: Consultants
B457: Tien Thuan Hai Luong | C457: tienthuan.luong@amaris.com | D457: HUYNH Minh Khoi | E457: Amaris Consulting | F457: Consultants | G457: In | H457: Male

Sheet Note
A1: Phòng 4 rẻ hơn phòng 2 | B1: Optimize phòng 4 | D1: Yes, count me in! | F1: 1 Phòng 2 ng lớn + con nít dưới 5 | K1: TWN | L1: 01 | M1: =$K$1&L1 -> TWN01 | O1: DBL | P1: 71
A2: Phòng 2 view đẹp | D2: Sorry, I won’t be able to join this time. | F2: Nếu không thì phải extra bed/room | L2: 02 | M2: =$K$1&L2 -> TWN02 | P2: 71
A3: Tăng bonding: Xếp staff với CS nếu có space | L3: 03 | M3: =$K$1&L3 -> TWN03
A4: Nguyen Nhat Anh LE | B4: Không đi | F4: 70% giá phòng | L4: 04 | M4: =$K$1&L4 -> TWN04
F5: 3tr 2tr1 | L5: 05 | M5: =$K$1&L5 -> TWN05
L6: 06 | M6: =$K$1&L6 -> TWN06
L7: 07 | M7: =$K$1&L7 -> TWN07
L8: 08 | M8: =$K$1&L8 -> TWN08
L9: 09 | M9: =$K$1&L9 -> TWN09
L10: 10 | M10: =$K$1&L10 -> TWN10
L11: 11 | M11: =$K$1&L11 -> TWN11
L12: 12 | M12: =$K$1&L12 -> TWN12
L13: 13 | M13: =$K$1&L13 -> TWN13
L14: 14 | M14: =$K$1&L14 -> TWN14
L15: 15 | M15: =$K$1&L15 -> TWN15
L16: 16 | M16: =$K$1&L16 -> TWN16
L17: 17 | M17: =$K$1&L17 -> TWN17
L18: 18 | M18: =$K$1&L18 -> TWN18
L19: 19 | M19: =$K$1&L19 -> TWN19
L20: 20 | M20: =$K$1&L20 -> TWN20
L21: 21 | M21: =$K$1&L21 -> TWN21
... L70: 70 | M70: =$K$1&L70 -> TWN70

Sheet Kids check
A1: Email | B1: Name | C1: If yes, please provide the details for each guest below | D1: C age | H1: Tuổi | I1: Số lượng
A2: nguyen.tai3@amaris.com | B2: Thanh Tai NGUYEN | C2: 1. Nguyen Thu Huyen - Female - 1991 - TBD 2. Nguyen Kha Han - Female - 2017 - TBD | D2: 2017 | H2: 2017 | I2: =COUNTIFS(D:D,H2) -> 1
A3: nguyen.tuananh@amaris.com | B3: Anh Tuan - Tl NGUYEN | C3: 1. TRẦN THỊ KIM THUỶ Ngày sinh: 07/10/1998 CCCD: 079198004873 2. NGUYỄN NGỌC KIM ANH Ngày sinh: 04/09/2022 CCCD: 079322018996 3. NGUYỄN NGỌC TUỆ NHI Ngày sinh: 01/03/2024 CCCD: 079324006070 | D3: 2022 | H3: 2021 | I3: =COUNTIFS(D:D,H3) -> 1
D4: 2024 | H4: 2022 | I4: =COUNTIFS(D:D,H4) -> 1
A5: nhamquy.tran@amaris.com | B5: Nham Quy TRAN | C5: Lam Vi Phuong - Female - 25/05/1994 - 084194007540 | H5: 2023 | I5: =COUNTIFS(D:D,H5) -> 1
A6: nguyen.huyhoang@amaris.com | B6: Huy Hoang NGUYEN | C6: 1. Lương Thị Lưu - Female - 06/03/1993 - 040193036578 2. Nguyễn Lương Hoàng Yến - Female - 19/10/2021 - 086321006062 3. Nguyễn Lương Thanh Thảo - Female - 06/03/2024 - 086324001119 | D6: 2021 | H6: 2024 | I6: =COUNTIFS(D:D,H6) -> 3
D7: 2024 | H7: 2025 | I7: =COUNTIFS(D:D,H7) -> 1
A8: congquan.pham@amaris.com | B8: Cong Quan PHAM | C8: 1. Ung Thụy Song Quỳnh - Female - 11/11/1995 - 049195000151 2. Phạm Công Quang - Male - 26/05/2024 - 049224004390 | D8: 2024 | H8: Total | I8: =SUM(I2:I7) -> 8
A9: thiphuong.vu@amaris.com | B9: Thi Phuong Thao VU | C9: Cao Thi Truc Duyen - Female - 15/06/1997 - 083197002767
A10: tuan.vancong@amaris.com | B10: Cong Tuan VAN | C10: Nguyen Thi Viet Le - Female - 20/11/1997 - 049197010026
A11: nhattan.tranhuynh@amaris.com | B11: Huynh Nhat Tan TRAN | C11: Nguyễn Thị Bích Duyên - Female - 05/08/1995
A12: pham.trungkien@amaris.com | B12: Trung Kien PHAM | C12: TRẦN DIỆP HUY - 046098011753 - 0766669006 - Male - 07/01/1998
A13: qdiep@mantu.com | B13: Tue Quan DIEP | C13: Nguyen The Anh - Male - 21/07/2000 - 040200000125
A14: htran1@mantu.com | B14: Thai Hung TRAN | C14: 1. Lưu Hồng Phương Thủy - Female - 27/10/1990 - 06619007476 2. Trần Hồng Như Ý - Female - 13/7/2025 - 079325017288 | D14: 2025
A15: tnguyen56@amaris.com | B15: Hoang Bich Tran NGUYEN | C15: Nguyen Tran Bao Phu - Male - 28/03/1999 - 080099002154
A16: pthaian@amaris.com | B16: Thai An PHAM | C16: Do Chi Thanh - Male - 20/10/2002 - 001202005933
A17: aphan1@mantu.com | B17: Anh Dung Cuong PHAN | C17: 1. Truong Ngoc Tinh Anh - 10/12/1993 - 060193015462 2. Phan Nhat Thien Dang - 28/11/2023 - 079223047176 | D17: 2023
A18: huuphuc.le@amaris.com | B18: Huu Phuc LE | C18: Hồ Thị Minh Hoàng- Female-19/11/1984-046184001362

Sheet Data4Hotel
A1: Email | B1: ID | C1: Họ & Tên | D1: CCCD
A2: phamkhanh.tran@amaris.com | B2: =_xlfn.XLOOKUP(A2,[1]employees!$E:$E,[1]employees!$B:$B) -> 35385 | C2: TRẦN PHẠM KHÁNH LINH
A3: thuytien.phamdo@amaris.com | B3: =_xlfn.XLOOKUP(A3,[1]employees!$E:$E,[1]employees!$B:$B) -> 20350 | C3: PHẠM ĐỖ THỦY TIÊN
A4: hoangha.nguyen@amaris.com | B4: =_xlfn.XLOOKUP(A4,[1]employees!$E:$E,[1]employees!$B:$B) -> 34275 | C4: NGUYỄN HOÀNG HẠ QUYÊN
A5: thientrang.doan@amaris.com | B5: =_xlfn.XLOOKUP(A5,[1]employees!$E:$E,[1]employees!$B:$B) -> 33490 | C5: ĐOÀN THIÊN TRANG
A6: uhonguyenhong@amaris.com | B6: =_xlfn.XLOOKUP(A6,[1]employees!$E:$E,[1]employees!$B:$B) -> 29186 | C6: HỒ NGUYỄN HỒNG UYÊN
A7: pha1@amaris.com | B7: =_xlfn.XLOOKUP(A7,[1]employees!$E:$E,[1]employees!$B:$B) -> 30105 | C7: HÀ PHƯƠNG THẢO
A8: hvu3@amaris.com | B8: =_xlfn.XLOOKUP(A8,[1]employees!$E:$E,[1]employees!$B:$B) -> 10902 | C8: VŨ THANH HẰNG
A9: cao.minh@amaris.com | B9: =_xlfn.XLOOKUP(A9,[1]employees!$E:$E,[1]employees!$B:$B) -> 35979 | C9: CAO ĐỨC MINH
A10: hoangtu.la@amaris.com | B10: =_xlfn.XLOOKUP(A10,[1]employees!$E:$E,[1]employees!$B:$B) -> 27174 | C10: LA HOÀNG TÚ
A11: trungnghia.cao@amaris.com | B11: =_xlfn.XLOOKUP(A11,[1]employees!$E:$E,[1]employees!$B:$B) -> 31982 | C11: CAO TRUNG NGHĨA
A12: minhthuan.le@amaris.com | B12: =_xlfn.XLOOKUP(A12,[1]employees!$E:$E,[1]employees!$B:$B) -> 37058 | C12: LÊ MINH THUẬN
A13: thanhthuan.nguyenvan@amaris.com | B13: =_xlfn.XLOOKUP(A13,[1]employees!$E:$E,[1]employees!$B:$B) -> 21983 | C13: NGUYỄN VĂN THANH THUẬN
... A272: quochung.phung@amaris.com | B272: =_xlfn.XLOOKUP(A272,[1]employees!$E:$E,[1]employees!$B:$B) -> 36242 | C272: PHÙNG QUỐC HÙNG
